Workbook

Sheet Revenue & gross margin
A1: Revenue & gross margin
A2: Revenue & Margin · Main Scenario
A4: Variable / dimension | B4: 2026-10 | C4: 2026-11 | D4: 2026-12 | E4: 2027-01 | F4: 2027-02 | G4: 2027-03 | H4: 2027-04 | I4: 2027-05 | J4: 2027-06 | K4: 2027-07 | L4: 2027-08 | M4: 2027-09 | N4: 2027-10 | O4: 2027-11 | P4: 2027-12 | Q4: 2028-01 | R4: 2028-02 | S4: 2028-03 | T4: 2028-04 | U4: 2028-05 | V4: 2028-06 | W4: 2028-07 | X4: 2028-08 | Y4: 2028-09
A5: Months since launch | B5: =IF(IF(IF(ISERROR(DATE(2026,10,1)<DATE(YEAR('Model inputs'!B8),MONTH('Model inputs'!B8),1)),DATE(2026,10,1)<DATE(YEAR('Model inputs'!B8),MONTH('Model inputs'!B8),1),IF(DATE(YEAR('Model inputs'!B8),MONTH('Model inputs'!B8),1)="","",DATE(2026,10,1)<DATE(YEAR('Model inputs'!B8),MONTH('Model inputs'!B8),1)))="",FALSE,IF(ISERROR(DATE(2026,10,1)<DATE(YEAR('Model inputs'!B8),MONTH('Model inputs'!B8),1)),DATE(2026,10,1)<DATE(YEAR('Model inputs'!B8),MONTH('Model inputs'!B8),1),IF(DATE(YEAR('Model inputs'!B8),MONTH('Model inputs'!B8),1)="","",DATE(2026,10,1)<DATE(YEAR('Model inputs'!B8),MONTH('Model inputs'!B8),1)))),0,IFERROR(DATEDIF(DATE(YEAR('Model inputs'!B8),MONTH('Model inputs'!B8),1),DATE(2026,10,1),"M"),0)+1) -> 0 | C5: =IF(IF(IF(ISERROR(DATE(2026,11,1)<DATE(YEAR('Model inputs'!B8),MONTH('Model inputs'!B8),1)),DATE(2026,11,1)<DATE(YEAR('Model inputs'!B8),MONTH('Model inputs'!B8),1),IF(DATE(YEAR('Model inputs'!B8),MONTH('Model inputs'!B8),1)="","",DATE(2026,11,1)<DATE(YEAR('Model inputs'!B8),MONTH('Model inputs'!B8),1)))="",FALSE,IF(ISERROR(DATE(2026,11,1)<DATE(YEAR('Model inputs'!B8),MONTH('Model inputs'!B8),1)),DATE(2026,11,1)<DATE(YEAR('Model inputs'!B8),MONTH('Model inputs'!B8),1),IF(DATE(YEAR('Model inputs'!B8),MONTH('Model inputs'!B8),1)="","",DATE(2026,11,1)<DATE(YEAR('Model inputs'!B8),MONTH('Model inputs'!B8),1)))),0,IFERROR(DATEDIF(DATE(YEAR('Model inputs'!B8),MONTH('Model inputs'!B8),1),DATE(2026,11,1),"M"),0)+1) -> 1 | D5: =IF(IF(IF(ISERROR(DATE(2026,12,1)<DATE(YEAR('Model inputs'!B8),MONTH('Model inputs'!B8),1)),DATE(2026,12,1)<DATE(YEAR('Model inputs'!B8),MONTH('Model inputs'!B8),1),IF(DATE(YEAR('Model inputs'!B8),MONTH('Model inputs'!B8),1)="","",DATE(2026,12,1)<DATE(YEAR('Model inputs'!B8),MONTH('Model inputs'!B8),1)))="",FALSE,IF(ISERROR(DATE(2026,12,1)<DATE(YEAR('Model inputs'!B8),MONTH('Model inputs'!B8),1)),DATE(2026,12,1)<DATE(YEAR('Model inputs'!B8),MONTH('Model inputs'!B8),1),IF(DATE(YEAR('Model inputs'!B8),MONTH('Model inputs'!B8),1)="","",DATE(2026,12,1)<DATE(YEAR('Model inputs'!B8),MONTH('Model inputs'!B8),1)))),0,IFERROR(DATEDIF(DATE(YEAR('Model inputs'!B8),MONTH('Model inputs'!B8),1),DATE(2026,12,1),"M"),0)+1) -> 2 | E5: =IF(IF(IF(ISERROR(DATE(2027,1,1)<DATE(YEAR('Model inputs'!B8),MONTH('Model inputs'!B8),1)),DATE(2027,1,1)<DATE(YEAR('Model inputs'!B8),MONTH('Model inputs'!B8),1),IF(DATE(YEAR('Model inputs'!B8),MONTH('Model inputs'!B8),1)="","",DATE(2027,1,1)<DATE(YEAR('Model inputs'!B8),MONTH('Model inputs'!B8),1)))="",FALSE,IF(ISERROR(DATE(2027,1,1)<DATE(YEAR('Model inputs'!B8),MONTH('Model inputs'!B8),1)),DATE(2027,1,1)<DATE(YEAR('Model inputs'!B8),MONTH('Model inputs'!B8),1),IF(DATE(YEAR('Model inputs'!B8),MONTH('Model inputs'!B8),1)="","",DATE(2027,1,1)<DATE(YEAR('Model inputs'!B8),MONTH('Model inputs'!B8),1)))),0,IFERROR(DATEDIF(DATE(YEAR('Model inputs'!B8),MONTH('Model inputs'!B8),1),DATE(2027,1,1),"M"),0)+1) -> 3 | F5: =IF(IF(IF(ISERROR(DATE(2027,2,1)<DATE(YEAR('Model inputs'!B8),MONTH('Model inputs'!B8),1)),DATE(2027,2,1)<DATE(YEAR('Model inputs'!B8),MONTH('Model inputs'!B8),1),IF(DATE(YEAR('Model inputs'!B8),MONTH('Model inputs'!B8),1)="","",DATE(2027,2,1)<DATE(YEAR('Model inputs'!B8),MONTH('Model inputs'!B8),1)))="",FALSE,IF(ISERROR(DATE(2027,2,1)<DATE(YEAR('Model inputs'!B8),MONTH('Model inputs'!B8),1)),DATE(2027,2,1)<DATE(YEAR('Model inputs'!B8),MONTH('Model inputs'!B8),1),IF(DATE(YEAR('Model inputs'!B8),MONTH('Model inputs'!B8),1)="","",DATE(2027,2,1)<DATE(YEAR('Model inputs'!B8),MONTH('Model inputs'!B8),1)))),0,IFERROR(DATEDIF(DATE(YEAR('Model inputs'!B8),MONTH('Model inputs'!B8),1),DATE(2027,2,1),"M"),0)+1) -> 4 | G5: =IF(IF(IF(ISERROR(DATE(2027,3,1)<DATE(YEAR('Model inputs'!B8),MONTH('Model inputs'!B8),1)),DATE(2027,3,1)<DATE(YEAR('Model inputs'!B8),MONTH('Model inputs'!B8),1),IF(DATE(YEAR('Model inputs'!B8),MONTH('Model inputs'!B8),1)="","",DATE(2027,3,1)<DATE(YEAR('Model inputs'!B8),MONTH('Model inputs'!B8),1)))="",FALSE,IF(ISERROR(DATE(2027,3,1)<DATE(YEAR('Model inputs'!B8),MONTH('Model inputs'!B8),1)),DATE(2027,3,1)<DATE(YEAR('Model inputs'!B8),MONTH('Model inputs'!B8),1),IF(DATE(YEAR('Model inputs'!B8),MONTH('Model inputs'!B8),1)="","",DATE(2027,3,1)<DATE(YEAR('Model inputs'!B8),MONTH('Model inputs'!B8),1)))),0,IFERROR(DATEDIF(DATE(YEAR('Model inputs'!B8),MONTH('Model inputs'!B8),1),DATE(2027,3,1),"M"),0)+1) -> 5 | H5: =IF(IF(IF(ISERROR(DATE(2027,4,1)<DATE(YEAR('Model inputs'!B8),MONTH('Model inputs'!B8),1)),DATE(2027,4,1)<DATE(YEAR('Model inputs'!B8),MONTH('Model inputs'!B8),1),IF(DATE(YEAR('Model inputs'!B8),MONTH('Model inputs'!B8),1)="","",DATE(2027,4,1)<DATE(YEAR('Model inputs'!B8),MONTH('Model inputs'!B8),1)))="",FALSE,IF(ISERROR(DATE(2027,4,1)<DATE(YEAR('Model inputs'!B8),MONTH('Model inputs'!B8),1)),DATE(2027,4,1)<DATE(YEAR('Model inputs'!B8),MONTH('Model inputs'!B8),1),IF(DATE(YEAR('Model inputs'!B8),MONTH('Model inputs'!B8),1)="","",DATE(2027,4,1)<DATE(YEAR('Model inputs'!B8),MONTH('Model inputs'!B8),1)))),0,IFERROR(DATEDIF(DATE(YEAR('Model inputs'!B8),MONTH('Model inputs'!B8),1),DATE(2027,4,1),"M"),0)+1) -> 6 | I5: =IF(IF(IF(ISERROR(DATE(2027,5,1)<DATE(YEAR('Model inputs'!B8),MONTH('Model inputs'!B8),1)),DATE(2027,5,1)<DATE(YEAR('Model inputs'!B8),MONTH('Model inputs'!B8),1),IF(DATE(YEAR('Model inputs'!B8),MONTH('Model inputs'!B8),1)="","",DATE(2027,5,1)<DATE(YEAR('Model inputs'!B8),MONTH('Model inputs'!B8),1)))="",FALSE,IF(ISERROR(DATE(2027,5,1)<DATE(YEAR('Model inputs'!B8),MONTH('Model inputs'!B8),1)),DATE(2027,5,1)<DATE(YEAR('Model inputs'!B8),MONTH('Model inputs'!B8),1),IF(DATE(YEAR('Model inputs'!B8),MONTH('Model inputs'!B8),1)="","",DATE(2027,5,1)<DATE(YEAR('Model inputs'!B8),MONTH('Model inputs'!B8),1)))),0,IFERROR(DATEDIF(DATE(YEAR('Model inputs'!B8),MONTH('Model inputs'!B8),1),DATE(2027,5,1),"M"),0)+1) -> 7 | J5: =IF(IF(IF(ISERROR(DATE(2027,6,1)<DATE(YEAR('Model inputs'!B8),MONTH('Model inputs'!B8),1)),DATE(2027,6,1)<DATE(YEAR('Model inputs'!B8),MONTH('Model inputs'!B8),1),IF(DATE(YEAR('Model inputs'!B8),MONTH('Model inputs'!B8),1)="","",DATE(2027,6,1)<DATE(YEAR('Model inputs'!B8),MONTH('Model inputs'!B8),1)))="",FALSE,IF(ISERROR(DATE(2027,6,1)<DATE(YEAR('Model inputs'!B8),MONTH('Model inputs'!B8),1)),DATE(2027,6,1)<DATE(YEAR('Model inputs'!B8),MONTH('Model inputs'!B8),1),IF(DATE(YEAR('Model inputs'!B8),MONTH('Model inputs'!B8),1)="","",DATE(2027,6,1)<DATE(YEAR('Model inputs'!B8),MONTH('Model inputs'!B8),1)))),0,IFERROR(DATEDIF(DATE(YEAR('Model inputs'!B8),MONTH('Model inputs'!B8),1),DATE(2027,6,1),"M"),0)+1) -> 8 | K5: =IF(IF(IF(ISERROR(DATE(2027,7,1)<DATE(YEAR('Model inputs'!B8),MONTH('Model inputs'!B8),1)),DATE(2027,7,1)<DATE(YEAR('Model inputs'!B8),MONTH('Model inputs'!B8),1),IF(DATE(YEAR('Model inputs'!B8),MONTH('Model inputs'!B8),1)="","",DATE(2027,7,1)<DATE(YEAR('Model inputs'!B8),MONTH('Model inputs'!B8),1)))="",FALSE,IF(ISERROR(DATE(2027,7,1)<DATE(YEAR('Model inputs'!B8),MONTH('Model inputs'!B8),1)),DATE(2027,7,1)<DATE(YEAR('Model inputs'!B8),MONTH('Model inputs'!B8),1),IF(DATE(YEAR('Model inputs'!B8),MONTH('Model inputs'!B8),1)="","",DATE(2027,7,1)<DATE(YEAR('Model inputs'!B8),MONTH('Model inputs'!B8),1)))),0,IFERROR(DATEDIF(DATE(YEAR('Model inputs'!B8),MONTH('Model inputs'!B8),1),DATE(2027,7,1),"M"),0)+1) -> 9 | L5: =IF(IF(IF(ISERROR(DATE(2027,8,1)<DATE(YEAR('Model inputs'!B8),MONTH('Model inputs'!B8),1)),DATE(2027,8,1)<DATE(YEAR('Model inputs'!B8),MONTH('Model inputs'!B8),1),IF(DATE(YEAR('Model inputs'!B8),MONTH('Model inputs'!B8),1)="","",DATE(2027,8,1)<DATE(YEAR('Model inputs'!B8),MONTH('Model inputs'!B8),1)))="",FALSE,IF(ISERROR(DATE(2027,8,1)<DATE(YEAR('Model inputs'!B8),MONTH('Model inputs'!B8),1)),DATE(2027,8,1)<DATE(YEAR('Model inputs'!B8),MONTH('Model inputs'!B8),1),IF(DATE(YEAR('Model inputs'!B8),MONTH('Model inputs'!B8),1)="","",DATE(2027,8,1)<DATE(YEAR('Model inputs'!B8),MONTH('Model inputs'!B8),1)))),0,IFERROR(DATEDIF(DATE(YEAR('Model inputs'!B8),MONTH('Model inputs'!B8),1),DATE(2027,8,1),"M"),0)+1) -> 10 | M5: =IF(IF(IF(ISERROR(DATE(2027,9,1)<DATE(YEAR('Model inputs'!B8),MONTH('Model inputs'!B8),1)),DATE(2027,9,1)<DATE(YEAR('Model inputs'!B8),MONTH('Model inputs'!B8),1),IF(DATE(YEAR('Model inputs'!B8),MONTH('Model inputs'!B8),1)="","",DATE(2027,9,1)<DATE(YEAR('Model inputs'!B8),MONTH('Model inputs'!B8),1)))="",FALSE,IF(ISERROR(DATE(2027,9,1)<DATE(YEAR('Model inputs'!B8),MONTH('Model inputs'!B8),1)),DATE(2027,9,1)<DATE(YEAR('Model inputs'!B8),MONTH('Model inputs'!B8),1),IF(DATE(YEAR('Model inputs'!B8),MONTH('Model inputs'!B8),1)="","",DATE(2027,9,1)<DATE(YEAR('Model inputs'!B8),MONTH('Model inputs'!B8),1)))),0,IFERROR(DATEDIF(DATE(YEAR('Model inputs'!B8),MONTH('Model inputs'!B8),1),DATE(2027,9,1),"M"),0)+1) -> 11 | N5: =IF(IF(IF(ISERROR(DATE(2027,10,1)<DATE(YEAR('Model inputs'!B8),MONTH('Model inputs'!B8),1)),DATE(2027,10,1)<DATE(YEAR('Model inputs'!B8),MONTH('Model inputs'!B8),1),IF(DATE(YEAR('Model inputs'!B8),MONTH('Model inputs'!B8),1)="","",DATE(2027,10,1)<DATE(YEAR('Model inputs'!B8),MONTH('Model inputs'!B8),1)))="",FALSE,IF(ISERROR(DATE(2027,10,1)<DATE(YEAR('Model inputs'!B8),MONTH('Model inputs'!B8),1)),DATE(2027,10,1)<DATE(YEAR('Model inputs'!B8),MONTH('Model inputs'!B8),1),IF(DATE(YEAR('Model inputs'!B8),MONTH('Model inputs'!B8),1)="","",DATE(2027,10,1)<DATE(YEAR('Model inputs'!B8),MONTH('Model inputs'!B8),1)))),0,IFERROR(DATEDIF(DATE(YEAR('Model inputs'!B8),MONTH('Model inputs'!B8),1),DATE(2027,10,1),"M"),0)+1) -> 12 | O5: =IF(IF(IF(ISERROR(DATE(2027,11,1)<DATE(YEAR('Model inputs'!B8),MONTH('Model inputs'!B8),1)),DATE(2027,11,1)<DATE(YEAR('Model inputs'!B8),MONTH('Model inputs'!B8),1),IF(DATE(YEAR('Model inputs'!B8),MONTH('Model inputs'!B8),1)="","",DATE(2027,11,1)<DATE(YEAR('Model inputs'!B8),MONTH('Model inputs'!B8),1)))="",FALSE,IF(ISERROR(DATE(2027,11,1)<DATE(YEAR('Model inputs'!B8),MONTH('Model inputs'!B8),1)),DATE(2027,11,1)<DATE(YEAR('Model inputs'!B8),MONTH('Model inputs'!B8),1),IF(DATE(YEAR('Model inputs'!B8),MONTH('Model inputs'!B8),1)="","",DATE(2027,11,1)<DATE(YEAR('Model inputs'!B8),MONTH('Model inputs'!B8),1)))),0,IFERROR(DATEDIF(DATE(YEAR('Model inputs'!B8),MONTH('Model inputs'!B8),1),DATE(2027,11,1),"M"),0)+1) -> 13 | P5: =IF(IF(IF(ISERROR(DATE(2027,12,1)<DATE(YEAR('Model inputs'!B8),MONTH('Model inputs'!B8),1)),DATE(2027,12,1)<DATE(YEAR('Model inputs'!B8),MONTH('Model inputs'!B8),1),IF(DATE(YEAR('Model inputs'!B8),MONTH('Model inputs'!B8),1)="","",DATE(2027,12,1)<DATE(YEAR('Model inputs'!B8),MONTH('Model inputs'!B8),1)))="",FALSE,IF(ISERROR(DATE(2027,12,1)<DATE(YEAR('Model inputs'!B8),MONTH('Model inputs'!B8),1)),DATE(2027,12,1)<DATE(YEAR('Model inputs'!B8),MONTH('Model inputs'!B8),1),IF(DATE(YEAR('Model inputs'!B8),MONTH('Model inputs'!B8),1)="","",DATE(2027,12,1)<DATE(YEAR('Model inputs'!B8),MONTH('Model inputs'!B8),1)))),0,IFERROR(DATEDIF(DATE(YEAR('Model inputs'!B8),MONTH('Model inputs'!B8),1),DATE(2027,12,1),"M"),0)+1) -> 14 | Q5: =IF(IF(IF(ISERROR(DATE(2028,1,1)<DATE(YEAR('Model inputs'!B8),MONTH('Model inputs'!B8),1)),DATE(2028,1,1)<DATE(YEAR('Model inputs'!B8),MONTH('Model inputs'!B8),1),IF(DATE(YEAR('Model inputs'!B8),MONTH('Model inputs'!B8),1)="","",DATE(2028,1,1)<DATE(YEAR('Model inputs'!B8),MONTH('Model inputs'!B8),1)))="",FALSE,IF(ISERROR(DATE(2028,1,1)<DATE(YEAR('Model inputs'!B8),MONTH('Model inputs'!B8),1)),DATE(2028,1,1)<DATE(YEAR('Model inputs'!B8),MONTH('Model inputs'!B8),1),IF(DATE(YEAR('Model inputs'!B8),MONTH('Model inputs'!B8),1)="","",DATE(2028,1,1)<DATE(YEAR('Model inputs'!B8),MONTH('Model inputs'!B8),1)))),0,IFERROR(DATEDIF(DATE(YEAR('Model inputs'!B8),MONTH('Model inputs'!B8),1),DATE(2028,1,1),"M"),0)+1) -> 15 | R5: =IF(IF(IF(ISERROR(DATE(2028,2,1)<DATE(YEAR('Model inputs'!B8),MONTH('Model inputs'!B8),1)),DATE(2028,2,1)<DATE(YEAR('Model inputs'!B8),MONTH('Model inputs'!B8),1),IF(DATE(YEAR('Model inputs'!B8),MONTH('Model inputs'!B8),1)="","",DATE(2028,2,1)<DATE(YEAR('Model inputs'!B8),MONTH('Model inputs'!B8),1)))="",FALSE,IF(ISERROR(DATE(2028,2,1)<DATE(YEAR('Model inputs'!B8),MONTH('Model inputs'!B8),1)),DATE(2028,2,1)<DATE(YEAR('Model inputs'!B8),MONTH('Model inputs'!B8),1),IF(DATE(YEAR('Model inputs'!B8),MONTH('Model inputs'!B8),1)="","",DATE(2028,2,1)<DATE(YEAR('Model inputs'!B8),MONTH('Model inputs'!B8),1)))),0,IFERROR(DATEDIF(DATE(YEAR('Model inputs'!B8),MONTH('Model inputs'!B8),1),DATE(2028,2,1),"M"),0)+1) -> 16 | S5: =IF(IF(IF(ISERROR(DATE(2028,3,1)<DATE(YEAR('Model inputs'!B8),MONTH('Model inputs'!B8),1)),DATE(2028,3,1)<DATE(YEAR('Model inputs'!B8),MONTH('Model inputs'!B8),1),IF(DATE(YEAR('Model inputs'!B8),MONTH('Model inputs'!B8),1)="","",DATE(2028,3,1)<DATE(YEAR('Model inputs'!B8),MONTH('Model inputs'!B8),1)))="",FALSE,IF(ISERROR(DATE(2028,3,1)<DATE(YEAR('Model inputs'!B8),MONTH('Model inputs'!B8),1)),DATE(2028,3,1)<DATE(YEAR('Model inputs'!B8),MONTH('Model inputs'!B8),1),IF(DATE(YEAR('Model inputs'!B8),MONTH('Model inputs'!B8),1)="","",DATE(2028,3,1)<DATE(YEAR('Model inputs'!B8),MONTH('Model inputs'!B8),1)))),0,IFERROR(DATEDIF(DATE(YEAR('Model inputs'!B8),MONTH('Model inputs'!B8),1),DATE(2028,3,1),"M"),0)+1) -> 17 | T5: =IF(IF(IF(ISERROR(DATE(2028,4,1)<DATE(YEAR('Model inputs'!B8),MONTH('Model inputs'!B8),1)),DATE(2028,4,1)<DATE(YEAR('Model inputs'!B8),MONTH('Model inputs'!B8),1),IF(DATE(YEAR('Model inputs'!B8),MONTH('Model inputs'!B8),1)="","",DATE(2028,4,1)<DATE(YEAR('Model inputs'!B8),MONTH('Model inputs'!B8),1)))="",FALSE,IF(ISERROR(DATE(2028,4,1)<DATE(YEAR('Model inputs'!B8),MONTH('Model inputs'!B8),1)),DATE(2028,4,1)<DATE(YEAR('Model inputs'!B8),MONTH('Model inputs'!B8),1),IF(DATE(YEAR('Model inputs'!B8),MONTH('Model inputs'!B8),1)="","",DATE(2028,4,1)<DATE(YEAR('Model inputs'!B8),MONTH('Model inputs'!B8),1)))),0,IFERROR(DATEDIF(DATE(YEAR('Model inputs'!B8),MONTH('Model inputs'!B8),1),DATE(2028,4,1),"M"),0)+1) -> 18 | U5: =IF(IF(IF(ISERROR(DATE(2028,5,1)<DATE(YEAR('Model inputs'!B8),MONTH('Model inputs'!B8),1)),DATE(2028,5,1)<DATE(YEAR('Model inputs'!B8),MONTH('Model inputs'!B8),1),IF(DATE(YEAR('Model inputs'!B8),MONTH('Model inputs'!B8),1)="","",DATE(2028,5,1)<DATE(YEAR('Model inputs'!B8),MONTH('Model inputs'!B8),1)))="",FALSE,IF(ISERROR(DATE(2028,5,1)<DATE(YEAR('Model inputs'!B8),MONTH('Model inputs'!B8),1)),DATE(2028,5,1)<DATE(YEAR('Model inputs'!B8),MONTH('Model inputs'!B8),1),IF(DATE(YEAR('Model inputs'!B8),MONTH('Model inputs'!B8),1)="","",DATE(2028,5,1)<DATE(YEAR('Model inputs'!B8),MONTH('Model inputs'!B8),1)))),0,IFERROR(DATEDIF(DATE(YEAR('Model inputs'!B8),MONTH('Model inputs'!B8),1),DATE(2028,5,1),"M"),0)+1) -> 19 | V5: =IF(IF(IF(ISERROR(DATE(2028,6,1)<DATE(YEAR('Model inputs'!B8),MONTH('Model inputs'!B8),1)),DATE(2028,6,1)<DATE(YEAR('Model inputs'!B8),MONTH('Model inputs'!B8),1),IF(DATE(YEAR('Model inputs'!B8),MONTH('Model inputs'!B8),1)="","",DATE(2028,6,1)<DATE(YEAR('Model inputs'!B8),MONTH('Model inputs'!B8),1)))="",FALSE,IF(ISERROR(DATE(2028,6,1)<DATE(YEAR('Model inputs'!B8),MONTH('Model inputs'!B8),1)),DATE(2028,6,1)<DATE(YEAR('Model inputs'!B8),MONTH('Model inputs'!B8),1),IF(DATE(YEAR('Model inputs'!B8),MONTH('Model inputs'!B8),1)="","",DATE(2028,6,1)<DATE(YEAR('Model inputs'!B8),MONTH('Model inputs'!B8),1)))),0,IFERROR(DATEDIF(DATE(YEAR('Model inputs'!B8),MONTH('Model inputs'!B8),1),DATE(2028,6,1),"M"),0)+1) -> 20 | W5: =IF(IF(IF(ISERROR(DATE(2028,7,1)<DATE(YEAR('Model inputs'!B8),MONTH('Model inputs'!B8),1)),DATE(2028,7,1)<DATE(YEAR('Model inputs'!B8),MONTH('Model inputs'!B8),1),IF(DATE(YEAR('Model inputs'!B8),MONTH('Model inputs'!B8),1)="","",DATE(2028,7,1)<DATE(YEAR('Model inputs'!B8),MONTH('Model inputs'!B8),1)))="",FALSE,IF(ISERROR(DATE(2028,7,1)<DATE(YEAR('Model inputs'!B8),MONTH('Model inputs'!B8),1)),DATE(2028,7,1)<DATE(YEAR('Model inputs'!B8),MONTH('Model inputs'!B8),1),IF(DATE(YEAR('Model inputs'!B8),MONTH('Model inputs'!B8),1)="","",DATE(2028,7,1)<DATE(YEAR('Model inputs'!B8),MONTH('Model inputs'!B8),1)))),0,IFERROR(DATEDIF(DATE(YEAR('Model inputs'!B8),MONTH('Model inputs'!B8),1),DATE(2028,7,1),"M"),0)+1) -> 21 | X5: =IF(IF(IF(ISERROR(DATE(2028,8,1)<DATE(YEAR('Model inputs'!B8),MONTH('Model inputs'!B8),1)),DATE(2028,8,1)<DATE(YEAR('Model inputs'!B8),MONTH('Model inputs'!B8),1),IF(DATE(YEAR('Model inputs'!B8),MONTH('Model inputs'!B8),1)="","",DATE(2028,8,1)<DATE(YEAR('Model inputs'!B8),MONTH('Model inputs'!B8),1)))="",FALSE,IF(ISERROR(DATE(2028,8,1)<DATE(YEAR('Model inputs'!B8),MONTH('Model inputs'!B8),1)),DATE(2028,8,1)<DATE(YEAR('Model inputs'!B8),MONTH('Model inputs'!B8),1),IF(DATE(YEAR('Model inputs'!B8),MONTH('Model inputs'!B8),1)="","",DATE(2028,8,1)<DATE(YEAR('Model inputs'!B8),MONTH('Model inputs'!B8),1)))),0,IFERROR(DATEDIF(DATE(YEAR('Model inputs'!B8),MONTH('Model inputs'!B8),1),DATE(2028,8,1),"M"),0)+1) -> 22 | Y5: =IF(IF(IF(ISERROR(DATE(2028,9,1)<DATE(YEAR('Model inputs'!B8),MONTH('Model inputs'!B8),1)),DATE(2028,9,1)<DATE(YEAR('Model inputs'!B8),MONTH('Model inputs'!B8),1),IF(DATE(YEAR('Model inputs'!B8),MONTH('Model inputs'!B8),1)="","",DATE(2028,9,1)<DATE(YEAR('Model inputs'!B8),MONTH('Model inputs'!B8),1)))="",FALSE,IF(ISERROR(DATE(2028,9,1)<DATE(YEAR('Model inputs'!B8),MONTH('Model inputs'!B8),1)),DATE(2028,9,1)<DATE(YEAR('Model inputs'!B8),MONTH('Model inputs'!B8),1),IF(DATE(YEAR('Model inputs'!B8),MONTH('Model inputs'!B8),1)="","",DATE(2028,9,1)<DATE(YEAR('Model inputs'!B8),MONTH('Model inputs'!B8),1)))),0,IFERROR(DATEDIF(DATE(YEAR('Model inputs'!B8),MONTH('Model inputs'!B8),1),DATE(2028,9,1),"M"),0)+1) -> 23
A6: Jobs attempted | B6: =IF(IF(IF(ISERROR('Revenue & gross margin'!B5<1),'Revenue & gross margin'!B5<1,IF('Revenue & gross margin'!B5="","",'Revenue & gross margin'!B5<1))="",FALSE,IF(ISERROR('Revenue & gross margin'!B5<1),'Revenue & gross margin'!B5<1,IF('Revenue & gross margin'!B5="","",'Revenue & gross margin'!B5<1))),0,'Model inputs'!B9*IF(AND((1+'Model inputs'!B10)=0,(MIN('Revenue & gross margin'!B5,'Model inputs'!B7)-1)=0),SQRT(-1),(1+'Model inputs'!B10)^(MIN('Revenue & gross margin'!B5,'Model inputs'!B7)-1))*'Model inputs'!B14) -> 0 | C6: =IF(IF(IF(ISERROR('Revenue & gross margin'!C5<1),'Revenue & gross margin'!C5<1,IF('Revenue & gross margin'!C5="","",'Revenue & gross margin'!C5<1))="",FALSE,IF(ISERROR('Revenue & gross margin'!C5<1),'Revenue & gross margin'!C5<1,IF('Revenue & gross margin'!C5="","",'Revenue & gross margin'!C5<1))),0,'Model inputs'!B9*IF(AND((1+'Model inputs'!B10)=0,(MIN('Revenue & gross margin'!C5,'Model inputs'!B7)-1)=0),SQRT(-1),(1+'Model inputs'!B10)^(MIN('Revenue & gross margin'!C5,'Model inputs'!B7)-1))*'Model inputs'!B14) -> 1000 | D6: =IF(IF(IF(ISERROR('Revenue & gross margin'!D5<1),'Revenue & gross margin'!D5<1,IF('Revenue & gross margin'!D5="","",'Revenue & gross margin'!D5<1))="",FALSE,IF(ISERROR('Revenue & gross margin'!D5<1),'Revenue & gross margin'!D5<1,IF('Revenue & gross margin'!D5="","",'Revenue & gross margin'!D5<1))),0,'Model inputs'!B9*IF(AND((1+'Model inputs'!B10)=0,(MIN('Revenue & gross margin'!D5,'Model inputs'!B7)-1)=0),SQRT(-1),(1+'Model inputs'!B10)^(MIN('Revenue & gross margin'!D5,'Model inputs'!B7)-1))*'Model inputs'!B14) -> 1000 | E6: =IF(IF(IF(ISERROR('Revenue & gross margin'!E5<1),'Revenue & gross margin'!E5<1,IF('Revenue & gross margin'!E5="","",'Revenue & gross margin'!E5<1))="",FALSE,IF(ISERROR('Revenue & gross margin'!E5<1),'Revenue & gross margin'!E5<1,IF('Revenue & gross margin'!E5="","",'Revenue & gross margin'!E5<1))),0,'Model inputs'!B9*IF(AND((1+'Model inputs'!B10)=0,(MIN('Revenue & gross margin'!E5,'Model inputs'!B7)-1)=0),SQRT(-1),(1+'Model inputs'!B10)^(MIN('Revenue & gross margin'!E5,'Model inputs'!B7)-1))*'Model inputs'!B14) -> 1000 | F6: =IF(IF(IF(ISERROR('Revenue & gross margin'!F5<1),'Revenue & gross margin'!F5<1,IF('Revenue & gross margin'!F5="","",'Revenue & gross margin'!F5<1))="",FALSE,IF(ISERROR('Revenue & gross margin'!F5<1),'Revenue & gross margin'!F5<1,IF('Revenue & gross margin'!F5="","",'Revenue & gross margin'!F5<1))),0,'Model inputs'!B9*IF(AND((1+'Model inputs'!B10)=0,(MIN('Revenue & gross margin'!F5,'Model inputs'!B7)-1)=0),SQRT(-1),(1+'Model inputs'!B10)^(MIN('Revenue & gross margin'!F5,'Model inputs'!B7)-1))*'Model inputs'!B14) -> 1000 | G6: =IF(IF(IF(ISERROR('Revenue & gross margin'!G5<1),'Revenue & gross margin'!G5<1,IF('Revenue & gross margin'!G5="","",'Revenue & gross margin'!G5<1))="",FALSE,IF(ISERROR('Revenue & gross margin'!G5<1),'Revenue & gross margin'!G5<1,IF('Revenue & gross margin'!G5="","",'Revenue & gross margin'!G5<1))),0,'Model inputs'!B9*IF(AND((1+'Model inputs'!B10)=0,(MIN('Revenue & gross margin'!G5,'Model inputs'!B7)-1)=0),SQRT(-1),(1+'Model inputs'!B10)^(MIN('Revenue & gross margin'!G5,'Model inputs'!B7)-1))*'Model inputs'!B14) -> 1000 | H6: =IF(IF(IF(ISERROR('Revenue & gross margin'!H5<1),'Revenue & gross margin'!H5<1,IF('Revenue & gross margin'!H5="","",'Revenue & gross margin'!H5<1))="",FALSE,IF(ISERROR('Revenue & gross margin'!H5<1),'Revenue & gross margin'!H5<1,IF('Revenue & gross margin'!H5="","",'Revenue & gross margin'!H5<1))),0,'Model inputs'!B9*IF(AND((1+'Model inputs'!B10)=0,(MIN('Revenue & gross margin'!H5,'Model inputs'!B7)-1)=0),SQRT(-1),(1+'Model inputs'!B10)^(MIN('Revenue & gross margin'!H5,'Model inputs'!B7)-1))*'Model inputs'!B14) -> 1000 | I6: =IF(IF(IF(ISERROR('Revenue & gross margin'!I5<1),'Revenue & gross margin'!I5<1,IF('Revenue & gross margin'!I5="","",'Revenue & gross margin'!I5<1))="",FALSE,IF(ISERROR('Revenue & gross margin'!I5<1),'Revenue & gross margin'!I5<1,IF('Revenue & gross margin'!I5="","",'Revenue & gross margin'!I5<1))),0,'Model inputs'!B9*IF(AND((1+'Model inputs'!B10)=0,(MIN('Revenue & gross margin'!I5,'Model inputs'!B7)-1)=0),SQRT(-1),(1+'Model inputs'!B10)^(MIN('Revenue & gross margin'!I5,'Model inputs'!B7)-1))*'Model inputs'!B14) -> 1000 | J6: =IF(IF(IF(ISERROR('Revenue & gross margin'!J5<1),'Revenue & gross margin'!J5<1,IF('Revenue & gross margin'!J5="","",'Revenue & gross margin'!J5<1))="",FALSE,IF(ISERROR('Revenue & gross margin'!J5<1),'Revenue & gross margin'!J5<1,IF('Revenue & gross margin'!J5="","",'Revenue & gross margin'!J5<1))),0,'Model inputs'!B9*IF(AND((1+'Model inputs'!B10)=0,(MIN('Revenue & gross margin'!J5,'Model inputs'!B7)-1)=0),SQRT(-1),(1+'Model inputs'!B10)^(MIN('Revenue & gross margin'!J5,'Model inputs'!B7)-1))*'Model inputs'!B14) -> 1000 | K6: =IF(IF(IF(ISERROR('Revenue & gross margin'!K5<1),'Revenue & gross margin'!K5<1,IF('Revenue & gross margin'!K5="","",'Revenue & gross margin'!K5<1))="",FALSE,IF(ISERROR('Revenue & gross margin'!K5<1),'Revenue & gross margin'!K5<1,IF('Revenue & gross margin'!K5="","",'Revenue & gross margin'!K5<1))),0,'Model inputs'!B9*IF(AND((1+'Model inputs'!B10)=0,(MIN('Revenue & gross margin'!K5,'Model inputs'!B7)-1)=0),SQRT(-1),(1+'Model inputs'!B10)^(MIN('Revenue & gross margin'!K5,'Model inputs'!B7)-1))*'Model inputs'!B14) -> 1000 | L6: =IF(IF(IF(ISERROR('Revenue & gross margin'!L5<1),'Revenue & gross margin'!L5<1,IF('Revenue & gross margin'!L5="","",'Revenue & gross margin'!L5<1))="",FALSE,IF(ISERROR('Revenue & gross margin'!L5<1),'Revenue & gross margin'!L5<1,IF('Revenue & gross margin'!L5="","",'Revenue & gross margin'!L5<1))),0,'Model inputs'!B9*IF(AND((1+'Model inputs'!B10)=0,(MIN('Revenue & gross margin'!L5,'Model inputs'!B7)-1)=0),SQRT(-1),(1+'Model inputs'!B10)^(MIN('Revenue & gross margin'!L5,'Model inputs'!B7)-1))*'Model inputs'!B14) -> 1000 | M6: =IF(IF(IF(ISERROR('Revenue & gross margin'!M5<1),'Revenue & gross margin'!M5<1,IF('Revenue & gross margin'!M5="","",'Revenue & gross margin'!M5<1))="",FALSE,IF(ISERROR('Revenue & gross margin'!M5<1),'Revenue & gross margin'!M5<1,IF('Revenue & gross margin'!M5="","",'Revenue & gross margin'!M5<1))),0,'Model inputs'!B9*IF(AND((1+'Model inputs'!B10)=0,(MIN('Revenue & gross margin'!M5,'Model inputs'!B7)-1)=0),SQRT(-1),(1+'Model inputs'!B10)^(MIN('Revenue & gross margin'!M5,'Model inputs'!B7)-1))*'Model inputs'!B14) -> 1000 | N6: =IF(IF(IF(ISERROR('Revenue & gross margin'!N5<1),'Revenue & gross margin'!N5<1,IF('Revenue & gross margin'!N5="","",'Revenue & gross margin'!N5<1))="",FALSE,IF(ISERROR('Revenue & gross margin'!N5<1),'Revenue & gross margin'!N5<1,IF('Revenue & gross margin'!N5="","",'Revenue & gross margin'!N5<1))),0,'Model inputs'!B9*IF(AND((1+'Model inputs'!B10)=0,(MIN('Revenue & gross margin'!N5,'Model inputs'!B7)-1)=0),SQRT(-1),(1+'Model inputs'!B10)^(MIN('Revenue & gross margin'!N5,'Model inputs'!B7)-1))*'Model inputs'!B14) -> 1000 | O6: =IF(IF(IF(ISERROR('Revenue & gross margin'!O5<1),'Revenue & gross margin'!O5<1,IF('Revenue & gross margin'!O5="","",'Revenue & gross margin'!O5<1))="",FALSE,IF(ISERROR('Revenue & gross margin'!O5<1),'Revenue & gross margin'!O5<1,IF('Revenue & gross margin'!O5="","",'Revenue & gross margin'!O5<1))),0,'Model inputs'!B9*IF(AND((1+'Model inputs'!B10)=0,(MIN('Revenue & gross margin'!O5,'Model inputs'!B7)-1)=0),SQRT(-1),(1+'Model inputs'!B10)^(MIN('Revenue & gross margin'!O5,'Model inputs'!B7)-1))*'Model inputs'!B14) -> 1000 | P6: =IF(IF(IF(ISERROR('Revenue & gross margin'!P5<1),'Revenue & gross margin'!P5<1,IF('Revenue & gross margin'!P5="","",'Revenue & gross margin'!P5<1))="",FALSE,IF(ISERROR('Revenue & gross margin'!P5<1),'Revenue & gross margin'!P5<1,IF('Revenue & gross margin'!P5="","",'Revenue & gross margin'!P5<1))),0,'Model inputs'!B9*IF(AND((1+'Model inputs'!B10)=0,(MIN('Revenue & gross margin'!P5,'Model inputs'!B7)-1)=0),SQRT(-1),(1+'Model inputs'!B10)^(MIN('Revenue & gross margin'!P5,'Model inputs'!B7)-1))*'Model inputs'!B14) -> 1000 | Q6: =IF(IF(IF(ISERROR('Revenue & gross margin'!Q5<1),'Revenue & gross margin'!Q5<1,IF('Revenue & gross margin'!Q5="","",'Revenue & gross margin'!Q5<1))="",FALSE,IF(ISERROR('Revenue & gross margin'!Q5<1),'Revenue & gross margin'!Q5<1,IF('Revenue & gross margin'!Q5="","",'Revenue & gross margin'!Q5<1))),0,'Model inputs'!B9*IF(AND((1+'Model inputs'!B10)=0,(MIN('Revenue & gross margin'!Q5,'Model inputs'!B7)-1)=0),SQRT(-1),(1+'Model inputs'!B10)^(MIN('Revenue & gross margin'!Q5,'Model inputs'!B7)-1))*'Model inputs'!B14) -> 1000 | R6: =IF(IF(IF(ISERROR('Revenue & gross margin'!R5<1),'Revenue & gross margin'!R5<1,IF('Revenue & gross margin'!R5="","",'Revenue & gross margin'!R5<1))="",FALSE,IF(ISERROR('Revenue & gross margin'!R5<1),'Revenue & gross margin'!R5<1,IF('Revenue & gross margin'!R5="","",'Revenue & gross margin'!R5<1))),0,'Model inputs'!B9*IF(AND((1+'Model inputs'!B10)=0,(MIN('Revenue & gross margin'!R5,'Model inputs'!B7)-1)=0),SQRT(-1),(1+'Model inputs'!B10)^(MIN('Revenue & gross margin'!R5,'Model inputs'!B7)-1))*'Model inputs'!B14) -> 1000 | S6: =IF(IF(IF(ISERROR('Revenue & gross margin'!S5<1),'Revenue & gross margin'!S5<1,IF('Revenue & gross margin'!S5="","",'Revenue & gross margin'!S5<1))="",FALSE,IF(ISERROR('Revenue & gross margin'!S5<1),'Revenue & gross margin'!S5<1,IF('Revenue & gross margin'!S5="","",'Revenue & gross margin'!S5<1))),0,'Model inputs'!B9*IF(AND((1+'Model inputs'!B10)=0,(MIN('Revenue & gross margin'!S5,'Model inputs'!B7)-1)=0),SQRT(-1),(1+'Model inputs'!B10)^(MIN('Revenue & gross margin'!S5,'Model inputs'!B7)-1))*'Model inputs'!B14) -> 1000 | T6: =IF(IF(IF(ISERROR('Revenue & gross margin'!T5<1),'Revenue & gross margin'!T5<1,IF('Revenue & gross margin'!T5="","",'Revenue & gross margin'!T5<1))="",FALSE,IF(ISERROR('Revenue & gross margin'!T5<1),'Revenue & gross margin'!T5<1,IF('Revenue & gross margin'!T5="","",'Revenue & gross margin'!T5<1))),0,'Model inputs'!B9*IF(AND((1+'Model inputs'!B10)=0,(MIN('Revenue & gross margin'!T5,'Model inputs'!B7)-1)=0),SQRT(-1),(1+'Model inputs'!B10)^(MIN('Revenue & gross margin'!T5,'Model inputs'!B7)-1))*'Model inputs'!B14) -> 1000 | U6: =IF(IF(IF(ISERROR('Revenue & gross margin'!U5<1),'Revenue & gross margin'!U5<1,IF('Revenue & gross margin'!U5="","",'Revenue & gross margin'!U5<1))="",FALSE,IF(ISERROR('Revenue & gross margin'!U5<1),'Revenue & gross margin'!U5<1,IF('Revenue & gross margin'!U5="","",'Revenue & gross margin'!U5<1))),0,'Model inputs'!B9*IF(AND((1+'Model inputs'!B10)=0,(MIN('Revenue & gross margin'!U5,'Model inputs'!B7)-1)=0),SQRT(-1),(1+'Model inputs'!B10)^(MIN('Revenue & gross margin'!U5,'Model inputs'!B7)-1))*'Model inputs'!B14) -> 1000 | V6: =IF(IF(IF(ISERROR('Revenue & gross margin'!V5<1),'Revenue & gross margin'!V5<1,IF('Revenue & gross margin'!V5="","",'Revenue & gross margin'!V5<1))="",FALSE,IF(ISERROR('Revenue & gross margin'!V5<1),'Revenue & gross margin'!V5<1,IF('Revenue & gross margin'!V5="","",'Revenue & gross margin'!V5<1))),0,'Model inputs'!B9*IF(AND((1+'Model inputs'!B10)=0,(MIN('Revenue & gross margin'!V5,'Model inputs'!B7)-1)=0),SQRT(-1),(1+'Model inputs'!B10)^(MIN('Revenue & gross margin'!V5,'Model inputs'!B7)-1))*'Model inputs'!B14) -> 1000 | W6: =IF(IF(IF(ISERROR('Revenue & gross margin'!W5<1),'Revenue & gross margin'!W5<1,IF('Revenue & gross margin'!W5="","",'Revenue & gross margin'!W5<1))="",FALSE,IF(ISERROR('Revenue & gross margin'!W5<1),'Revenue & gross margin'!W5<1,IF('Revenue & gross margin'!W5="","",'Revenue & gross margin'!W5<1))),0,'Model inputs'!B9*IF(AND((1+'Model inputs'!B10)=0,(MIN('Revenue & gross margin'!W5,'Model inputs'!B7)-1)=0),SQRT(-1),(1+'Model inputs'!B10)^(MIN('Revenue & gross margin'!W5,'Model inputs'!B7)-1))*'Model inputs'!B14) -> 1000 | X6: =IF(IF(IF(ISERROR('Revenue & gross margin'!X5<1),'Revenue & gross margin'!X5<1,IF('Revenue & gross margin'!X5="","",'Revenue & gross margin'!X5<1))="",FALSE,IF(ISERROR('Revenue & gross margin'!X5<1),'Revenue & gross margin'!X5<1,IF('Revenue & gross margin'!X5="","",'Revenue & gross margin'!X5<1))),0,'Model inputs'!B9*IF(AND((1+'Model inputs'!B10)=0,(MIN('Revenue & gross margin'!X5,'Model inputs'!B7)-1)=0),SQRT(-1),(1+'Model inputs'!B10)^(MIN('Revenue & gross margin'!X5,'Model inputs'!B7)-1))*'Model inputs'!B14) -> 1000 | Y6: =IF(IF(IF(ISERROR('Revenue & gross margin'!Y5<1),'Revenue & gross margin'!Y5<1,IF('Revenue & gross margin'!Y5="","",'Revenue & gross margin'!Y5<1))="",FALSE,IF(ISERROR('Revenue & gross margin'!Y5<1),'Revenue & gross margin'!Y5<1,IF('Revenue & gross margin'!Y5="","",'Revenue & gross margin'!Y5<1))),0,'Model inputs'!B9*IF(AND((1+'Model inputs'!B10)=0,(MIN('Revenue & gross margin'!Y5,'Model inputs'!B7)-1)=0),SQRT(-1),(1+'Model inputs'!B10)^(MIN('Revenue & gross margin'!Y5,'Model inputs'!B7)-1))*'Model inputs'!B14) -> 1000
A7: Verified fixes | B7: ='Revenue & gross margin'!B6*'Model inputs'!B13 -> 0 | C7: ='Revenue & gross margin'!C6*'Model inputs'!B13 -> 750 | D7: ='Revenue & gross margin'!D6*'Model inputs'!B13 -> 750 | E7: ='Revenue & gross margin'!E6*'Model inputs'!B13 -> 750 | F7: ='Revenue & gross margin'!F6*'Model inputs'!B13 -> 750 | G7: ='Revenue & gross margin'!G6*'Model inputs'!B13 -> 750 | H7: ='Revenue & gross margin'!H6*'Model inputs'!B13 -> 750 | I7: ='Revenue & gross margin'!I6*'Model inputs'!B13 -> 750 | J7: ='Revenue & gross margin'!J6*'Model inputs'!B13 -> 750 | K7: ='Revenue & gross margin'!K6*'Model inputs'!B13 -> 750 | L7: ='Revenue & gross margin'!L6*'Model inputs'!B13 -> 750 | M7: ='Revenue & gross margin'!M6*'Model inputs'!B13 -> 750 | N7: ='Revenue & gross margin'!N6*'Model inputs'!B13 -> 750 | O7: ='Revenue & gross margin'!O6*'Model inputs'!B13 -> 750 | P7: ='Revenue & gross margin'!P6*'Model inputs'!B13 -> 750 | Q7: ='Revenue & gross margin'!Q6*'Model inputs'!B13 -> 750 | R7: ='Revenue & gross margin'!R6*'Model inputs'!B13 -> 750 | S7: ='Revenue & gross margin'!S6*'Model inputs'!B13 -> 750 | T7: ='Revenue & gross margin'!T6*'Model inputs'!B13 -> 750 | U7: ='Revenue & gross margin'!U6*'Model inputs'!B13 -> 750 | V7: ='Revenue & gross margin'!V6*'Model inputs'!B13 -> 750 | W7: ='Revenue & gross margin'!W6*'Model inputs'!B13 -> 750 | X7: ='Revenue & gross margin'!X6*'Model inputs'!B13 -> 750 | Y7: ='Revenue & gross margin'!Y6*'Model inputs'!B13 -> 750
A8: Revenue | B8: ='Revenue & gross margin'!B7*'Model inputs'!B12 -> 0 | C8: ='Revenue & gross margin'!C7*'Model inputs'!B12 -> 255 | D8: ='Revenue & gross margin'!D7*'Model inputs'!B12 -> 255 | E8: ='Revenue & gross margin'!E7*'Model inputs'!B12 -> 255 | F8: ='Revenue & gross margin'!F7*'Model inputs'!B12 -> 255 | G8: ='Revenue & gross margin'!G7*'Model inputs'!B12 -> 255 | H8: ='Revenue & gross margin'!H7*'Model inputs'!B12 -> 255 | I8: ='Revenue & gross margin'!I7*'Model inputs'!B12 -> 255 | J8: ='Revenue & gross margin'!J7*'Model inputs'!B12 -> 255 | K8: ='Revenue & gross margin'!K7*'Model inputs'!B12 -> 255 | L8: ='Revenue & gross margin'!L7*'Model inputs'!B12 -> 255 | M8: ='Revenue & gross margin'!M7*'Model inputs'!B12 -> 255 | N8: ='Revenue & gross margin'!N7*'Model inputs'!B12 -> 255 | O8: ='Revenue & gross margin'!O7*'Model inputs'!B12 -> 255 | P8: ='Revenue & gross margin'!P7*'Model inputs'!B12 -> 255 | Q8: ='Revenue & gross margin'!Q7*'Model inputs'!B12 -> 255 | R8: ='Revenue & gross margin'!R7*'Model inputs'!B12 -> 255 | S8: ='Revenue & gross margin'!S7*'Model inputs'!B12 -> 255 | T8: ='Revenue & gross margin'!T7*'Model inputs'!B12 -> 255 | U8: ='Revenue & gross margin'!U7*'Model inputs'!B12 -> 255 | V8: ='Revenue & gross margin'!V7*'Model inputs'!B12 -> 255 | W8: ='Revenue & gross margin'!W7*'Model inputs'!B12 -> 255 | X8: ='Revenue & gross margin'!X7*'Model inputs'!B12 -> 255 | Y8: ='Revenue & gross margin'!Y7*'Model inputs'!B12 -> 255
A9: Model usage cost | B9: ='Revenue & gross margin'!B7*'Model inputs'!B6 -> 0 | C9: ='Revenue & gross margin'!C7*'Model inputs'!B6 -> 97.5 | D9: ='Revenue & gross margin'!D7*'Model inputs'!B6 -> 97.5 | E9: ='Revenue & gross margin'!E7*'Model inputs'!B6 -> 97.5 | F9: ='Revenue & gross margin'!F7*'Model inputs'!B6 -> 97.5 | G9: ='Revenue & gross margin'!G7*'Model inputs'!B6 -> 97.5 | H9: ='Revenue & gross margin'!H7*'Model inputs'!B6 -> 97.5 | I9: ='Revenue & gross margin'!I7*'Model inputs'!B6 -> 97.5 | J9: ='Revenue & gross margin'!J7*'Model inputs'!B6 -> 97.5 | K9: ='Revenue & gross margin'!K7*'Model inputs'!B6 -> 97.5 | L9: ='Revenue & gross margin'!L7*'Model inputs'!B6 -> 97.5 | M9: ='Revenue & gross margin'!M7*'Model inputs'!B6 -> 97.5 | N9: ='Revenue & gross margin'!N7*'Model inputs'!B6 -> 97.5 | O9: ='Revenue & gross margin'!O7*'Model inputs'!B6 -> 97.5 | P9: ='Revenue & gross margin'!P7*'Model inputs'!B6 -> 97.5 | Q9: ='Revenue & gross margin'!Q7*'Model inputs'!B6 -> 97.5 | R9: ='Revenue & gross margin'!R7*'Model inputs'!B6 -> 97.5 | S9: ='Revenue & gross margin'!S7*'Model inputs'!B6 -> 97.5 | T9: ='Revenue & gross margin'!T7*'Model inputs'!B6 -> 97.5 | U9: ='Revenue & gross margin'!U7*'Model inputs'!B6 -> 97.5 | V9: ='Revenue & gross margin'!V7*'Model inputs'!B6 -> 97.5 | W9: ='Revenue & gross margin'!W7*'Model inputs'!B6 -> 97.5 | X9: ='Revenue & gross margin'!X7*'Model inputs'!B6 -> 97.5 | Y9: ='Revenue & gross margin'!Y7*'Model inputs'!B6 -> 97.5
A10: Payment processing | B10: ='Revenue & gross margin'!B8*'Model inputs'!B11 -> 0 | C10: ='Revenue & gross margin'!C8*'Model inputs'!B11 -> 7.65 | D10: ='Revenue & gross margin'!D8*'Model inputs'!B11 -> 7.65 | E10: ='Revenue & gross margin'!E8*'Model inputs'!B11 -> 7.65 | F10: ='Revenue & gross margin'!F8*'Model inputs'!B11 -> 7.65 | G10: ='Revenue & gross margin'!G8*'Model inputs'!B11 -> 7.65 | H10: ='Revenue & gross margin'!H8*'Model inputs'!B11 -> 7.65 | I10: ='Revenue & gross margin'!I8*'Model inputs'!B11 -> 7.65 | J10: ='Revenue & gross margin'!J8*'Model inputs'!B11 -> 7.65 | K10: ='Revenue & gross margin'!K8*'Model inputs'!B11 -> 7.65 | L10: ='Revenue & gross margin'!L8*'Model inputs'!B11 -> 7.65 | M10: ='Revenue & gross margin'!M8*'Model inputs'!B11 -> 7.65 | N10: ='Revenue & gross margin'!N8*'Model inputs'!B11 -> 7.65 | O10: ='Revenue & gross margin'!O8*'Model inputs'!B11 -> 7.65 | P10: ='Revenue & gross margin'!P8*'Model inputs'!B11 -> 7.65 | Q10: ='Revenue & gross margin'!Q8*'Model inputs'!B11 -> 7.65 | R10: ='Revenue & gross margin'!R8*'Model inputs'!B11 -> 7.65 | S10: ='Revenue & gross margin'!S8*'Model inputs'!B11 -> 7.65 | T10: ='Revenue & gross margin'!T8*'Model inputs'!B11 -> 7.65 | U10: ='Revenue & gross margin'!U8*'Model inputs'!B11 -> 7.65 | V10: ='Revenue & gross margin'!V8*'Model inputs'!B11 -> 7.65 | W10: ='Revenue & gross margin'!W8*'Model inputs'!B11 -> 7.65 | X10: ='Revenue & gross margin'!X8*'Model inputs'!B11 -> 7.65 | Y10: ='Revenue & gross margin'!Y8*'Model inputs'!B11 -> 7.65
A11: Cost of revenue | B11: ='Revenue & gross margin'!B9+'Revenue & gross margin'!B10 -> 0 | C11: ='Revenue & gross margin'!C9+'Revenue & gross margin'!C10 -> 105.15 | D11: ='Revenue & gross margin'!D9+'Revenue & gross margin'!D10 -> 105.15 | E11: ='Revenue & gross margin'!E9+'Revenue & gross margin'!E10 -> 105.15 | F11: ='Revenue & gross margin'!F9+'Revenue & gross margin'!F10 -> 105.15 | G11: ='Revenue & gross margin'!G9+'Revenue & gross margin'!G10 -> 105.15 | H11: ='Revenue & gross margin'!H9+'Revenue & gross margin'!H10 -> 105.15 | I11: ='Revenue & gross margin'!I9+'Revenue & gross margin'!I10 -> 105.15 | ... Y11: ='Revenue & gross margin'!Y9+'Revenue & gross margin'!Y10 -> 105.15
A12: Gross profit | B12: ='Revenue & gross margin'!B8-'Revenue & gross margin'!B11 -> 0 | C12: ='Revenue & gross margin'!C8-'Revenue & gross margin'!C11 -> 149.85 | D12: ='Revenue & gross margin'!D8-'Revenue & gross margin'!D11 -> 149.85 | E12: ='Revenue & gross margin'!E8-'Revenue & gross margin'!E11 -> 149.85 | F12: ='Revenue & gross margin'!F8-'Revenue & gross margin'!F11 -> 149.85 | G12: ='Revenue & gross margin'!G8-'Revenue & gross margin'!G11 -> 149.85 | H12: ='Revenue & gross margin'!H8-'Revenue & gross margin'!H11 -> 149.85 | I12: ='Revenue & gross margin'!I8-'Revenue & gross margin'!I11 -> 149.85 | ... Y12: ='Revenue & gross margin'!Y8-'Revenue & gross margin'!Y11 -> 149.85
A13: Gross margin | B13: =IFERROR('Revenue & gross margin'!B12/'Revenue & gross margin'!B8,"") | C13: =IFERROR('Revenue & gross margin'!C12/'Revenue & gross margin'!C8,"") -> 0.58764706 | D13: =IFERROR('Revenue & gross margin'!D12/'Revenue & gross margin'!D8,"") -> 0.58764706 | E13: =IFERROR('Revenue & gross margin'!E12/'Revenue & gross margin'!E8,"") -> 0.58764706 | F13: =IFERROR('Revenue & gross margin'!F12/'Revenue & gross margin'!F8,"") -> 0.58764706 | G13: =IFERROR('Revenue & gross margin'!G12/'Revenue & gross margin'!G8,"") -> 0.58764706 | H13: =IFERROR('Revenue & gross margin'!H12/'Revenue & gross margin'!H8,"") -> 0.58764706 | I13: =IFERROR('Revenue & gross margin'!I12/'Revenue & gross margin'!I8,"") -> 0.58764706 | ... Y13: =IFERROR('Revenue & gross margin'!Y12/'Revenue & gross margin'!Y8,"") -> 0.58764706
A14: Revenue per job attempted | B14: =IFERROR('Revenue & gross margin'!B8/'Revenue & gross margin'!B6,"") | C14: =IFERROR('Revenue & gross margin'!C8/'Revenue & gross margin'!C6,"") -> 0.255 | D14: =IFERROR('Revenue & gross margin'!D8/'Revenue & gross margin'!D6,"") -> 0.255 | E14: =IFERROR('Revenue & gross margin'!E8/'Revenue & gross margin'!E6,"") -> 0.255 | F14: =IFERROR('Revenue & gross margin'!F8/'Revenue & gross margin'!F6,"") -> 0.255 | G14: =IFERROR('Revenue & gross margin'!G8/'Revenue & gross margin'!G6,"") -> 0.255 | H14: =IFERROR('Revenue & gross margin'!H8/'Revenue & gross margin'!H6,"") -> 0.255 | I14: =IFERROR('Revenue & gross margin'!I8/'Revenue & gross margin'!I6,"") -> 0.255 | ... Y14: =IFERROR('Revenue & gross margin'!Y8/'Revenue & gross margin'!Y6,"") -> 0.255

Sheet Model inputs
A1: Model inputs
A2: Integration values are aggregated snapshots; raw source records are not included.
A4: Variables
A5: Variable / segment | B5: Value
A6: All-in cost per verified fix | B6: =0.13 -> 0.13
A7: Growth months | B7: =12 -> 12
A8: Launch month | B8: =DATE(2026,11,1) -> 46327
A9: Launch month jobs | B9: =1000 -> 1000
A10: Monthly job growth | B10: =0 -> 0
A11: Payment processing rate | B11: =0.03 -> 0.03
A12: Price per verified fix | B12: =0.34 -> 0.34
A13: Verification rate | B13: =0.75 -> 0.75
A14: Volume vs $0.34 price | B14: =1 -> 1
