Workbook

Sheet Price point test
A1: Price point test
A2: Pricing · Main Scenario
A4: Variable / dimension | B4: Test price per fix | C4: Test volume vs $0.34 | D4: Quote band floor | E4: Quote band cap | F4: Cost per fix incl. processing | G4: Gross profit per fix | H4: Margin before processing | I4: Gross margin after processing | J4: Floor cushion vs hard job | K4: Profit per job attempted | L4: Break-even jobs / month | M4: Break-even jobs with salary | N4: Monthly profit at base volume
A5: $0.34 standard | B5: =0.34 -> 0.34 | C5: =1 -> 1 | D5: =0.18 -> 0.18 | E5: =0.67 -> 0.67 | F5: ='Model inputs'!B6+'Price point test'!B5*'Model inputs'!B15 -> 0.1402 | G5: ='Price point test'!B5-'Price point test'!F5 -> 0.1998 | H5: =IFERROR(('Price point test'!B5-'Model inputs'!B6)/'Price point test'!B5,"") -> 0.61764706 | I5: =IFERROR('Price point test'!G5/'Price point test'!B5,"") -> 0.58764706 | J5: ='Price point test'!D5-'Model inputs'!B14/'Model inputs'!B16 -> -0.0066666667 | K5: ='Price point test'!G5*'Model inputs'!B16 -> 0.14985 | L5: =IFERROR(SUM('Model inputs'!B10,'Model inputs'!B11,'Model inputs'!B12,'Model inputs'!B13)/'Price point test'!K5,"") -> 1134.4678 | M5: =IFERROR((SUM('Model inputs'!B10,'Model inputs'!B11,'Model inputs'!B12,'Model inputs'!B13)+'Model inputs'!B7)/'Price point test'!K5,"") -> 14481.148 | N5: ='Model inputs'!B8*'Price point test'!C5*'Price point test'!K5-SUM('Model inputs'!B10,'Model inputs'!B11,'Model inputs'!B12,'Model inputs'!B13) -> -20.15
A6: $0.60 premium | B6: =0.6 -> 0.6 | C6: =0.85 -> 0.85 | D6: =0.32 -> 0.32 | E6: =1.18 -> 1.18 | F6: ='Model inputs'!B6+'Price point test'!B6*'Model inputs'!B15 -> 0.148 | G6: ='Price point test'!B6-'Price point test'!F6 -> 0.452 | H6: =IFERROR(('Price point test'!B6-'Model inputs'!B6)/'Price point test'!B6,"") -> 0.78333333 | I6: =IFERROR('Price point test'!G6/'Price point test'!B6,"") -> 0.75333333 | J6: ='Price point test'!D6-'Model inputs'!B14/'Model inputs'!B16 -> 0.13333333 | K6: ='Price point test'!G6*'Model inputs'!B16 -> 0.339 | L6: =IFERROR(SUM('Model inputs'!B10,'Model inputs'!B11,'Model inputs'!B12,'Model inputs'!B13)/'Price point test'!K6,"") -> 501.47493 | M6: =IFERROR((SUM('Model inputs'!B10,'Model inputs'!B11,'Model inputs'!B12,'Model inputs'!B13)+'Model inputs'!B7)/'Price point test'!K6,"") -> 6401.1799 | N6: ='Model inputs'!B8*'Price point test'!C6*'Price point test'!K6-SUM('Model inputs'!B10,'Model inputs'!B11,'Model inputs'!B12,'Model inputs'!B13) -> 118.15

Sheet Model inputs
A1: Model inputs
A2: Integration values are aggregated snapshots; raw source records are not included.
A4: Variables
A5: Variable / segment | B5: Value
A6: All-in cost per verified fix | B6: =0.13 -> 0.13
A7: Founder salary (comparison) | B7: =2000 -> 2000
A8: Launch month jobs | B8: =1000 -> 1000
A9: Monthly fixed cost | B9: 0
A10: Monthly fixed cost > Accounting, legal & misc | B10: =50 -> 50
A11: Monthly fixed cost > Hosting | B11: =40 -> 40
A12: Monthly fixed cost > Observability | B12: =50 -> 50
A13: Monthly fixed cost > Tooling & misc | B13: =30 -> 30
A14: P90 cost per job | B14: =0.14 -> 0.14
A15: Payment processing rate | B15: =0.03 -> 0.03
A16: Verification rate | B16: =0.75 -> 0.75
A18: Dimensions
A19: Cost line | B19: Accounting, legal & misc | C19: Hosting | D19: Observability | E19: Tooling & misc
