Workbook

Sheet Scenario comparison by quarter
A1: Scenario comparison by quarter
A2: Scenarios · Main Scenario
A4: Variable / dimension | B4: 2026-10 | C4: 2026-10 > Base · $0.60 | D4: 2026-10 > Growth · $0.34 | E4: 2026-10 > Growth · $0.60 | F4: 2027-01 | G4: 2027-01 > Base · $0.60 | H4: 2027-01 > Growth · $0.34 | I4: 2027-01 > Growth · $0.60 | J4: 2027-04 | K4: 2027-04 > Base · $0.60 | L4: 2027-04 > Growth · $0.34 | M4: 2027-04 > Growth · $0.60 | N4: 2027-07 | O4: 2027-07 > Base · $0.60 | P4: 2027-07 > Growth · $0.34 | Q4: 2027-07 > Growth · $0.60 | R4: 2027-10 | S4: 2027-10 > Base · $0.60 | T4: 2027-10 > Growth · $0.34 | U4: 2027-10 > Growth · $0.60 | V4: 2028-01 | W4: 2028-01 > Base · $0.60 | X4: 2028-01 > Growth · $0.34 | Y4: 2028-01 > Growth · $0.60 | Z4: 2028-04 | AA4: 2028-04 > Base · $0.60 | AB4: 2028-04 > Growth · $0.34 | AC4: 2028-04 > Growth · $0.60 | AD4: 2028-07 | AE4: 2028-07 > Base · $0.60 | AF4: 2028-07 > Growth · $0.34 | AG4: 2028-07 > Growth · $0.60
A5: Jobs attempted | B5: =SUM('Model inputs'!K18,'Model inputs'!L18,'Model inputs'!M18) -> 2000 | C5: =SUM('Model inputs'!K20,'Model inputs'!L20,'Model inputs'!M20) -> 1700 | D5: =SUM('Model inputs'!K21,'Model inputs'!L21,'Model inputs'!M21) -> 2250 | E5: =SUM('Model inputs'!K19,'Model inputs'!L19,'Model inputs'!M19) -> 1912.5 | F5: =SUM('Model inputs'!N18,'Model inputs'!O18,'Model inputs'!P18) -> 3000 | G5: =SUM('Model inputs'!N20,'Model inputs'!O20,'Model inputs'!P20) -> 2550 | H5: =SUM('Model inputs'!N21,'Model inputs'!O21,'Model inputs'!P21) -> 5957.0312 | I5: =SUM('Model inputs'!N19,'Model inputs'!O19,'Model inputs'!P19) -> 5063.4766 | J5: =SUM('Model inputs'!Q18,'Model inputs'!R18,'Model inputs'!S18) -> 3000 | K5: =SUM('Model inputs'!Q20,'Model inputs'!R20,'Model inputs'!S20) -> 2550 | L5: =SUM('Model inputs'!Q21,'Model inputs'!R21,'Model inputs'!S21) -> 11634.827 | M5: =SUM('Model inputs'!Q19,'Model inputs'!R19,'Model inputs'!S19) -> 9889.6027 | N5: =SUM('Model inputs'!T18,'Model inputs'!U18,'Model inputs'!V18) -> 3000 | O5: =SUM('Model inputs'!T20,'Model inputs'!U20,'Model inputs'!V20) -> 2550 | P5: =SUM('Model inputs'!T21,'Model inputs'!U21,'Model inputs'!V21) -> 22724.271 | Q5: =SUM('Model inputs'!T19,'Model inputs'!U19,'Model inputs'!V19) -> 19315.63 | R5: =SUM('Model inputs'!W18,'Model inputs'!X18,'Model inputs'!Y18) -> 3000 | S5: =SUM('Model inputs'!W20,'Model inputs'!X20,'Model inputs'!Y20) -> 2550 | T5: =SUM('Model inputs'!W21,'Model inputs'!X21,'Model inputs'!Y21) -> 34924.597 | U5: =SUM('Model inputs'!W19,'Model inputs'!X19,'Model inputs'!Y19) -> 29685.907 | V5: =SUM('Model inputs'!Z18,'Model inputs'!AA18,'Model inputs'!AB18) -> 3000 | W5: =SUM('Model inputs'!Z20,'Model inputs'!AA20,'Model inputs'!AB20) -> 2550 | X5: =SUM('Model inputs'!Z21,'Model inputs'!AA21,'Model inputs'!AB21) -> 34924.597 | Y5: =SUM('Model inputs'!Z19,'Model inputs'!AA19,'Model inputs'!AB19) -> 29685.907 | Z5: =SUM('Model inputs'!AC18,'Model inputs'!AD18,'Model inputs'!AE18) -> 3000 | AA5: =SUM('Model inputs'!AC20,'Model inputs'!AD20,'Model inputs'!AE20) -> 2550 | AB5: =SUM('Model inputs'!AC21,'Model inputs'!AD21,'Model inputs'!AE21) -> 34924.597 | AC5: =SUM('Model inputs'!AC19,'Model inputs'!AD19,'Model inputs'!AE19) -> 29685.907 | AD5: =SUM('Model inputs'!AF18,'Model inputs'!AG18,'Model inputs'!AH18) -> 3000 | AE5: =SUM('Model inputs'!AF20,'Model inputs'!AG20,'Model inputs'!AH20) -> 2550 | AF5: =SUM('Model inputs'!AF21,'Model inputs'!AG21,'Model inputs'!AH21) -> 34924.597 | AG5: =SUM('Model inputs'!AF19,'Model inputs'!AG19,'Model inputs'!AH19) -> 29685.907
A6: Revenue | B6: =SUM('Model inputs'!K30,'Model inputs'!L30,'Model inputs'!M30) -> 510 | C6: =SUM('Model inputs'!K32,'Model inputs'!L32,'Model inputs'!M32) -> 765 | D6: =SUM('Model inputs'!K33,'Model inputs'!L33,'Model inputs'!M33) -> 573.75 | E6: =SUM('Model inputs'!K31,'Model inputs'!L31,'Model inputs'!M31) -> 860.625 | F6: =SUM('Model inputs'!N30,'Model inputs'!O30,'Model inputs'!P30) -> 765 | G6: =SUM('Model inputs'!N32,'Model inputs'!O32,'Model inputs'!P32) -> 1147.5 | H6: =SUM('Model inputs'!N33,'Model inputs'!O33,'Model inputs'!P33) -> 1519.043 | I6: =SUM('Model inputs'!N31,'Model inputs'!O31,'Model inputs'!P31) -> 2278.5645 | J6: =SUM('Model inputs'!Q30,'Model inputs'!R30,'Model inputs'!S30) -> 765 | K6: =SUM('Model inputs'!Q32,'Model inputs'!R32,'Model inputs'!S32) -> 1147.5 | L6: =SUM('Model inputs'!Q33,'Model inputs'!R33,'Model inputs'!S33) -> 2966.8808 | M6: =SUM('Model inputs'!Q31,'Model inputs'!R31,'Model inputs'!S31) -> 4450.3212 | N6: =SUM('Model inputs'!T30,'Model inputs'!U30,'Model inputs'!V30) -> 765 | O6: =SUM('Model inputs'!T32,'Model inputs'!U32,'Model inputs'!V32) -> 1147.5 | P6: =SUM('Model inputs'!T33,'Model inputs'!U33,'Model inputs'!V33) -> 5794.6891 | Q6: =SUM('Model inputs'!T31,'Model inputs'!U31,'Model inputs'!V31) -> 8692.0336 | R6: =SUM('Model inputs'!W30,'Model inputs'!X30,'Model inputs'!Y30) -> 765 | S6: =SUM('Model inputs'!W32,'Model inputs'!X32,'Model inputs'!Y32) -> 1147.5 | T6: =SUM('Model inputs'!W33,'Model inputs'!X33,'Model inputs'!Y33) -> 8905.7721 | U6: =SUM('Model inputs'!W31,'Model inputs'!X31,'Model inputs'!Y31) -> 13358.658 | V6: =SUM('Model inputs'!Z30,'Model inputs'!AA30,'Model inputs'!AB30) -> 765 | W6: =SUM('Model inputs'!Z32,'Model inputs'!AA32,'Model inputs'!AB32) -> 1147.5 | X6: =SUM('Model inputs'!Z33,'Model inputs'!AA33,'Model inputs'!AB33) -> 8905.7721 | Y6: =SUM('Model inputs'!Z31,'Model inputs'!AA31,'Model inputs'!AB31) -> 13358.658 | Z6: =SUM('Model inputs'!AC30,'Model inputs'!AD30,'Model inputs'!AE30) -> 765 | AA6: =SUM('Model inputs'!AC32,'Model inputs'!AD32,'Model inputs'!AE32) -> 1147.5 | AB6: =SUM('Model inputs'!AC33,'Model inputs'!AD33,'Model inputs'!AE33) -> 8905.7721 | AC6: =SUM('Model inputs'!AC31,'Model inputs'!AD31,'Model inputs'!AE31) -> 13358.658 | AD6: =SUM('Model inputs'!AF30,'Model inputs'!AG30,'Model inputs'!AH30) -> 765 | AE6: =SUM('Model inputs'!AF32,'Model inputs'!AG32,'Model inputs'!AH32) -> 1147.5 | AF6: =SUM('Model inputs'!AF33,'Model inputs'!AG33,'Model inputs'!AH33) -> 8905.7721 | AG6: =SUM('Model inputs'!AF31,'Model inputs'!AG31,'Model inputs'!AH31) -> 13358.658
A7: Gross profit | B7: =SUM('Model inputs'!K14,'Model inputs'!L14,'Model inputs'!M14) -> 299.7 | C7: =SUM('Model inputs'!K16,'Model inputs'!L16,'Model inputs'!M16) -> 576.3 | D7: =SUM('Model inputs'!K17,'Model inputs'!L17,'Model inputs'!M17) -> 337.1625 | E7: =SUM('Model inputs'!K15,'Model inputs'!L15,'Model inputs'!M15) -> 648.3375 | F7: =SUM('Model inputs'!N14,'Model inputs'!O14,'Model inputs'!P14) -> 449.55 | G7: =SUM('Model inputs'!N16,'Model inputs'!O16,'Model inputs'!P16) -> 864.45 | H7: =SUM('Model inputs'!N17,'Model inputs'!O17,'Model inputs'!P17) -> 892.66113 | I7: =SUM('Model inputs'!N15,'Model inputs'!O15,'Model inputs'!P15) -> 1716.5186 | J7: =SUM('Model inputs'!Q14,'Model inputs'!R14,'Model inputs'!S14) -> 449.55 | K7: =SUM('Model inputs'!Q16,'Model inputs'!R16,'Model inputs'!S16) -> 864.45 | L7: =SUM('Model inputs'!Q17,'Model inputs'!R17,'Model inputs'!S17) -> 1743.4788 | M7: =SUM('Model inputs'!Q15,'Model inputs'!R15,'Model inputs'!S15) -> 3352.5753 | N7: =SUM('Model inputs'!T14,'Model inputs'!U14,'Model inputs'!V14) -> 449.55 | O7: =SUM('Model inputs'!T16,'Model inputs'!U16,'Model inputs'!V16) -> 864.45 | P7: =SUM('Model inputs'!T17,'Model inputs'!U17,'Model inputs'!V17) -> 3405.232 | Q7: =SUM('Model inputs'!T15,'Model inputs'!U15,'Model inputs'!V15) -> 6547.9986 | R7: =SUM('Model inputs'!W14,'Model inputs'!X14,'Model inputs'!Y14) -> 449.55 | S7: =SUM('Model inputs'!W16,'Model inputs'!X16,'Model inputs'!Y16) -> 864.45 | T7: =SUM('Model inputs'!W17,'Model inputs'!X17,'Model inputs'!Y17) -> 5233.4508 | U7: =SUM('Model inputs'!W15,'Model inputs'!X15,'Model inputs'!Y15) -> 10063.522 | V7: =SUM('Model inputs'!Z14,'Model inputs'!AA14,'Model inputs'!AB14) -> 449.55 | W7: =SUM('Model inputs'!Z16,'Model inputs'!AA16,'Model inputs'!AB16) -> 864.45 | X7: =SUM('Model inputs'!Z17,'Model inputs'!AA17,'Model inputs'!AB17) -> 5233.4508 | Y7: =SUM('Model inputs'!Z15,'Model inputs'!AA15,'Model inputs'!AB15) -> 10063.522 | Z7: =SUM('Model inputs'!AC14,'Model inputs'!AD14,'Model inputs'!AE14) -> 449.55 | AA7: =SUM('Model inputs'!AC16,'Model inputs'!AD16,'Model inputs'!AE16) -> 864.45 | AB7: =SUM('Model inputs'!AC17,'Model inputs'!AD17,'Model inputs'!AE17) -> 5233.4508 | AC7: =SUM('Model inputs'!AC15,'Model inputs'!AD15,'Model inputs'!AE15) -> 10063.522 | AD7: =SUM('Model inputs'!AF14,'Model inputs'!AG14,'Model inputs'!AH14) -> 449.55 | AE7: =SUM('Model inputs'!AF16,'Model inputs'!AG16,'Model inputs'!AH16) -> 864.45 | AF7: =SUM('Model inputs'!AF17,'Model inputs'!AG17,'Model inputs'!AH17) -> 5233.4508 | AG7: =SUM('Model inputs'!AF15,'Model inputs'!AG15,'Model inputs'!AH15) -> 10063.522
A8: Operating profit | B8: =SUM('Model inputs'!K26,'Model inputs'!L26,'Model inputs'!M26) -> -210.3 | C8: =SUM('Model inputs'!K28,'Model inputs'!L28,'Model inputs'!M28) -> 66.3 | D8: =SUM('Model inputs'!K29,'Model inputs'!L29,'Model inputs'!M29) -> -172.8375 | E8: =SUM('Model inputs'!K27,'Model inputs'!L27,'Model inputs'!M27) -> 138.3375 | F8: =SUM('Model inputs'!N26,'Model inputs'!O26,'Model inputs'!P26) -> -60.45 | G8: =SUM('Model inputs'!N28,'Model inputs'!O28,'Model inputs'!P28) -> 354.45 | H8: =SUM('Model inputs'!N29,'Model inputs'!O29,'Model inputs'!P29) -> 382.66113 | I8: =SUM('Model inputs'!N27,'Model inputs'!O27,'Model inputs'!P27) -> 1206.5186 | J8: =SUM('Model inputs'!Q26,'Model inputs'!R26,'Model inputs'!S26) -> -60.45 | K8: =SUM('Model inputs'!Q28,'Model inputs'!R28,'Model inputs'!S28) -> 354.45 | L8: =SUM('Model inputs'!Q29,'Model inputs'!R29,'Model inputs'!S29) -> 1233.4788 | M8: =SUM('Model inputs'!Q27,'Model inputs'!R27,'Model inputs'!S27) -> 2842.5753 | N8: =SUM('Model inputs'!T26,'Model inputs'!U26,'Model inputs'!V26) -> -60.45 | O8: =SUM('Model inputs'!T28,'Model inputs'!U28,'Model inputs'!V28) -> 354.45 | P8: =SUM('Model inputs'!T29,'Model inputs'!U29,'Model inputs'!V29) -> 2895.232 | Q8: =SUM('Model inputs'!T27,'Model inputs'!U27,'Model inputs'!V27) -> 6037.9986 | R8: =SUM('Model inputs'!W26,'Model inputs'!X26,'Model inputs'!Y26) -> -60.45 | S8: =SUM('Model inputs'!W28,'Model inputs'!X28,'Model inputs'!Y28) -> 354.45 | T8: =SUM('Model inputs'!W29,'Model inputs'!X29,'Model inputs'!Y29) -> 4723.4508 | U8: =SUM('Model inputs'!W27,'Model inputs'!X27,'Model inputs'!Y27) -> 9553.5225 | V8: =SUM('Model inputs'!Z26,'Model inputs'!AA26,'Model inputs'!AB26) -> -60.45 | W8: =SUM('Model inputs'!Z28,'Model inputs'!AA28,'Model inputs'!AB28) -> 354.45 | X8: =SUM('Model inputs'!Z29,'Model inputs'!AA29,'Model inputs'!AB29) -> 4723.4508 | Y8: =SUM('Model inputs'!Z27,'Model inputs'!AA27,'Model inputs'!AB27) -> 9553.5225 | Z8: =SUM('Model inputs'!AC26,'Model inputs'!AD26,'Model inputs'!AE26) -> -60.45 | AA8: =SUM('Model inputs'!AC28,'Model inputs'!AD28,'Model inputs'!AE28) -> 354.45 | AB8: =SUM('Model inputs'!AC29,'Model inputs'!AD29,'Model inputs'!AE29) -> 4723.4508 | AC8: =SUM('Model inputs'!AC27,'Model inputs'!AD27,'Model inputs'!AE27) -> 9553.5225 | AD8: =SUM('Model inputs'!AF26,'Model inputs'!AG26,'Model inputs'!AH26) -> -60.45 | AE8: =SUM('Model inputs'!AF28,'Model inputs'!AG28,'Model inputs'!AH28) -> 354.45 | AF8: =SUM('Model inputs'!AF29,'Model inputs'!AG29,'Model inputs'!AH29) -> 4723.4508 | AG8: =SUM('Model inputs'!AF27,'Model inputs'!AG27,'Model inputs'!AH27) -> 9553.5225
A9: Net cash flow | B9: =SUM('Model inputs'!K22,'Model inputs'!L22,'Model inputs'!M22) -> -457.65 | C9: =SUM('Model inputs'!K24,'Model inputs'!L24,'Model inputs'!M24) -> -304.725 | D9: =SUM('Model inputs'!K25,'Model inputs'!L25,'Model inputs'!M25) -> -482.025 | E9: =SUM('Model inputs'!K23,'Model inputs'!L23,'Model inputs'!M23) -> -325.44375 | F9: =SUM('Model inputs'!N22,'Model inputs'!O22,'Model inputs'!P22) -> -60.45 | G9: =SUM('Model inputs'!N24,'Model inputs'!O24,'Model inputs'!P24) -> 354.45 | H9: =SUM('Model inputs'!N25,'Model inputs'!O25,'Model inputs'!P25) -> 87.966797 | I9: =SUM('Model inputs'!N23,'Model inputs'!O23,'Model inputs'!P23) -> 764.47705 | J9: =SUM('Model inputs'!Q22,'Model inputs'!R22,'Model inputs'!S22) -> -60.45 | K9: =SUM('Model inputs'!Q24,'Model inputs'!R24,'Model inputs'!S24) -> 354.45 | L9: =SUM('Model inputs'!Q25,'Model inputs'!R25,'Model inputs'!S25) -> 657.9039 | M9: =SUM('Model inputs'!Q23,'Model inputs'!R23,'Model inputs'!S23) -> 1979.213 | N9: =SUM('Model inputs'!T22,'Model inputs'!U22,'Model inputs'!V22) -> -60.45 | O9: =SUM('Model inputs'!T24,'Model inputs'!U24,'Model inputs'!V24) -> 354.45 | P9: =SUM('Model inputs'!T25,'Model inputs'!U25,'Model inputs'!V25) -> 1771.0623 | Q9: =SUM('Model inputs'!T23,'Model inputs'!U23,'Model inputs'!V23) -> 4351.7441 | R9: =SUM('Model inputs'!W22,'Model inputs'!X22,'Model inputs'!Y22) -> -60.45 | S9: =SUM('Model inputs'!W24,'Model inputs'!X24,'Model inputs'!Y24) -> 354.45 | T9: =SUM('Model inputs'!W25,'Model inputs'!X25,'Model inputs'!Y25) -> 4147.5442 | U9: =SUM('Model inputs'!W23,'Model inputs'!X23,'Model inputs'!Y23) -> 8689.6626 | V9: =SUM('Model inputs'!Z22,'Model inputs'!AA22,'Model inputs'!AB22) -> -60.45 | W9: =SUM('Model inputs'!Z24,'Model inputs'!AA24,'Model inputs'!AB24) -> 354.45 | X9: =SUM('Model inputs'!Z25,'Model inputs'!AA25,'Model inputs'!AB25) -> 4723.4508 | Y9: =SUM('Model inputs'!Z23,'Model inputs'!AA23,'Model inputs'!AB23) -> 9553.5225 | Z9: =SUM('Model inputs'!AC22,'Model inputs'!AD22,'Model inputs'!AE22) -> -60.45 | AA9: =SUM('Model inputs'!AC24,'Model inputs'!AD24,'Model inputs'!AE24) -> 354.45 | AB9: =SUM('Model inputs'!AC25,'Model inputs'!AD25,'Model inputs'!AE25) -> 4723.4508 | AC9: =SUM('Model inputs'!AC23,'Model inputs'!AD23,'Model inputs'!AE23) -> 9553.5225 | AD9: =SUM('Model inputs'!AF22,'Model inputs'!AG22,'Model inputs'!AH22) -> -60.45 | AE9: =SUM('Model inputs'!AF24,'Model inputs'!AG24,'Model inputs'!AH24) -> 354.45 | AF9: =SUM('Model inputs'!AF25,'Model inputs'!AG25,'Model inputs'!AH25) -> 4723.4508 | AG9: =SUM('Model inputs'!AF23,'Model inputs'!AG23,'Model inputs'!AH23) -> 9553.5225
A10: Cash balance | B10: =IF('Model inputs'!M6="","",'Model inputs'!M6) -> 2542.35 | C10: =IF('Model inputs'!M8="","",'Model inputs'!M8) -> 2695.275 | D10: =IF('Model inputs'!M9="","",'Model inputs'!M9) -> 2517.975 | E10: =IF('Model inputs'!M7="","",'Model inputs'!M7) -> 2674.5563 | F10: =IF('Model inputs'!P6="","",'Model inputs'!P6) -> 2481.9 | G10: =IF('Model inputs'!P8="","",'Model inputs'!P8) -> 3049.725 | H10: =IF('Model inputs'!P9="","",'Model inputs'!P9) -> 2605.9418 | I10: =IF('Model inputs'!P7="","",'Model inputs'!P7) -> 3439.0333 | J10: =IF('Model inputs'!S6="","",'Model inputs'!S6) -> 2421.45 | K10: =IF('Model inputs'!S8="","",'Model inputs'!S8) -> 3404.175 | L10: =IF('Model inputs'!S9="","",'Model inputs'!S9) -> 3263.8457 | M10: =IF('Model inputs'!S7="","",'Model inputs'!S7) -> 5418.2463 | N10: =IF('Model inputs'!V6="","",'Model inputs'!V6) -> 2361 | O10: =IF('Model inputs'!V8="","",'Model inputs'!V8) -> 3758.625 | P10: =IF('Model inputs'!V9="","",'Model inputs'!V9) -> 5034.908 | Q10: =IF('Model inputs'!V7="","",'Model inputs'!V7) -> 9769.9904 | R10: =IF('Model inputs'!Y6="","",'Model inputs'!Y6) -> 2300.55 | S10: =IF('Model inputs'!Y8="","",'Model inputs'!Y8) -> 4113.075 | T10: =IF('Model inputs'!Y9="","",'Model inputs'!Y9) -> 9182.4522 | U10: =IF('Model inputs'!Y7="","",'Model inputs'!Y7) -> 18459.653 | V10: =IF('Model inputs'!AB6="","",'Model inputs'!AB6) -> 2240.1 | W10: =IF('Model inputs'!AB8="","",'Model inputs'!AB8) -> 4467.525 | X10: =IF('Model inputs'!AB9="","",'Model inputs'!AB9) -> 13905.903 | Y10: =IF('Model inputs'!AB7="","",'Model inputs'!AB7) -> 28013.176 | Z10: =IF('Model inputs'!AE6="","",'Model inputs'!AE6) -> 2179.65 | AA10: =IF('Model inputs'!AE8="","",'Model inputs'!AE8) -> 4821.975 | AB10: =IF('Model inputs'!AE9="","",'Model inputs'!AE9) -> 18629.354 | AC10: =IF('Model inputs'!AE7="","",'Model inputs'!AE7) -> 37566.698 | AD10: =IF('Model inputs'!AH6="","",'Model inputs'!AH6) -> 2119.2 | AE10: =IF('Model inputs'!AH8="","",'Model inputs'!AH8) -> 5176.425 | AF10: =IF('Model inputs'!AH9="","",'Model inputs'!AH9) -> 23352.805 | AG10: =IF('Model inputs'!AH7="","",'Model inputs'!AH7) -> 47120.22
A11: Cash balance with salary | B11: =IF('Model inputs'!M10="","",'Model inputs'!M10) -> -3457.65 | C11: =IF('Model inputs'!M12="","",'Model inputs'!M12) -> -3304.725 | D11: =IF('Model inputs'!M13="","",'Model inputs'!M13) -> -3482.025 | E11: =IF('Model inputs'!M11="","",'Model inputs'!M11) -> -3325.4437 | F11: =IF('Model inputs'!P10="","",'Model inputs'!P10) -> -9518.1 | G11: =IF('Model inputs'!P12="","",'Model inputs'!P12) -> -8950.275 | H11: =IF('Model inputs'!P13="","",'Model inputs'!P13) -> -9394.0582 | I11: =IF('Model inputs'!P11="","",'Model inputs'!P11) -> -8560.9667 | J11: =IF('Model inputs'!S10="","",'Model inputs'!S10) -> -15578.55 | K11: =IF('Model inputs'!S12="","",'Model inputs'!S12) -> -14595.825 | L11: =IF('Model inputs'!S13="","",'Model inputs'!S13) -> -14736.154 | M11: =IF('Model inputs'!S11="","",'Model inputs'!S11) -> -12581.754 | N11: =IF('Model inputs'!V10="","",'Model inputs'!V10) -> -21639 | O11: =IF('Model inputs'!V12="","",'Model inputs'!V12) -> -20241.375 | P11: =IF('Model inputs'!V13="","",'Model inputs'!V13) -> -18965.092 | Q11: =IF('Model inputs'!V11="","",'Model inputs'!V11) -> -14230.01 | R11: =IF('Model inputs'!Y10="","",'Model inputs'!Y10) -> -27699.45 | S11: =IF('Model inputs'!Y12="","",'Model inputs'!Y12) -> -25886.925 | T11: =IF('Model inputs'!Y13="","",'Model inputs'!Y13) -> -20817.548 | U11: =IF('Model inputs'!Y11="","",'Model inputs'!Y11) -> -11540.347 | V11: =IF('Model inputs'!AB10="","",'Model inputs'!AB10) -> -33759.9 | W11: =IF('Model inputs'!AB12="","",'Model inputs'!AB12) -> -31532.475 | X11: =IF('Model inputs'!AB13="","",'Model inputs'!AB13) -> -22094.097 | Y11: =IF('Model inputs'!AB11="","",'Model inputs'!AB11) -> -7986.8245 | Z11: =IF('Model inputs'!AE10="","",'Model inputs'!AE10) -> -39820.35 | AA11: =IF('Model inputs'!AE12="","",'Model inputs'!AE12) -> -37178.025 | AB11: =IF('Model inputs'!AE13="","",'Model inputs'!AE13) -> -23370.646 | AC11: =IF('Model inputs'!AE11="","",'Model inputs'!AE11) -> -4433.302 | AD11: =IF('Model inputs'!AH10="","",'Model inputs'!AH10) -> -45880.8 | AE11: =IF('Model inputs'!AH12="","",'Model inputs'!AH12) -> -42823.575 | AF11: =IF('Model inputs'!AH13="","",'Model inputs'!AH13) -> -24647.195 | AG11: =IF('Model inputs'!AH11="","",'Model inputs'!AH11) -> -879.7795

Sheet Model inputs
A1: Model inputs
A2: Integration values are aggregated snapshots; raw source records are not included.
A4: Variables
A5: Variable / segment | B5: 2026-01 | C5: 2026-02 | D5: 2026-03 | E5: 2026-04 | F5: 2026-05 | G5: 2026-06 | H5: 2026-07 | I5: 2026-08 | J5: 2026-09 | K5: 2026-10 | L5: 2026-11 | M5: 2026-12 | N5: 2027-01 | O5: 2027-02 | P5: 2027-03 | Q5: 2027-04 | R5: 2027-05 | S5: 2027-06 | T5: 2027-07 | U5: 2027-08 | V5: 2027-09 | W5: 2027-10 | X5: 2027-11 | Y5: 2027-12 | Z5: 2028-01 | AA5: 2028-02 | AB5: 2028-03 | AC5: 2028-04 | AD5: 2028-05 | AE5: 2028-06 | AF5: 2028-07 | AG5: 2028-08 | AH5: 2028-09 | AI5: Value
A6: Cash balance · Main Scenario | B6: =IF('Model inputs'!AI74="","",'Model inputs'!AI74) -> 3000 | C6: =IF('Model inputs'!AI74="","",'Model inputs'!AI74) -> 3000 | D6: =IF('Model inputs'!AI74="","",'Model inputs'!AI74) -> 3000 | E6: =IF('Model inputs'!AI74="","",'Model inputs'!AI74) -> 3000 | F6: =IF('Model inputs'!AI74="","",'Model inputs'!AI74) -> 3000 | G6: =IF('Model inputs'!AI74="","",'Model inputs'!AI74) -> 3000 | H6: =IF('Model inputs'!AI74="","",'Model inputs'!AI74) -> 3000 | I6: =IF('Model inputs'!AI74="","",'Model inputs'!AI74) -> 3000 | J6: =IF('Model inputs'!AI74="","",'Model inputs'!AI74) -> 3000 | K6: ='Model inputs'!J6+'Model inputs'!K22 -> 2830 | L6: ='Model inputs'!K6+'Model inputs'!L22 -> 2562.5 | M6: ='Model inputs'!L6+'Model inputs'!M22 -> 2542.35 | N6: ='Model inputs'!M6+'Model inputs'!N22 -> 2522.2 | O6: ='Model inputs'!N6+'Model inputs'!O22 -> 2502.05 | P6: ='Model inputs'!O6+'Model inputs'!P22 -> 2481.9 | Q6: ='Model inputs'!P6+'Model inputs'!Q22 -> 2461.75 | R6: ='Model inputs'!Q6+'Model inputs'!R22 -> 2441.6 | ... AH6: ='Model inputs'!AG6+'Model inputs'!AH22 -> 2119.2
A7: Cash balance · Growth · $0.60 | B7: =IF('Model inputs'!AI75="","",'Model inputs'!AI75) -> 3000 | C7: =IF('Model inputs'!AI75="","",'Model inputs'!AI75) -> 3000 | D7: =IF('Model inputs'!AI75="","",'Model inputs'!AI75) -> 3000 | E7: =IF('Model inputs'!AI75="","",'Model inputs'!AI75) -> 3000 | F7: =IF('Model inputs'!AI75="","",'Model inputs'!AI75) -> 3000 | G7: =IF('Model inputs'!AI75="","",'Model inputs'!AI75) -> 3000 | H7: =IF('Model inputs'!AI75="","",'Model inputs'!AI75) -> 3000 | I7: =IF('Model inputs'!AI75="","",'Model inputs'!AI75) -> 3000 | J7: =IF('Model inputs'!AI75="","",'Model inputs'!AI75) -> 3000 | K7: ='Model inputs'!J7+'Model inputs'!K23 -> 2830 | L7: ='Model inputs'!K7+'Model inputs'!L23 -> 2577.125 | M7: ='Model inputs'!L7+'Model inputs'!M23 -> 2674.5563 | N7: ='Model inputs'!M7+'Model inputs'!N23 -> 2838.8453 | O7: ='Model inputs'!N7+'Model inputs'!O23 -> 3086.7066 | P7: ='Model inputs'!O7+'Model inputs'!P23 -> 3439.0333 | Q7: ='Model inputs'!P7+'Model inputs'!Q23 -> 3921.9416 | R7: ='Model inputs'!Q7+'Model inputs'!R23 -> 4568.077 | ... AH7: ='Model inputs'!AG7+'Model inputs'!AH23 -> 47120.22
A8: Cash balance · Base · $0.60 | B8: =IF('Model inputs'!AI76="","",'Model inputs'!AI76) -> 3000 | C8: =IF('Model inputs'!AI76="","",'Model inputs'!AI76) -> 3000 | D8: =IF('Model inputs'!AI76="","",'Model inputs'!AI76) -> 3000 | E8: =IF('Model inputs'!AI76="","",'Model inputs'!AI76) -> 3000 | F8: =IF('Model inputs'!AI76="","",'Model inputs'!AI76) -> 3000 | G8: =IF('Model inputs'!AI76="","",'Model inputs'!AI76) -> 3000 | H8: =IF('Model inputs'!AI76="","",'Model inputs'!AI76) -> 3000 | I8: =IF('Model inputs'!AI76="","",'Model inputs'!AI76) -> 3000 | J8: =IF('Model inputs'!AI76="","",'Model inputs'!AI76) -> 3000 | K8: ='Model inputs'!J8+'Model inputs'!K24 -> 2830 | L8: ='Model inputs'!K8+'Model inputs'!L24 -> 2577.125 | M8: ='Model inputs'!L8+'Model inputs'!M24 -> 2695.275 | N8: ='Model inputs'!M8+'Model inputs'!N24 -> 2813.425 | O8: ='Model inputs'!N8+'Model inputs'!O24 -> 2931.575 | P8: ='Model inputs'!O8+'Model inputs'!P24 -> 3049.725 | Q8: ='Model inputs'!P8+'Model inputs'!Q24 -> 3167.875 | R8: ='Model inputs'!Q8+'Model inputs'!R24 -> 3286.025 | ... AH8: ='Model inputs'!AG8+'Model inputs'!AH24 -> 5176.425
A9: Cash balance · Growth · $0.34 | B9: =IF('Model inputs'!AI77="","",'Model inputs'!AI77) -> 3000 | C9: =IF('Model inputs'!AI77="","",'Model inputs'!AI77) -> 3000 | D9: =IF('Model inputs'!AI77="","",'Model inputs'!AI77) -> 3000 | E9: =IF('Model inputs'!AI77="","",'Model inputs'!AI77) -> 3000 | F9: =IF('Model inputs'!AI77="","",'Model inputs'!AI77) -> 3000 | G9: =IF('Model inputs'!AI77="","",'Model inputs'!AI77) -> 3000 | H9: =IF('Model inputs'!AI77="","",'Model inputs'!AI77) -> 3000 | I9: =IF('Model inputs'!AI77="","",'Model inputs'!AI77) -> 3000 | J9: =IF('Model inputs'!AI77="","",'Model inputs'!AI77) -> 3000 | K9: ='Model inputs'!J9+'Model inputs'!K25 -> 2830 | L9: ='Model inputs'!K9+'Model inputs'!L25 -> 2562.5 | M9: ='Model inputs'!L9+'Model inputs'!M25 -> 2517.975 | N9: ='Model inputs'!M9+'Model inputs'!N25 -> 2504.8187 | O9: ='Model inputs'!N9+'Model inputs'!O25 -> 2530.8734 | P9: ='Model inputs'!O9+'Model inputs'!P25 -> 2605.9418 | Q9: ='Model inputs'!P9+'Model inputs'!Q25 -> 2742.2772 | R9: ='Model inputs'!Q9+'Model inputs'!R25 -> 2955.1966 | ... AH9: ='Model inputs'!AG9+'Model inputs'!AH25 -> 23352.805
A10: Cash balance with salary · Main Scenario | B10: =IF('Model inputs'!AI74="","",'Model inputs'!AI74) -> 3000 | C10: =IF('Model inputs'!AI74="","",'Model inputs'!AI74) -> 3000 | D10: =IF('Model inputs'!AI74="","",'Model inputs'!AI74) -> 3000 | E10: =IF('Model inputs'!AI74="","",'Model inputs'!AI74) -> 3000 | F10: =IF('Model inputs'!AI74="","",'Model inputs'!AI74) -> 3000 | G10: =IF('Model inputs'!AI74="","",'Model inputs'!AI74) -> 3000 | H10: =IF('Model inputs'!AI74="","",'Model inputs'!AI74) -> 3000 | I10: =IF('Model inputs'!AI74="","",'Model inputs'!AI74) -> 3000 | J10: =IF('Model inputs'!AI74="","",'Model inputs'!AI74) -> 3000 | K10: ='Model inputs'!J10+'Model inputs'!K66 -> 830 | L10: ='Model inputs'!K10+'Model inputs'!L66 -> -1437.5 | M10: ='Model inputs'!L10+'Model inputs'!M66 -> -3457.65 | N10: ='Model inputs'!M10+'Model inputs'!N66 -> -5477.8 | O10: ='Model inputs'!N10+'Model inputs'!O66 -> -7497.95 | P10: ='Model inputs'!O10+'Model inputs'!P66 -> -9518.1 | Q10: ='Model inputs'!P10+'Model inputs'!Q66 -> -11538.25 | R10: ='Model inputs'!Q10+'Model inputs'!R66 -> -13558.4 | ... AH10: ='Model inputs'!AG10+'Model inputs'!AH66 -> -45880.8
A11: Cash balance with salary · Growth · $0.60 | B11: =IF('Model inputs'!AI75="","",'Model inputs'!AI75) -> 3000 | C11: =IF('Model inputs'!AI75="","",'Model inputs'!AI75) -> 3000 | D11: =IF('Model inputs'!AI75="","",'Model inputs'!AI75) -> 3000 | E11: =IF('Model inputs'!AI75="","",'Model inputs'!AI75) -> 3000 | F11: =IF('Model inputs'!AI75="","",'Model inputs'!AI75) -> 3000 | G11: =IF('Model inputs'!AI75="","",'Model inputs'!AI75) -> 3000 | H11: =IF('Model inputs'!AI75="","",'Model inputs'!AI75) -> 3000 | I11: =IF('Model inputs'!AI75="","",'Model inputs'!AI75) -> 3000 | J11: =IF('Model inputs'!AI75="","",'Model inputs'!AI75) -> 3000 | K11: ='Model inputs'!J11+'Model inputs'!K67 -> 830 | L11: ='Model inputs'!K11+'Model inputs'!L67 -> -1422.875 | M11: ='Model inputs'!L11+'Model inputs'!M67 -> -3325.4437 | N11: ='Model inputs'!M11+'Model inputs'!N67 -> -5161.1547 | O11: ='Model inputs'!N11+'Model inputs'!O67 -> -6913.2934 | P11: ='Model inputs'!O11+'Model inputs'!P67 -> -8560.9667 | Q11: ='Model inputs'!P11+'Model inputs'!Q67 -> -10078.058 | R11: ='Model inputs'!Q11+'Model inputs'!R67 -> -11431.923 | ... AH11: ='Model inputs'!AG11+'Model inputs'!AH67 -> -879.7795
A12: Cash balance with salary · Base · $0.60 | B12: =IF('Model inputs'!AI76="","",'Model inputs'!AI76) -> 3000 | C12: =IF('Model inputs'!AI76="","",'Model inputs'!AI76) -> 3000 | D12: =IF('Model inputs'!AI76="","",'Model inputs'!AI76) -> 3000 | E12: =IF('Model inputs'!AI76="","",'Model inputs'!AI76) -> 3000 | F12: =IF('Model inputs'!AI76="","",'Model inputs'!AI76) -> 3000 | G12: =IF('Model inputs'!AI76="","",'Model inputs'!AI76) -> 3000 | H12: =IF('Model inputs'!AI76="","",'Model inputs'!AI76) -> 3000 | I12: =IF('Model inputs'!AI76="","",'Model inputs'!AI76) -> 3000 | J12: =IF('Model inputs'!AI76="","",'Model inputs'!AI76) -> 3000 | K12: ='Model inputs'!J12+'Model inputs'!K68 -> 830 | L12: ='Model inputs'!K12+'Model inputs'!L68 -> -1422.875 | M12: ='Model inputs'!L12+'Model inputs'!M68 -> -3304.725 | N12: ='Model inputs'!M12+'Model inputs'!N68 -> -5186.575 | O12: ='Model inputs'!N12+'Model inputs'!O68 -> -7068.425 | P12: ='Model inputs'!O12+'Model inputs'!P68 -> -8950.275 | Q12: ='Model inputs'!P12+'Model inputs'!Q68 -> -10832.125 | R12: ='Model inputs'!Q12+'Model inputs'!R68 -> -12713.975 | ... AH12: ='Model inputs'!AG12+'Model inputs'!AH68 -> -42823.575
A13: Cash balance with salary · Growth · $0.34 | B13: =IF('Model inputs'!AI77="","",'Model inputs'!AI77) -> 3000 | C13: =IF('Model inputs'!AI77="","",'Model inputs'!AI77) -> 3000 | D13: =IF('Model inputs'!AI77="","",'Model inputs'!AI77) -> 3000 | E13: =IF('Model inputs'!AI77="","",'Model inputs'!AI77) -> 3000 | F13: =IF('Model inputs'!AI77="","",'Model inputs'!AI77) -> 3000 | G13: =IF('Model inputs'!AI77="","",'Model inputs'!AI77) -> 3000 | H13: =IF('Model inputs'!AI77="","",'Model inputs'!AI77) -> 3000 | I13: =IF('Model inputs'!AI77="","",'Model inputs'!AI77) -> 3000 | J13: =IF('Model inputs'!AI77="","",'Model inputs'!AI77) -> 3000 | K13: ='Model inputs'!J13+'Model inputs'!K69 -> 830 | L13: ='Model inputs'!K13+'Model inputs'!L69 -> -1437.5 | M13: ='Model inputs'!L13+'Model inputs'!M69 -> -3482.025 | N13: ='Model inputs'!M13+'Model inputs'!N69 -> -5495.1812 | O13: ='Model inputs'!N13+'Model inputs'!O69 -> -7469.1266 | P13: ='Model inputs'!O13+'Model inputs'!P69 -> -9394.0582 | Q13: ='Model inputs'!P13+'Model inputs'!Q69 -> -11257.723 | R13: ='Model inputs'!Q13+'Model inputs'!R69 -> -13044.803 | ... AH13: ='Model inputs'!AG13+'Model inputs'!AH69 -> -24647.195
A14: Gross profit · Main Scenario | B14: 0 | C14: 0 | D14: 0 | E14: 0 | F14: 0 | G14: 0 | H14: 0 | I14: 0 | J14: 0 | K14: ='Model inputs'!K30-'Model inputs'!K38 -> 0 | L14: ='Model inputs'!L30-'Model inputs'!L38 -> 149.85 | M14: ='Model inputs'!M30-'Model inputs'!M38 -> 149.85 | N14: ='Model inputs'!N30-'Model inputs'!N38 -> 149.85 | O14: ='Model inputs'!O30-'Model inputs'!O38 -> 149.85 | P14: ='Model inputs'!P30-'Model inputs'!P38 -> 149.85 | Q14: ='Model inputs'!Q30-'Model inputs'!Q38 -> 149.85 | R14: ='Model inputs'!R30-'Model inputs'!R38 -> 149.85 | ... AH14: ='Model inputs'!AH30-'Model inputs'!AH38 -> 149.85
A15: Gross profit · Growth · $0.60 | B15: 0 | C15: 0 | D15: 0 | E15: 0 | F15: 0 | G15: 0 | H15: 0 | I15: 0 | J15: 0 | K15: ='Model inputs'!K31-'Model inputs'!K39 -> 0 | L15: ='Model inputs'!L31-'Model inputs'!L39 -> 288.15 | M15: ='Model inputs'!M31-'Model inputs'!M39 -> 360.1875 | N15: ='Model inputs'!N31-'Model inputs'!N39 -> 450.23438 | O15: ='Model inputs'!O31-'Model inputs'!O39 -> 562.79297 | P15: ='Model inputs'!P31-'Model inputs'!P39 -> 703.49121 | Q15: ='Model inputs'!Q31-'Model inputs'!Q39 -> 879.36401 | R15: ='Model inputs'!R31-'Model inputs'!R39 -> 1099.205 | ... AH15: ='Model inputs'!AH31-'Model inputs'!AH39 -> 3354.5075
A16: Gross profit · Base · $0.60 | B16: 0 | C16: 0 | D16: 0 | E16: 0 | F16: 0 | G16: 0 | H16: 0 | I16: 0 | J16: 0 | K16: ='Model inputs'!K32-'Model inputs'!K40 -> 0 | L16: ='Model inputs'!L32-'Model inputs'!L40 -> 288.15 | M16: ='Model inputs'!M32-'Model inputs'!M40 -> 288.15 | N16: ='Model inputs'!N32-'Model inputs'!N40 -> 288.15 | O16: ='Model inputs'!O32-'Model inputs'!O40 -> 288.15 | P16: ='Model inputs'!P32-'Model inputs'!P40 -> 288.15 | Q16: ='Model inputs'!Q32-'Model inputs'!Q40 -> 288.15 | R16: ='Model inputs'!R32-'Model inputs'!R40 -> 288.15 | ... AH16: ='Model inputs'!AH32-'Model inputs'!AH40 -> 288.15
A17: Gross profit · Growth · $0.34 | B17: 0 | C17: 0 | D17: 0 | E17: 0 | F17: 0 | G17: 0 | H17: 0 | I17: 0 | J17: 0 | K17: ='Model inputs'!K33-'Model inputs'!K41 -> 0 | L17: ='Model inputs'!L33-'Model inputs'!L41 -> 149.85 | M17: ='Model inputs'!M33-'Model inputs'!M41 -> 187.3125 | N17: ='Model inputs'!N33-'Model inputs'!N41 -> 234.14063 | O17: ='Model inputs'!O33-'Model inputs'!O41 -> 292.67578 | P17: ='Model inputs'!P33-'Model inputs'!P41 -> 365.84473 | Q17: ='Model inputs'!Q33-'Model inputs'!Q41 -> 457.30591 | R17: ='Model inputs'!R33-'Model inputs'!R41 -> 571.63239 | ... AH17: ='Model inputs'!AH33-'Model inputs'!AH41 -> 1744.4836
A18: Jobs attempted · Main Scenario | B18: 0 | C18: 0 | D18: 0 | E18: 0 | F18: 0 | G18: 0 | H18: 0 | I18: 0 | J18: 0 | K18: =IF(IF(IF(ISERROR('Model inputs'!K62<1),'Model inputs'!K62<1,IF('Model inputs'!K62="","",'Model inputs'!K62<1))="",FALSE,IF(ISERROR('Model inputs'!K62<1),'Model inputs'!K62<1,IF('Model inputs'!K62="","",'Model inputs'!K62<1))),0,'Model inputs'!AI50*IF(AND((1+'Model inputs'!AI58)=0,(MIN('Model inputs'!K62,'Model inputs'!AI46)-1)=0),SQRT(-1),(1+'Model inputs'!AI58)^(MIN('Model inputs'!K62,'Model inputs'!AI46)-1))*'Model inputs'!AI82) -> 0 | L18: =IF(IF(IF(ISERROR('Model inputs'!L62<1),'Model inputs'!L62<1,IF('Model inputs'!L62="","",'Model inputs'!L62<1))="",FALSE,IF(ISERROR('Model inputs'!L62<1),'Model inputs'!L62<1,IF('Model inputs'!L62="","",'Model inputs'!L62<1))),0,'Model inputs'!AI50*IF(AND((1+'Model inputs'!AI58)=0,(MIN('Model inputs'!L62,'Model inputs'!AI46)-1)=0),SQRT(-1),(1+'Model inputs'!AI58)^(MIN('Model inputs'!L62,'Model inputs'!AI46)-1))*'Model inputs'!AI82) -> 1000 | M18: =IF(IF(IF(ISERROR('Model inputs'!M62<1),'Model inputs'!M62<1,IF('Model inputs'!M62="","",'Model inputs'!M62<1))="",FALSE,IF(ISERROR('Model inputs'!M62<1),'Model inputs'!M62<1,IF('Model inputs'!M62="","",'Model inputs'!M62<1))),0,'Model inputs'!AI50*IF(AND((1+'Model inputs'!AI58)=0,(MIN('Model inputs'!M62,'Model inputs'!AI46)-1)=0),SQRT(-1),(1+'Model inputs'!AI58)^(MIN('Model inputs'!M62,'Model inputs'!AI46)-1))*'Model inputs'!AI82) -> 1000 | N18: =IF(IF(IF(ISERROR('Model inputs'!N62<1),'Model inputs'!N62<1,IF('Model inputs'!N62="","",'Model inputs'!N62<1))="",FALSE,IF(ISERROR('Model inputs'!N62<1),'Model inputs'!N62<1,IF('Model inputs'!N62="","",'Model inputs'!N62<1))),0,'Model inputs'!AI50*IF(AND((1+'Model inputs'!AI58)=0,(MIN('Model inputs'!N62,'Model inputs'!AI46)-1)=0),SQRT(-1),(1+'Model inputs'!AI58)^(MIN('Model inputs'!N62,'Model inputs'!AI46)-1))*'Model inputs'!AI82) -> 1000 | O18: =IF(IF(IF(ISERROR('Model inputs'!O62<1),'Model inputs'!O62<1,IF('Model inputs'!O62="","",'Model inputs'!O62<1))="",FALSE,IF(ISERROR('Model inputs'!O62<1),'Model inputs'!O62<1,IF('Model inputs'!O62="","",'Model inputs'!O62<1))),0,'Model inputs'!AI50*IF(AND((1+'Model inputs'!AI58)=0,(MIN('Model inputs'!O62,'Model inputs'!AI46)-1)=0),SQRT(-1),(1+'Model inputs'!AI58)^(MIN('Model inputs'!O62,'Model inputs'!AI46)-1))*'Model inputs'!AI82) -> 1000 | P18: =IF(IF(IF(ISERROR('Model inputs'!P62<1),'Model inputs'!P62<1,IF('Model inputs'!P62="","",'Model inputs'!P62<1))="",FALSE,IF(ISERROR('Model inputs'!P62<1),'Model inputs'!P62<1,IF('Model inputs'!P62="","",'Model inputs'!P62<1))),0,'Model inputs'!AI50*IF(AND((1+'Model inputs'!AI58)=0,(MIN('Model inputs'!P62,'Model inputs'!AI46)-1)=0),SQRT(-1),(1+'Model inputs'!AI58)^(MIN('Model inputs'!P62,'Model inputs'!AI46)-1))*'Model inputs'!AI82) -> 1000 | Q18: =IF(IF(IF(ISERROR('Model inputs'!Q62<1),'Model inputs'!Q62<1,IF('Model inputs'!Q62="","",'Model inputs'!Q62<1))="",FALSE,IF(ISERROR('Model inputs'!Q62<1),'Model inputs'!Q62<1,IF('Model inputs'!Q62="","",'Model inputs'!Q62<1))),0,'Model inputs'!AI50*IF(AND((1+'Model inputs'!AI58)=0,(MIN('Model inputs'!Q62,'Model inputs'!AI46)-1)=0),SQRT(-1),(1+'Model inputs'!AI58)^(MIN('Model inputs'!Q62,'Model inputs'!AI46)-1))*'Model inputs'!AI82) -> 1000 | R18: =IF(IF(IF(ISERROR('Model inputs'!R62<1),'Model inputs'!R62<1,IF('Model inputs'!R62="","",'Model inputs'!R62<1))="",FALSE,IF(ISERROR('Model inputs'!R62<1),'Model inputs'!R62<1,IF('Model inputs'!R62="","",'Model inputs'!R62<1))),0,'Model inputs'!AI50*IF(AND((1+'Model inputs'!AI58)=0,(MIN('Model inputs'!R62,'Model inputs'!AI46)-1)=0),SQRT(-1),(1+'Model inputs'!AI58)^(MIN('Model inputs'!R62,'Model inputs'!AI46)-1))*'Model inputs'!AI82) -> 1000 | S18: =IF(IF(IF(ISERROR('Model inputs'!S62<1),'Model inputs'!S62<1,IF('Model inputs'!S62="","",'Model inputs'!S62<1))="",FALSE,IF(ISERROR('Model inputs'!S62<1),'Model inputs'!S62<1,IF('Model inputs'!S62="","",'Model inputs'!S62<1))),0,'Model inputs'!AI50*IF(AND((1+'Model inputs'!AI58)=0,(MIN('Model inputs'!S62,'Model inputs'!AI46)-1)=0),SQRT(-1),(1+'Model inputs'!AI58)^(MIN('Model inputs'!S62,'Model inputs'!AI46)-1))*'Model inputs'!AI82) -> 1000 | T18: =IF(IF(IF(ISERROR('Model inputs'!T62<1),'Model inputs'!T62<1,IF('Model inputs'!T62="","",'Model inputs'!T62<1))="",FALSE,IF(ISERROR('Model inputs'!T62<1),'Model inputs'!T62<1,IF('Model inputs'!T62="","",'Model inputs'!T62<1))),0,'Model inputs'!AI50*IF(AND((1+'Model inputs'!AI58)=0,(MIN('Model inputs'!T62,'Model inputs'!AI46)-1)=0),SQRT(-1),(1+'Model inputs'!AI58)^(MIN('Model inputs'!T62,'Model inputs'!AI46)-1))*'Model inputs'!AI82) -> 1000 | U18: =IF(IF(IF(ISERROR('Model inputs'!U62<1),'Model inputs'!U62<1,IF('Model inputs'!U62="","",'Model inputs'!U62<1))="",FALSE,IF(ISERROR('Model inputs'!U62<1),'Model inputs'!U62<1,IF('Model inputs'!U62="","",'Model inputs'!U62<1))),0,'Model inputs'!AI50*IF(AND((1+'Model inputs'!AI58)=0,(MIN('Model inputs'!U62,'Model inputs'!AI46)-1)=0),SQRT(-1),(1+'Model inputs'!AI58)^(MIN('Model inputs'!U62,'Model inputs'!AI46)-1))*'Model inputs'!AI82) -> 1000 | V18: =IF(IF(IF(ISERROR('Model inputs'!V62<1),'Model inputs'!V62<1,IF('Model inputs'!V62="","",'Model inputs'!V62<1))="",FALSE,IF(ISERROR('Model inputs'!V62<1),'Model inputs'!V62<1,IF('Model inputs'!V62="","",'Model inputs'!V62<1))),0,'Model inputs'!AI50*IF(AND((1+'Model inputs'!AI58)=0,(MIN('Model inputs'!V62,'Model inputs'!AI46)-1)=0),SQRT(-1),(1+'Model inputs'!AI58)^(MIN('Model inputs'!V62,'Model inputs'!AI46)-1))*'Model inputs'!AI82) -> 1000 | W18: =IF(IF(IF(ISERROR('Model inputs'!W62<1),'Model inputs'!W62<1,IF('Model inputs'!W62="","",'Model inputs'!W62<1))="",FALSE,IF(ISERROR('Model inputs'!W62<1),'Model inputs'!W62<1,IF('Model inputs'!W62="","",'Model inputs'!W62<1))),0,'Model inputs'!AI50*IF(AND((1+'Model inputs'!AI58)=0,(MIN('Model inputs'!W62,'Model inputs'!AI46)-1)=0),SQRT(-1),(1+'Model inputs'!AI58)^(MIN('Model inputs'!W62,'Model inputs'!AI46)-1))*'Model inputs'!AI82) -> 1000 | X18: =IF(IF(IF(ISERROR('Model inputs'!X62<1),'Model inputs'!X62<1,IF('Model inputs'!X62="","",'Model inputs'!X62<1))="",FALSE,IF(ISERROR('Model inputs'!X62<1),'Model inputs'!X62<1,IF('Model inputs'!X62="","",'Model inputs'!X62<1))),0,'Model inputs'!AI50*IF(AND((1+'Model inputs'!AI58)=0,(MIN('Model inputs'!X62,'Model inputs'!AI46)-1)=0),SQRT(-1),(1+'Model inputs'!AI58)^(MIN('Model inputs'!X62,'Model inputs'!AI46)-1))*'Model inputs'!AI82) -> 1000 | Y18: =IF(IF(IF(ISERROR('Model inputs'!Y62<1),'Model inputs'!Y62<1,IF('Model inputs'!Y62="","",'Model inputs'!Y62<1))="",FALSE,IF(ISERROR('Model inputs'!Y62<1),'Model inputs'!Y62<1,IF('Model inputs'!Y62="","",'Model inputs'!Y62<1))),0,'Model inputs'!AI50*IF(AND((1+'Model inputs'!AI58)=0,(MIN('Model inputs'!Y62,'Model inputs'!AI46)-1)=0),SQRT(-1),(1+'Model inputs'!AI58)^(MIN('Model inputs'!Y62,'Model inputs'!AI46)-1))*'Model inputs'!AI82) -> 1000 | Z18: =IF(IF(IF(ISERROR('Model inputs'!Z62<1),'Model inputs'!Z62<1,IF('Model inputs'!Z62="","",'Model inputs'!Z62<1))="",FALSE,IF(ISERROR('Model inputs'!Z62<1),'Model inputs'!Z62<1,IF('Model inputs'!Z62="","",'Model inputs'!Z62<1))),0,'Model inputs'!AI50*IF(AND((1+'Model inputs'!AI58)=0,(MIN('Model inputs'!Z62,'Model inputs'!AI46)-1)=0),SQRT(-1),(1+'Model inputs'!AI58)^(MIN('Model inputs'!Z62,'Model inputs'!AI46)-1))*'Model inputs'!AI82) -> 1000 | AA18: =IF(IF(IF(ISERROR('Model inputs'!AA62<1),'Model inputs'!AA62<1,IF('Model inputs'!AA62="","",'Model inputs'!AA62<1))="",FALSE,IF(ISERROR('Model inputs'!AA62<1),'Model inputs'!AA62<1,IF('Model inputs'!AA62="","",'Model inputs'!AA62<1))),0,'Model inputs'!AI50*IF(AND((1+'Model inputs'!AI58)=0,(MIN('Model inputs'!AA62,'Model inputs'!AI46)-1)=0),SQRT(-1),(1+'Model inputs'!AI58)^(MIN('Model inputs'!AA62,'Model inputs'!AI46)-1))*'Model inputs'!AI82) -> 1000 | AB18: =IF(IF(IF(ISERROR('Model inputs'!AB62<1),'Model inputs'!AB62<1,IF('Model inputs'!AB62="","",'Model inputs'!AB62<1))="",FALSE,IF(ISERROR('Model inputs'!AB62<1),'Model inputs'!AB62<1,IF('Model inputs'!AB62="","",'Model inputs'!AB62<1))),0,'Model inputs'!AI50*IF(AND((1+'Model inputs'!AI58)=0,(MIN('Model inputs'!AB62,'Model inputs'!AI46)-1)=0),SQRT(-1),(1+'Model inputs'!AI58)^(MIN('Model inputs'!AB62,'Model inputs'!AI46)-1))*'Model inputs'!AI82) -> 1000 | AC18: =IF(IF(IF(ISERROR('Model inputs'!AC62<1),'Model inputs'!AC62<1,IF('Model inputs'!AC62="","",'Model inputs'!AC62<1))="",FALSE,IF(ISERROR('Model inputs'!AC62<1),'Model inputs'!AC62<1,IF('Model inputs'!AC62="","",'Model inputs'!AC62<1))),0,'Model inputs'!AI50*IF(AND((1+'Model inputs'!AI58)=0,(MIN('Model inputs'!AC62,'Model inputs'!AI46)-1)=0),SQRT(-1),(1+'Model inputs'!AI58)^(MIN('Model inputs'!AC62,'Model inputs'!AI46)-1))*'Model inputs'!AI82) -> 1000 | AD18: =IF(IF(IF(ISERROR('Model inputs'!AD62<1),'Model inputs'!AD62<1,IF('Model inputs'!AD62="","",'Model inputs'!AD62<1))="",FALSE,IF(ISERROR('Model inputs'!AD62<1),'Model inputs'!AD62<1,IF('Model inputs'!AD62="","",'Model inputs'!AD62<1))),0,'Model inputs'!AI50*IF(AND((1+'Model inputs'!AI58)=0,(MIN('Model inputs'!AD62,'Model inputs'!AI46)-1)=0),SQRT(-1),(1+'Model inputs'!AI58)^(MIN('Model inputs'!AD62,'Model inputs'!AI46)-1))*'Model inputs'!AI82) -> 1000 | AE18: =IF(IF(IF(ISERROR('Model inputs'!AE62<1),'Model inputs'!AE62<1,IF('Model inputs'!AE62="","",'Model inputs'!AE62<1))="",FALSE,IF(ISERROR('Model inputs'!AE62<1),'Model inputs'!AE62<1,IF('Model inputs'!AE62="","",'Model inputs'!AE62<1))),0,'Model inputs'!AI50*IF(AND((1+'Model inputs'!AI58)=0,(MIN('Model inputs'!AE62,'Model inputs'!AI46)-1)=0),SQRT(-1),(1+'Model inputs'!AI58)^(MIN('Model inputs'!AE62,'Model inputs'!AI46)-1))*'Model inputs'!AI82) -> 1000 | AF18: =IF(IF(IF(ISERROR('Model inputs'!AF62<1),'Model inputs'!AF62<1,IF('Model inputs'!AF62="","",'Model inputs'!AF62<1))="",FALSE,IF(ISERROR('Model inputs'!AF62<1),'Model inputs'!AF62<1,IF('Model inputs'!AF62="","",'Model inputs'!AF62<1))),0,'Model inputs'!AI50*IF(AND((1+'Model inputs'!AI58)=0,(MIN('Model inputs'!AF62,'Model inputs'!AI46)-1)=0),SQRT(-1),(1+'Model inputs'!AI58)^(MIN('Model inputs'!AF62,'Model inputs'!AI46)-1))*'Model inputs'!AI82) -> 1000 | AG18: =IF(IF(IF(ISERROR('Model inputs'!AG62<1),'Model inputs'!AG62<1,IF('Model inputs'!AG62="","",'Model inputs'!AG62<1))="",FALSE,IF(ISERROR('Model inputs'!AG62<1),'Model inputs'!AG62<1,IF('Model inputs'!AG62="","",'Model inputs'!AG62<1))),0,'Model inputs'!AI50*IF(AND((1+'Model inputs'!AI58)=0,(MIN('Model inputs'!AG62,'Model inputs'!AI46)-1)=0),SQRT(-1),(1+'Model inputs'!AI58)^(MIN('Model inputs'!AG62,'Model inputs'!AI46)-1))*'Model inputs'!AI82) -> 1000 | AH18: =IF(IF(IF(ISERROR('Model inputs'!AH62<1),'Model inputs'!AH62<1,IF('Model inputs'!AH62="","",'Model inputs'!AH62<1))="",FALSE,IF(ISERROR('Model inputs'!AH62<1),'Model inputs'!AH62<1,IF('Model inputs'!AH62="","",'Model inputs'!AH62<1))),0,'Model inputs'!AI50*IF(AND((1+'Model inputs'!AI58)=0,(MIN('Model inputs'!AH62,'Model inputs'!AI46)-1)=0),SQRT(-1),(1+'Model inputs'!AI58)^(MIN('Model inputs'!AH62,'Model inputs'!AI46)-1))*'Model inputs'!AI82) -> 1000
A19: Jobs attempted · Growth · $0.60 | B19: 0 | C19: 0 | D19: 0 | E19: 0 | F19: 0 | G19: 0 | H19: 0 | I19: 0 | J19: 0 | K19: =IF(IF(IF(ISERROR('Model inputs'!K63<1),'Model inputs'!K63<1,IF('Model inputs'!K63="","",'Model inputs'!K63<1))="",FALSE,IF(ISERROR('Model inputs'!K63<1),'Model inputs'!K63<1,IF('Model inputs'!K63="","",'Model inputs'!K63<1))),0,'Model inputs'!AI51*IF(AND((1+'Model inputs'!AI59)=0,(MIN('Model inputs'!K63,'Model inputs'!AI47)-1)=0),SQRT(-1),(1+'Model inputs'!AI59)^(MIN('Model inputs'!K63,'Model inputs'!AI47)-1))*'Model inputs'!AI83) -> 0 | L19: =IF(IF(IF(ISERROR('Model inputs'!L63<1),'Model inputs'!L63<1,IF('Model inputs'!L63="","",'Model inputs'!L63<1))="",FALSE,IF(ISERROR('Model inputs'!L63<1),'Model inputs'!L63<1,IF('Model inputs'!L63="","",'Model inputs'!L63<1))),0,'Model inputs'!AI51*IF(AND((1+'Model inputs'!AI59)=0,(MIN('Model inputs'!L63,'Model inputs'!AI47)-1)=0),SQRT(-1),(1+'Model inputs'!AI59)^(MIN('Model inputs'!L63,'Model inputs'!AI47)-1))*'Model inputs'!AI83) -> 850 | M19: =IF(IF(IF(ISERROR('Model inputs'!M63<1),'Model inputs'!M63<1,IF('Model inputs'!M63="","",'Model inputs'!M63<1))="",FALSE,IF(ISERROR('Model inputs'!M63<1),'Model inputs'!M63<1,IF('Model inputs'!M63="","",'Model inputs'!M63<1))),0,'Model inputs'!AI51*IF(AND((1+'Model inputs'!AI59)=0,(MIN('Model inputs'!M63,'Model inputs'!AI47)-1)=0),SQRT(-1),(1+'Model inputs'!AI59)^(MIN('Model inputs'!M63,'Model inputs'!AI47)-1))*'Model inputs'!AI83) -> 1062.5 | N19: =IF(IF(IF(ISERROR('Model inputs'!N63<1),'Model inputs'!N63<1,IF('Model inputs'!N63="","",'Model inputs'!N63<1))="",FALSE,IF(ISERROR('Model inputs'!N63<1),'Model inputs'!N63<1,IF('Model inputs'!N63="","",'Model inputs'!N63<1))),0,'Model inputs'!AI51*IF(AND((1+'Model inputs'!AI59)=0,(MIN('Model inputs'!N63,'Model inputs'!AI47)-1)=0),SQRT(-1),(1+'Model inputs'!AI59)^(MIN('Model inputs'!N63,'Model inputs'!AI47)-1))*'Model inputs'!AI83) -> 1328.125 | O19: =IF(IF(IF(ISERROR('Model inputs'!O63<1),'Model inputs'!O63<1,IF('Model inputs'!O63="","",'Model inputs'!O63<1))="",FALSE,IF(ISERROR('Model inputs'!O63<1),'Model inputs'!O63<1,IF('Model inputs'!O63="","",'Model inputs'!O63<1))),0,'Model inputs'!AI51*IF(AND((1+'Model inputs'!AI59)=0,(MIN('Model inputs'!O63,'Model inputs'!AI47)-1)=0),SQRT(-1),(1+'Model inputs'!AI59)^(MIN('Model inputs'!O63,'Model inputs'!AI47)-1))*'Model inputs'!AI83) -> 1660.1562 | P19: =IF(IF(IF(ISERROR('Model inputs'!P63<1),'Model inputs'!P63<1,IF('Model inputs'!P63="","",'Model inputs'!P63<1))="",FALSE,IF(ISERROR('Model inputs'!P63<1),'Model inputs'!P63<1,IF('Model inputs'!P63="","",'Model inputs'!P63<1))),0,'Model inputs'!AI51*IF(AND((1+'Model inputs'!AI59)=0,(MIN('Model inputs'!P63,'Model inputs'!AI47)-1)=0),SQRT(-1),(1+'Model inputs'!AI59)^(MIN('Model inputs'!P63,'Model inputs'!AI47)-1))*'Model inputs'!AI83) -> 2075.1953 | Q19: =IF(IF(IF(ISERROR('Model inputs'!Q63<1),'Model inputs'!Q63<1,IF('Model inputs'!Q63="","",'Model inputs'!Q63<1))="",FALSE,IF(ISERROR('Model inputs'!Q63<1),'Model inputs'!Q63<1,IF('Model inputs'!Q63="","",'Model inputs'!Q63<1))),0,'Model inputs'!AI51*IF(AND((1+'Model inputs'!AI59)=0,(MIN('Model inputs'!Q63,'Model inputs'!AI47)-1)=0),SQRT(-1),(1+'Model inputs'!AI59)^(MIN('Model inputs'!Q63,'Model inputs'!AI47)-1))*'Model inputs'!AI83) -> 2593.9941 | R19: =IF(IF(IF(ISERROR('Model inputs'!R63<1),'Model inputs'!R63<1,IF('Model inputs'!R63="","",'Model inputs'!R63<1))="",FALSE,IF(ISERROR('Model inputs'!R63<1),'Model inputs'!R63<1,IF('Model inputs'!R63="","",'Model inputs'!R63<1))),0,'Model inputs'!AI51*IF(AND((1+'Model inputs'!AI59)=0,(MIN('Model inputs'!R63,'Model inputs'!AI47)-1)=0),SQRT(-1),(1+'Model inputs'!AI59)^(MIN('Model inputs'!R63,'Model inputs'!AI47)-1))*'Model inputs'!AI83) -> 3242.4927 | S19: =IF(IF(IF(ISERROR('Model inputs'!S63<1),'Model inputs'!S63<1,IF('Model inputs'!S63="","",'Model inputs'!S63<1))="",FALSE,IF(ISERROR('Model inputs'!S63<1),'Model inputs'!S63<1,IF('Model inputs'!S63="","",'Model inputs'!S63<1))),0,'Model inputs'!AI51*IF(AND((1+'Model inputs'!AI59)=0,(MIN('Model inputs'!S63,'Model inputs'!AI47)-1)=0),SQRT(-1),(1+'Model inputs'!AI59)^(MIN('Model inputs'!S63,'Model inputs'!AI47)-1))*'Model inputs'!AI83) -> 4053.1158 | T19: =IF(IF(IF(ISERROR('Model inputs'!T63<1),'Model inputs'!T63<1,IF('Model inputs'!T63="","",'Model inputs'!T63<1))="",FALSE,IF(ISERROR('Model inputs'!T63<1),'Model inputs'!T63<1,IF('Model inputs'!T63="","",'Model inputs'!T63<1))),0,'Model inputs'!AI51*IF(AND((1+'Model inputs'!AI59)=0,(MIN('Model inputs'!T63,'Model inputs'!AI47)-1)=0),SQRT(-1),(1+'Model inputs'!AI59)^(MIN('Model inputs'!T63,'Model inputs'!AI47)-1))*'Model inputs'!AI83) -> 5066.3948 | U19: =IF(IF(IF(ISERROR('Model inputs'!U63<1),'Model inputs'!U63<1,IF('Model inputs'!U63="","",'Model inputs'!U63<1))="",FALSE,IF(ISERROR('Model inputs'!U63<1),'Model inputs'!U63<1,IF('Model inputs'!U63="","",'Model inputs'!U63<1))),0,'Model inputs'!AI51*IF(AND((1+'Model inputs'!AI59)=0,(MIN('Model inputs'!U63,'Model inputs'!AI47)-1)=0),SQRT(-1),(1+'Model inputs'!AI59)^(MIN('Model inputs'!U63,'Model inputs'!AI47)-1))*'Model inputs'!AI83) -> 6332.9935 | V19: =IF(IF(IF(ISERROR('Model inputs'!V63<1),'Model inputs'!V63<1,IF('Model inputs'!V63="","",'Model inputs'!V63<1))="",FALSE,IF(ISERROR('Model inputs'!V63<1),'Model inputs'!V63<1,IF('Model inputs'!V63="","",'Model inputs'!V63<1))),0,'Model inputs'!AI51*IF(AND((1+'Model inputs'!AI59)=0,(MIN('Model inputs'!V63,'Model inputs'!AI47)-1)=0),SQRT(-1),(1+'Model inputs'!AI59)^(MIN('Model inputs'!V63,'Model inputs'!AI47)-1))*'Model inputs'!AI83) -> 7916.2419 | W19: =IF(IF(IF(ISERROR('Model inputs'!W63<1),'Model inputs'!W63<1,IF('Model inputs'!W63="","",'Model inputs'!W63<1))="",FALSE,IF(ISERROR('Model inputs'!W63<1),'Model inputs'!W63<1,IF('Model inputs'!W63="","",'Model inputs'!W63<1))),0,'Model inputs'!AI51*IF(AND((1+'Model inputs'!AI59)=0,(MIN('Model inputs'!W63,'Model inputs'!AI47)-1)=0),SQRT(-1),(1+'Model inputs'!AI59)^(MIN('Model inputs'!W63,'Model inputs'!AI47)-1))*'Model inputs'!AI83) -> 9895.3024 | X19: =IF(IF(IF(ISERROR('Model inputs'!X63<1),'Model inputs'!X63<1,IF('Model inputs'!X63="","",'Model inputs'!X63<1))="",FALSE,IF(ISERROR('Model inputs'!X63<1),'Model inputs'!X63<1,IF('Model inputs'!X63="","",'Model inputs'!X63<1))),0,'Model inputs'!AI51*IF(AND((1+'Model inputs'!AI59)=0,(MIN('Model inputs'!X63,'Model inputs'!AI47)-1)=0),SQRT(-1),(1+'Model inputs'!AI59)^(MIN('Model inputs'!X63,'Model inputs'!AI47)-1))*'Model inputs'!AI83) -> 9895.3024 | Y19: =IF(IF(IF(ISERROR('Model inputs'!Y63<1),'Model inputs'!Y63<1,IF('Model inputs'!Y63="","",'Model inputs'!Y63<1))="",FALSE,IF(ISERROR('Model inputs'!Y63<1),'Model inputs'!Y63<1,IF('Model inputs'!Y63="","",'Model inputs'!Y63<1))),0,'Model inputs'!AI51*IF(AND((1+'Model inputs'!AI59)=0,(MIN('Model inputs'!Y63,'Model inputs'!AI47)-1)=0),SQRT(-1),(1+'Model inputs'!AI59)^(MIN('Model inputs'!Y63,'Model inputs'!AI47)-1))*'Model inputs'!AI83) -> 9895.3024 | Z19: =IF(IF(IF(ISERROR('Model inputs'!Z63<1),'Model inputs'!Z63<1,IF('Model inputs'!Z63="","",'Model inputs'!Z63<1))="",FALSE,IF(ISERROR('Model inputs'!Z63<1),'Model inputs'!Z63<1,IF('Model inputs'!Z63="","",'Model inputs'!Z63<1))),0,'Model inputs'!AI51*IF(AND((1+'Model inputs'!AI59)=0,(MIN('Model inputs'!Z63,'Model inputs'!AI47)-1)=0),SQRT(-1),(1+'Model inputs'!AI59)^(MIN('Model inputs'!Z63,'Model inputs'!AI47)-1))*'Model inputs'!AI83) -> 9895.3024 | AA19: =IF(IF(IF(ISERROR('Model inputs'!AA63<1),'Model inputs'!AA63<1,IF('Model inputs'!AA63="","",'Model inputs'!AA63<1))="",FALSE,IF(ISERROR('Model inputs'!AA63<1),'Model inputs'!AA63<1,IF('Model inputs'!AA63="","",'Model inputs'!AA63<1))),0,'Model inputs'!AI51*IF(AND((1+'Model inputs'!AI59)=0,(MIN('Model inputs'!AA63,'Model inputs'!AI47)-1)=0),SQRT(-1),(1+'Model inputs'!AI59)^(MIN('Model inputs'!AA63,'Model inputs'!AI47)-1))*'Model inputs'!AI83) -> 9895.3024 | AB19: =IF(IF(IF(ISERROR('Model inputs'!AB63<1),'Model inputs'!AB63<1,IF('Model inputs'!AB63="","",'Model inputs'!AB63<1))="",FALSE,IF(ISERROR('Model inputs'!AB63<1),'Model inputs'!AB63<1,IF('Model inputs'!AB63="","",'Model inputs'!AB63<1))),0,'Model inputs'!AI51*IF(AND((1+'Model inputs'!AI59)=0,(MIN('Model inputs'!AB63,'Model inputs'!AI47)-1)=0),SQRT(-1),(1+'Model inputs'!AI59)^(MIN('Model inputs'!AB63,'Model inputs'!AI47)-1))*'Model inputs'!AI83) -> 9895.3024 | AC19: =IF(IF(IF(ISERROR('Model inputs'!AC63<1),'Model inputs'!AC63<1,IF('Model inputs'!AC63="","",'Model inputs'!AC63<1))="",FALSE,IF(ISERROR('Model inputs'!AC63<1),'Model inputs'!AC63<1,IF('Model inputs'!AC63="","",'Model inputs'!AC63<1))),0,'Model inputs'!AI51*IF(AND((1+'Model inputs'!AI59)=0,(MIN('Model inputs'!AC63,'Model inputs'!AI47)-1)=0),SQRT(-1),(1+'Model inputs'!AI59)^(MIN('Model inputs'!AC63,'Model inputs'!AI47)-1))*'Model inputs'!AI83) -> 9895.3024 | AD19: =IF(IF(IF(ISERROR('Model inputs'!AD63<1),'Model inputs'!AD63<1,IF('Model inputs'!AD63="","",'Model inputs'!AD63<1))="",FALSE,IF(ISERROR('Model inputs'!AD63<1),'Model inputs'!AD63<1,IF('Model inputs'!AD63="","",'Model inputs'!AD63<1))),0,'Model inputs'!AI51*IF(AND((1+'Model inputs'!AI59)=0,(MIN('Model inputs'!AD63,'Model inputs'!AI47)-1)=0),SQRT(-1),(1+'Model inputs'!AI59)^(MIN('Model inputs'!AD63,'Model inputs'!AI47)-1))*'Model inputs'!AI83) -> 9895.3024 | AE19: =IF(IF(IF(ISERROR('Model inputs'!AE63<1),'Model inputs'!AE63<1,IF('Model inputs'!AE63="","",'Model inputs'!AE63<1))="",FALSE,IF(ISERROR('Model inputs'!AE63<1),'Model inputs'!AE63<1,IF('Model inputs'!AE63="","",'Model inputs'!AE63<1))),0,'Model inputs'!AI51*IF(AND((1+'Model inputs'!AI59)=0,(MIN('Model inputs'!AE63,'Model inputs'!AI47)-1)=0),SQRT(-1),(1+'Model inputs'!AI59)^(MIN('Model inputs'!AE63,'Model inputs'!AI47)-1))*'Model inputs'!AI83) -> 9895.3024 | AF19: =IF(IF(IF(ISERROR('Model inputs'!AF63<1),'Model inputs'!AF63<1,IF('Model inputs'!AF63="","",'Model inputs'!AF63<1))="",FALSE,IF(ISERROR('Model inputs'!AF63<1),'Model inputs'!AF63<1,IF('Model inputs'!AF63="","",'Model inputs'!AF63<1))),0,'Model inputs'!AI51*IF(AND((1+'Model inputs'!AI59)=0,(MIN('Model inputs'!AF63,'Model inputs'!AI47)-1)=0),SQRT(-1),(1+'Model inputs'!AI59)^(MIN('Model inputs'!AF63,'Model inputs'!AI47)-1))*'Model inputs'!AI83) -> 9895.3024 | AG19: =IF(IF(IF(ISERROR('Model inputs'!AG63<1),'Model inputs'!AG63<1,IF('Model inputs'!AG63="","",'Model inputs'!AG63<1))="",FALSE,IF(ISERROR('Model inputs'!AG63<1),'Model inputs'!AG63<1,IF('Model inputs'!AG63="","",'Model inputs'!AG63<1))),0,'Model inputs'!AI51*IF(AND((1+'Model inputs'!AI59)=0,(MIN('Model inputs'!AG63,'Model inputs'!AI47)-1)=0),SQRT(-1),(1+'Model inputs'!AI59)^(MIN('Model inputs'!AG63,'Model inputs'!AI47)-1))*'Model inputs'!AI83) -> 9895.3024 | AH19: =IF(IF(IF(ISERROR('Model inputs'!AH63<1),'Model inputs'!AH63<1,IF('Model inputs'!AH63="","",'Model inputs'!AH63<1))="",FALSE,IF(ISERROR('Model inputs'!AH63<1),'Model inputs'!AH63<1,IF('Model inputs'!AH63="","",'Model inputs'!AH63<1))),0,'Model inputs'!AI51*IF(AND((1+'Model inputs'!AI59)=0,(MIN('Model inputs'!AH63,'Model inputs'!AI47)-1)=0),SQRT(-1),(1+'Model inputs'!AI59)^(MIN('Model inputs'!AH63,'Model inputs'!AI47)-1))*'Model inputs'!AI83) -> 9895.3024
A20: Jobs attempted · Base · $0.60 | B20: 0 | C20: 0 | D20: 0 | E20: 0 | F20: 0 | G20: 0 | H20: 0 | I20: 0 | J20: 0 | K20: =IF(IF(IF(ISERROR('Model inputs'!K64<1),'Model inputs'!K64<1,IF('Model inputs'!K64="","",'Model inputs'!K64<1))="",FALSE,IF(ISERROR('Model inputs'!K64<1),'Model inputs'!K64<1,IF('Model inputs'!K64="","",'Model inputs'!K64<1))),0,'Model inputs'!AI52*IF(AND((1+'Model inputs'!AI60)=0,(MIN('Model inputs'!K64,'Model inputs'!AI48)-1)=0),SQRT(-1),(1+'Model inputs'!AI60)^(MIN('Model inputs'!K64,'Model inputs'!AI48)-1))*'Model inputs'!AI84) -> 0 | L20: =IF(IF(IF(ISERROR('Model inputs'!L64<1),'Model inputs'!L64<1,IF('Model inputs'!L64="","",'Model inputs'!L64<1))="",FALSE,IF(ISERROR('Model inputs'!L64<1),'Model inputs'!L64<1,IF('Model inputs'!L64="","",'Model inputs'!L64<1))),0,'Model inputs'!AI52*IF(AND((1+'Model inputs'!AI60)=0,(MIN('Model inputs'!L64,'Model inputs'!AI48)-1)=0),SQRT(-1),(1+'Model inputs'!AI60)^(MIN('Model inputs'!L64,'Model inputs'!AI48)-1))*'Model inputs'!AI84) -> 850 | M20: =IF(IF(IF(ISERROR('Model inputs'!M64<1),'Model inputs'!M64<1,IF('Model inputs'!M64="","",'Model inputs'!M64<1))="",FALSE,IF(ISERROR('Model inputs'!M64<1),'Model inputs'!M64<1,IF('Model inputs'!M64="","",'Model inputs'!M64<1))),0,'Model inputs'!AI52*IF(AND((1+'Model inputs'!AI60)=0,(MIN('Model inputs'!M64,'Model inputs'!AI48)-1)=0),SQRT(-1),(1+'Model inputs'!AI60)^(MIN('Model inputs'!M64,'Model inputs'!AI48)-1))*'Model inputs'!AI84) -> 850 | N20: =IF(IF(IF(ISERROR('Model inputs'!N64<1),'Model inputs'!N64<1,IF('Model inputs'!N64="","",'Model inputs'!N64<1))="",FALSE,IF(ISERROR('Model inputs'!N64<1),'Model inputs'!N64<1,IF('Model inputs'!N64="","",'Model inputs'!N64<1))),0,'Model inputs'!AI52*IF(AND((1+'Model inputs'!AI60)=0,(MIN('Model inputs'!N64,'Model inputs'!AI48)-1)=0),SQRT(-1),(1+'Model inputs'!AI60)^(MIN('Model inputs'!N64,'Model inputs'!AI48)-1))*'Model inputs'!AI84) -> 850 | O20: =IF(IF(IF(ISERROR('Model inputs'!O64<1),'Model inputs'!O64<1,IF('Model inputs'!O64="","",'Model inputs'!O64<1))="",FALSE,IF(ISERROR('Model inputs'!O64<1),'Model inputs'!O64<1,IF('Model inputs'!O64="","",'Model inputs'!O64<1))),0,'Model inputs'!AI52*IF(AND((1+'Model inputs'!AI60)=0,(MIN('Model inputs'!O64,'Model inputs'!AI48)-1)=0),SQRT(-1),(1+'Model inputs'!AI60)^(MIN('Model inputs'!O64,'Model inputs'!AI48)-1))*'Model inputs'!AI84) -> 850 | P20: =IF(IF(IF(ISERROR('Model inputs'!P64<1),'Model inputs'!P64<1,IF('Model inputs'!P64="","",'Model inputs'!P64<1))="",FALSE,IF(ISERROR('Model inputs'!P64<1),'Model inputs'!P64<1,IF('Model inputs'!P64="","",'Model inputs'!P64<1))),0,'Model inputs'!AI52*IF(AND((1+'Model inputs'!AI60)=0,(MIN('Model inputs'!P64,'Model inputs'!AI48)-1)=0),SQRT(-1),(1+'Model inputs'!AI60)^(MIN('Model inputs'!P64,'Model inputs'!AI48)-1))*'Model inputs'!AI84) -> 850 | Q20: =IF(IF(IF(ISERROR('Model inputs'!Q64<1),'Model inputs'!Q64<1,IF('Model inputs'!Q64="","",'Model inputs'!Q64<1))="",FALSE,IF(ISERROR('Model inputs'!Q64<1),'Model inputs'!Q64<1,IF('Model inputs'!Q64="","",'Model inputs'!Q64<1))),0,'Model inputs'!AI52*IF(AND((1+'Model inputs'!AI60)=0,(MIN('Model inputs'!Q64,'Model inputs'!AI48)-1)=0),SQRT(-1),(1+'Model inputs'!AI60)^(MIN('Model inputs'!Q64,'Model inputs'!AI48)-1))*'Model inputs'!AI84) -> 850 | R20: =IF(IF(IF(ISERROR('Model inputs'!R64<1),'Model inputs'!R64<1,IF('Model inputs'!R64="","",'Model inputs'!R64<1))="",FALSE,IF(ISERROR('Model inputs'!R64<1),'Model inputs'!R64<1,IF('Model inputs'!R64="","",'Model inputs'!R64<1))),0,'Model inputs'!AI52*IF(AND((1+'Model inputs'!AI60)=0,(MIN('Model inputs'!R64,'Model inputs'!AI48)-1)=0),SQRT(-1),(1+'Model inputs'!AI60)^(MIN('Model inputs'!R64,'Model inputs'!AI48)-1))*'Model inputs'!AI84) -> 850 | S20: =IF(IF(IF(ISERROR('Model inputs'!S64<1),'Model inputs'!S64<1,IF('Model inputs'!S64="","",'Model inputs'!S64<1))="",FALSE,IF(ISERROR('Model inputs'!S64<1),'Model inputs'!S64<1,IF('Model inputs'!S64="","",'Model inputs'!S64<1))),0,'Model inputs'!AI52*IF(AND((1+'Model inputs'!AI60)=0,(MIN('Model inputs'!S64,'Model inputs'!AI48)-1)=0),SQRT(-1),(1+'Model inputs'!AI60)^(MIN('Model inputs'!S64,'Model inputs'!AI48)-1))*'Model inputs'!AI84) -> 850 | T20: =IF(IF(IF(ISERROR('Model inputs'!T64<1),'Model inputs'!T64<1,IF('Model inputs'!T64="","",'Model inputs'!T64<1))="",FALSE,IF(ISERROR('Model inputs'!T64<1),'Model inputs'!T64<1,IF('Model inputs'!T64="","",'Model inputs'!T64<1))),0,'Model inputs'!AI52*IF(AND((1+'Model inputs'!AI60)=0,(MIN('Model inputs'!T64,'Model inputs'!AI48)-1)=0),SQRT(-1),(1+'Model inputs'!AI60)^(MIN('Model inputs'!T64,'Model inputs'!AI48)-1))*'Model inputs'!AI84) -> 850 | U20: =IF(IF(IF(ISERROR('Model inputs'!U64<1),'Model inputs'!U64<1,IF('Model inputs'!U64="","",'Model inputs'!U64<1))="",FALSE,IF(ISERROR('Model inputs'!U64<1),'Model inputs'!U64<1,IF('Model inputs'!U64="","",'Model inputs'!U64<1))),0,'Model inputs'!AI52*IF(AND((1+'Model inputs'!AI60)=0,(MIN('Model inputs'!U64,'Model inputs'!AI48)-1)=0),SQRT(-1),(1+'Model inputs'!AI60)^(MIN('Model inputs'!U64,'Model inputs'!AI48)-1))*'Model inputs'!AI84) -> 850 | V20: =IF(IF(IF(ISERROR('Model inputs'!V64<1),'Model inputs'!V64<1,IF('Model inputs'!V64="","",'Model inputs'!V64<1))="",FALSE,IF(ISERROR('Model inputs'!V64<1),'Model inputs'!V64<1,IF('Model inputs'!V64="","",'Model inputs'!V64<1))),0,'Model inputs'!AI52*IF(AND((1+'Model inputs'!AI60)=0,(MIN('Model inputs'!V64,'Model inputs'!AI48)-1)=0),SQRT(-1),(1+'Model inputs'!AI60)^(MIN('Model inputs'!V64,'Model inputs'!AI48)-1))*'Model inputs'!AI84) -> 850 | W20: =IF(IF(IF(ISERROR('Model inputs'!W64<1),'Model inputs'!W64<1,IF('Model inputs'!W64="","",'Model inputs'!W64<1))="",FALSE,IF(ISERROR('Model inputs'!W64<1),'Model inputs'!W64<1,IF('Model inputs'!W64="","",'Model inputs'!W64<1))),0,'Model inputs'!AI52*IF(AND((1+'Model inputs'!AI60)=0,(MIN('Model inputs'!W64,'Model inputs'!AI48)-1)=0),SQRT(-1),(1+'Model inputs'!AI60)^(MIN('Model inputs'!W64,'Model inputs'!AI48)-1))*'Model inputs'!AI84) -> 850 | X20: =IF(IF(IF(ISERROR('Model inputs'!X64<1),'Model inputs'!X64<1,IF('Model inputs'!X64="","",'Model inputs'!X64<1))="",FALSE,IF(ISERROR('Model inputs'!X64<1),'Model inputs'!X64<1,IF('Model inputs'!X64="","",'Model inputs'!X64<1))),0,'Model inputs'!AI52*IF(AND((1+'Model inputs'!AI60)=0,(MIN('Model inputs'!X64,'Model inputs'!AI48)-1)=0),SQRT(-1),(1+'Model inputs'!AI60)^(MIN('Model inputs'!X64,'Model inputs'!AI48)-1))*'Model inputs'!AI84) -> 850 | Y20: =IF(IF(IF(ISERROR('Model inputs'!Y64<1),'Model inputs'!Y64<1,IF('Model inputs'!Y64="","",'Model inputs'!Y64<1))="",FALSE,IF(ISERROR('Model inputs'!Y64<1),'Model inputs'!Y64<1,IF('Model inputs'!Y64="","",'Model inputs'!Y64<1))),0,'Model inputs'!AI52*IF(AND((1+'Model inputs'!AI60)=0,(MIN('Model inputs'!Y64,'Model inputs'!AI48)-1)=0),SQRT(-1),(1+'Model inputs'!AI60)^(MIN('Model inputs'!Y64,'Model inputs'!AI48)-1))*'Model inputs'!AI84) -> 850 | Z20: =IF(IF(IF(ISERROR('Model inputs'!Z64<1),'Model inputs'!Z64<1,IF('Model inputs'!Z64="","",'Model inputs'!Z64<1))="",FALSE,IF(ISERROR('Model inputs'!Z64<1),'Model inputs'!Z64<1,IF('Model inputs'!Z64="","",'Model inputs'!Z64<1))),0,'Model inputs'!AI52*IF(AND((1+'Model inputs'!AI60)=0,(MIN('Model inputs'!Z64,'Model inputs'!AI48)-1)=0),SQRT(-1),(1+'Model inputs'!AI60)^(MIN('Model inputs'!Z64,'Model inputs'!AI48)-1))*'Model inputs'!AI84) -> 850 | AA20: =IF(IF(IF(ISERROR('Model inputs'!AA64<1),'Model inputs'!AA64<1,IF('Model inputs'!AA64="","",'Model inputs'!AA64<1))="",FALSE,IF(ISERROR('Model inputs'!AA64<1),'Model inputs'!AA64<1,IF('Model inputs'!AA64="","",'Model inputs'!AA64<1))),0,'Model inputs'!AI52*IF(AND((1+'Model inputs'!AI60)=0,(MIN('Model inputs'!AA64,'Model inputs'!AI48)-1)=0),SQRT(-1),(1+'Model inputs'!AI60)^(MIN('Model inputs'!AA64,'Model inputs'!AI48)-1))*'Model inputs'!AI84) -> 850 | AB20: =IF(IF(IF(ISERROR('Model inputs'!AB64<1),'Model inputs'!AB64<1,IF('Model inputs'!AB64="","",'Model inputs'!AB64<1))="",FALSE,IF(ISERROR('Model inputs'!AB64<1),'Model inputs'!AB64<1,IF('Model inputs'!AB64="","",'Model inputs'!AB64<1))),0,'Model inputs'!AI52*IF(AND((1+'Model inputs'!AI60)=0,(MIN('Model inputs'!AB64,'Model inputs'!AI48)-1)=0),SQRT(-1),(1+'Model inputs'!AI60)^(MIN('Model inputs'!AB64,'Model inputs'!AI48)-1))*'Model inputs'!AI84) -> 850 | AC20: =IF(IF(IF(ISERROR('Model inputs'!AC64<1),'Model inputs'!AC64<1,IF('Model inputs'!AC64="","",'Model inputs'!AC64<1))="",FALSE,IF(ISERROR('Model inputs'!AC64<1),'Model inputs'!AC64<1,IF('Model inputs'!AC64="","",'Model inputs'!AC64<1))),0,'Model inputs'!AI52*IF(AND((1+'Model inputs'!AI60)=0,(MIN('Model inputs'!AC64,'Model inputs'!AI48)-1)=0),SQRT(-1),(1+'Model inputs'!AI60)^(MIN('Model inputs'!AC64,'Model inputs'!AI48)-1))*'Model inputs'!AI84) -> 850 | AD20: =IF(IF(IF(ISERROR('Model inputs'!AD64<1),'Model inputs'!AD64<1,IF('Model inputs'!AD64="","",'Model inputs'!AD64<1))="",FALSE,IF(ISERROR('Model inputs'!AD64<1),'Model inputs'!AD64<1,IF('Model inputs'!AD64="","",'Model inputs'!AD64<1))),0,'Model inputs'!AI52*IF(AND((1+'Model inputs'!AI60)=0,(MIN('Model inputs'!AD64,'Model inputs'!AI48)-1)=0),SQRT(-1),(1+'Model inputs'!AI60)^(MIN('Model inputs'!AD64,'Model inputs'!AI48)-1))*'Model inputs'!AI84) -> 850 | AE20: =IF(IF(IF(ISERROR('Model inputs'!AE64<1),'Model inputs'!AE64<1,IF('Model inputs'!AE64="","",'Model inputs'!AE64<1))="",FALSE,IF(ISERROR('Model inputs'!AE64<1),'Model inputs'!AE64<1,IF('Model inputs'!AE64="","",'Model inputs'!AE64<1))),0,'Model inputs'!AI52*IF(AND((1+'Model inputs'!AI60)=0,(MIN('Model inputs'!AE64,'Model inputs'!AI48)-1)=0),SQRT(-1),(1+'Model inputs'!AI60)^(MIN('Model inputs'!AE64,'Model inputs'!AI48)-1))*'Model inputs'!AI84) -> 850 | AF20: =IF(IF(IF(ISERROR('Model inputs'!AF64<1),'Model inputs'!AF64<1,IF('Model inputs'!AF64="","",'Model inputs'!AF64<1))="",FALSE,IF(ISERROR('Model inputs'!AF64<1),'Model inputs'!AF64<1,IF('Model inputs'!AF64="","",'Model inputs'!AF64<1))),0,'Model inputs'!AI52*IF(AND((1+'Model inputs'!AI60)=0,(MIN('Model inputs'!AF64,'Model inputs'!AI48)-1)=0),SQRT(-1),(1+'Model inputs'!AI60)^(MIN('Model inputs'!AF64,'Model inputs'!AI48)-1))*'Model inputs'!AI84) -> 850 | AG20: =IF(IF(IF(ISERROR('Model inputs'!AG64<1),'Model inputs'!AG64<1,IF('Model inputs'!AG64="","",'Model inputs'!AG64<1))="",FALSE,IF(ISERROR('Model inputs'!AG64<1),'Model inputs'!AG64<1,IF('Model inputs'!AG64="","",'Model inputs'!AG64<1))),0,'Model inputs'!AI52*IF(AND((1+'Model inputs'!AI60)=0,(MIN('Model inputs'!AG64,'Model inputs'!AI48)-1)=0),SQRT(-1),(1+'Model inputs'!AI60)^(MIN('Model inputs'!AG64,'Model inputs'!AI48)-1))*'Model inputs'!AI84) -> 850 | AH20: =IF(IF(IF(ISERROR('Model inputs'!AH64<1),'Model inputs'!AH64<1,IF('Model inputs'!AH64="","",'Model inputs'!AH64<1))="",FALSE,IF(ISERROR('Model inputs'!AH64<1),'Model inputs'!AH64<1,IF('Model inputs'!AH64="","",'Model inputs'!AH64<1))),0,'Model inputs'!AI52*IF(AND((1+'Model inputs'!AI60)=0,(MIN('Model inputs'!AH64,'Model inputs'!AI48)-1)=0),SQRT(-1),(1+'Model inputs'!AI60)^(MIN('Model inputs'!AH64,'Model inputs'!AI48)-1))*'Model inputs'!AI84) -> 850
A21: Jobs attempted · Growth · $0.34 | B21: 0 | C21: 0 | D21: 0 | E21: 0 | F21: 0 | G21: 0 | H21: 0 | I21: 0 | J21: 0 | K21: =IF(IF(IF(ISERROR('Model inputs'!K65<1),'Model inputs'!K65<1,IF('Model inputs'!K65="","",'Model inputs'!K65<1))="",FALSE,IF(ISERROR('Model inputs'!K65<1),'Model inputs'!K65<1,IF('Model inputs'!K65="","",'Model inputs'!K65<1))),0,'Model inputs'!AI53*IF(AND((1+'Model inputs'!AI61)=0,(MIN('Model inputs'!K65,'Model inputs'!AI49)-1)=0),SQRT(-1),(1+'Model inputs'!AI61)^(MIN('Model inputs'!K65,'Model inputs'!AI49)-1))*'Model inputs'!AI85) -> 0 | L21: =IF(IF(IF(ISERROR('Model inputs'!L65<1),'Model inputs'!L65<1,IF('Model inputs'!L65="","",'Model inputs'!L65<1))="",FALSE,IF(ISERROR('Model inputs'!L65<1),'Model inputs'!L65<1,IF('Model inputs'!L65="","",'Model inputs'!L65<1))),0,'Model inputs'!AI53*IF(AND((1+'Model inputs'!AI61)=0,(MIN('Model inputs'!L65,'Model inputs'!AI49)-1)=0),SQRT(-1),(1+'Model inputs'!AI61)^(MIN('Model inputs'!L65,'Model inputs'!AI49)-1))*'Model inputs'!AI85) -> 1000 | M21: =IF(IF(IF(ISERROR('Model inputs'!M65<1),'Model inputs'!M65<1,IF('Model inputs'!M65="","",'Model inputs'!M65<1))="",FALSE,IF(ISERROR('Model inputs'!M65<1),'Model inputs'!M65<1,IF('Model inputs'!M65="","",'Model inputs'!M65<1))),0,'Model inputs'!AI53*IF(AND((1+'Model inputs'!AI61)=0,(MIN('Model inputs'!M65,'Model inputs'!AI49)-1)=0),SQRT(-1),(1+'Model inputs'!AI61)^(MIN('Model inputs'!M65,'Model inputs'!AI49)-1))*'Model inputs'!AI85) -> 1250 | N21: =IF(IF(IF(ISERROR('Model inputs'!N65<1),'Model inputs'!N65<1,IF('Model inputs'!N65="","",'Model inputs'!N65<1))="",FALSE,IF(ISERROR('Model inputs'!N65<1),'Model inputs'!N65<1,IF('Model inputs'!N65="","",'Model inputs'!N65<1))),0,'Model inputs'!AI53*IF(AND((1+'Model inputs'!AI61)=0,(MIN('Model inputs'!N65,'Model inputs'!AI49)-1)=0),SQRT(-1),(1+'Model inputs'!AI61)^(MIN('Model inputs'!N65,'Model inputs'!AI49)-1))*'Model inputs'!AI85) -> 1562.5 | O21: =IF(IF(IF(ISERROR('Model inputs'!O65<1),'Model inputs'!O65<1,IF('Model inputs'!O65="","",'Model inputs'!O65<1))="",FALSE,IF(ISERROR('Model inputs'!O65<1),'Model inputs'!O65<1,IF('Model inputs'!O65="","",'Model inputs'!O65<1))),0,'Model inputs'!AI53*IF(AND((1+'Model inputs'!AI61)=0,(MIN('Model inputs'!O65,'Model inputs'!AI49)-1)=0),SQRT(-1),(1+'Model inputs'!AI61)^(MIN('Model inputs'!O65,'Model inputs'!AI49)-1))*'Model inputs'!AI85) -> 1953.125 | P21: =IF(IF(IF(ISERROR('Model inputs'!P65<1),'Model inputs'!P65<1,IF('Model inputs'!P65="","",'Model inputs'!P65<1))="",FALSE,IF(ISERROR('Model inputs'!P65<1),'Model inputs'!P65<1,IF('Model inputs'!P65="","",'Model inputs'!P65<1))),0,'Model inputs'!AI53*IF(AND((1+'Model inputs'!AI61)=0,(MIN('Model inputs'!P65,'Model inputs'!AI49)-1)=0),SQRT(-1),(1+'Model inputs'!AI61)^(MIN('Model inputs'!P65,'Model inputs'!AI49)-1))*'Model inputs'!AI85) -> 2441.4062 | Q21: =IF(IF(IF(ISERROR('Model inputs'!Q65<1),'Model inputs'!Q65<1,IF('Model inputs'!Q65="","",'Model inputs'!Q65<1))="",FALSE,IF(ISERROR('Model inputs'!Q65<1),'Model inputs'!Q65<1,IF('Model inputs'!Q65="","",'Model inputs'!Q65<1))),0,'Model inputs'!AI53*IF(AND((1+'Model inputs'!AI61)=0,(MIN('Model inputs'!Q65,'Model inputs'!AI49)-1)=0),SQRT(-1),(1+'Model inputs'!AI61)^(MIN('Model inputs'!Q65,'Model inputs'!AI49)-1))*'Model inputs'!AI85) -> 3051.7578 | R21: =IF(IF(IF(ISERROR('Model inputs'!R65<1),'Model inputs'!R65<1,IF('Model inputs'!R65="","",'Model inputs'!R65<1))="",FALSE,IF(ISERROR('Model inputs'!R65<1),'Model inputs'!R65<1,IF('Model inputs'!R65="","",'Model inputs'!R65<1))),0,'Model inputs'!AI53*IF(AND((1+'Model inputs'!AI61)=0,(MIN('Model inputs'!R65,'Model inputs'!AI49)-1)=0),SQRT(-1),(1+'Model inputs'!AI61)^(MIN('Model inputs'!R65,'Model inputs'!AI49)-1))*'Model inputs'!AI85) -> 3814.6973 | S21: =IF(IF(IF(ISERROR('Model inputs'!S65<1),'Model inputs'!S65<1,IF('Model inputs'!S65="","",'Model inputs'!S65<1))="",FALSE,IF(ISERROR('Model inputs'!S65<1),'Model inputs'!S65<1,IF('Model inputs'!S65="","",'Model inputs'!S65<1))),0,'Model inputs'!AI53*IF(AND((1+'Model inputs'!AI61)=0,(MIN('Model inputs'!S65,'Model inputs'!AI49)-1)=0),SQRT(-1),(1+'Model inputs'!AI61)^(MIN('Model inputs'!S65,'Model inputs'!AI49)-1))*'Model inputs'!AI85) -> 4768.3716 | T21: =IF(IF(IF(ISERROR('Model inputs'!T65<1),'Model inputs'!T65<1,IF('Model inputs'!T65="","",'Model inputs'!T65<1))="",FALSE,IF(ISERROR('Model inputs'!T65<1),'Model inputs'!T65<1,IF('Model inputs'!T65="","",'Model inputs'!T65<1))),0,'Model inputs'!AI53*IF(AND((1+'Model inputs'!AI61)=0,(MIN('Model inputs'!T65,'Model inputs'!AI49)-1)=0),SQRT(-1),(1+'Model inputs'!AI61)^(MIN('Model inputs'!T65,'Model inputs'!AI49)-1))*'Model inputs'!AI85) -> 5960.4645 | U21: =IF(IF(IF(ISERROR('Model inputs'!U65<1),'Model inputs'!U65<1,IF('Model inputs'!U65="","",'Model inputs'!U65<1))="",FALSE,IF(ISERROR('Model inputs'!U65<1),'Model inputs'!U65<1,IF('Model inputs'!U65="","",'Model inputs'!U65<1))),0,'Model inputs'!AI53*IF(AND((1+'Model inputs'!AI61)=0,(MIN('Model inputs'!U65,'Model inputs'!AI49)-1)=0),SQRT(-1),(1+'Model inputs'!AI61)^(MIN('Model inputs'!U65,'Model inputs'!AI49)-1))*'Model inputs'!AI85) -> 7450.5806 | V21: =IF(IF(IF(ISERROR('Model inputs'!V65<1),'Model inputs'!V65<1,IF('Model inputs'!V65="","",'Model inputs'!V65<1))="",FALSE,IF(ISERROR('Model inputs'!V65<1),'Model inputs'!V65<1,IF('Model inputs'!V65="","",'Model inputs'!V65<1))),0,'Model inputs'!AI53*IF(AND((1+'Model inputs'!AI61)=0,(MIN('Model inputs'!V65,'Model inputs'!AI49)-1)=0),SQRT(-1),(1+'Model inputs'!AI61)^(MIN('Model inputs'!V65,'Model inputs'!AI49)-1))*'Model inputs'!AI85) -> 9313.2257 | W21: =IF(IF(IF(ISERROR('Model inputs'!W65<1),'Model inputs'!W65<1,IF('Model inputs'!W65="","",'Model inputs'!W65<1))="",FALSE,IF(ISERROR('Model inputs'!W65<1),'Model inputs'!W65<1,IF('Model inputs'!W65="","",'Model inputs'!W65<1))),0,'Model inputs'!AI53*IF(AND((1+'Model inputs'!AI61)=0,(MIN('Model inputs'!W65,'Model inputs'!AI49)-1)=0),SQRT(-1),(1+'Model inputs'!AI61)^(MIN('Model inputs'!W65,'Model inputs'!AI49)-1))*'Model inputs'!AI85) -> 11641.532 | X21: =IF(IF(IF(ISERROR('Model inputs'!X65<1),'Model inputs'!X65<1,IF('Model inputs'!X65="","",'Model inputs'!X65<1))="",FALSE,IF(ISERROR('Model inputs'!X65<1),'Model inputs'!X65<1,IF('Model inputs'!X65="","",'Model inputs'!X65<1))),0,'Model inputs'!AI53*IF(AND((1+'Model inputs'!AI61)=0,(MIN('Model inputs'!X65,'Model inputs'!AI49)-1)=0),SQRT(-1),(1+'Model inputs'!AI61)^(MIN('Model inputs'!X65,'Model inputs'!AI49)-1))*'Model inputs'!AI85) -> 11641.532 | Y21: =IF(IF(IF(ISERROR('Model inputs'!Y65<1),'Model inputs'!Y65<1,IF('Model inputs'!Y65="","",'Model inputs'!Y65<1))="",FALSE,IF(ISERROR('Model inputs'!Y65<1),'Model inputs'!Y65<1,IF('Model inputs'!Y65="","",'Model inputs'!Y65<1))),0,'Model inputs'!AI53*IF(AND((1+'Model inputs'!AI61)=0,(MIN('Model inputs'!Y65,'Model inputs'!AI49)-1)=0),SQRT(-1),(1+'Model inputs'!AI61)^(MIN('Model inputs'!Y65,'Model inputs'!AI49)-1))*'Model inputs'!AI85) -> 11641.532 | Z21: =IF(IF(IF(ISERROR('Model inputs'!Z65<1),'Model inputs'!Z65<1,IF('Model inputs'!Z65="","",'Model inputs'!Z65<1))="",FALSE,IF(ISERROR('Model inputs'!Z65<1),'Model inputs'!Z65<1,IF('Model inputs'!Z65="","",'Model inputs'!Z65<1))),0,'Model inputs'!AI53*IF(AND((1+'Model inputs'!AI61)=0,(MIN('Model inputs'!Z65,'Model inputs'!AI49)-1)=0),SQRT(-1),(1+'Model inputs'!AI61)^(MIN('Model inputs'!Z65,'Model inputs'!AI49)-1))*'Model inputs'!AI85) -> 11641.532 | AA21: =IF(IF(IF(ISERROR('Model inputs'!AA65<1),'Model inputs'!AA65<1,IF('Model inputs'!AA65="","",'Model inputs'!AA65<1))="",FALSE,IF(ISERROR('Model inputs'!AA65<1),'Model inputs'!AA65<1,IF('Model inputs'!AA65="","",'Model inputs'!AA65<1))),0,'Model inputs'!AI53*IF(AND((1+'Model inputs'!AI61)=0,(MIN('Model inputs'!AA65,'Model inputs'!AI49)-1)=0),SQRT(-1),(1+'Model inputs'!AI61)^(MIN('Model inputs'!AA65,'Model inputs'!AI49)-1))*'Model inputs'!AI85) -> 11641.532 | AB21: =IF(IF(IF(ISERROR('Model inputs'!AB65<1),'Model inputs'!AB65<1,IF('Model inputs'!AB65="","",'Model inputs'!AB65<1))="",FALSE,IF(ISERROR('Model inputs'!AB65<1),'Model inputs'!AB65<1,IF('Model inputs'!AB65="","",'Model inputs'!AB65<1))),0,'Model inputs'!AI53*IF(AND((1+'Model inputs'!AI61)=0,(MIN('Model inputs'!AB65,'Model inputs'!AI49)-1)=0),SQRT(-1),(1+'Model inputs'!AI61)^(MIN('Model inputs'!AB65,'Model inputs'!AI49)-1))*'Model inputs'!AI85) -> 11641.532 | AC21: =IF(IF(IF(ISERROR('Model inputs'!AC65<1),'Model inputs'!AC65<1,IF('Model inputs'!AC65="","",'Model inputs'!AC65<1))="",FALSE,IF(ISERROR('Model inputs'!AC65<1),'Model inputs'!AC65<1,IF('Model inputs'!AC65="","",'Model inputs'!AC65<1))),0,'Model inputs'!AI53*IF(AND((1+'Model inputs'!AI61)=0,(MIN('Model inputs'!AC65,'Model inputs'!AI49)-1)=0),SQRT(-1),(1+'Model inputs'!AI61)^(MIN('Model inputs'!AC65,'Model inputs'!AI49)-1))*'Model inputs'!AI85) -> 11641.532 | AD21: =IF(IF(IF(ISERROR('Model inputs'!AD65<1),'Model inputs'!AD65<1,IF('Model inputs'!AD65="","",'Model inputs'!AD65<1))="",FALSE,IF(ISERROR('Model inputs'!AD65<1),'Model inputs'!AD65<1,IF('Model inputs'!AD65="","",'Model inputs'!AD65<1))),0,'Model inputs'!AI53*IF(AND((1+'Model inputs'!AI61)=0,(MIN('Model inputs'!AD65,'Model inputs'!AI49)-1)=0),SQRT(-1),(1+'Model inputs'!AI61)^(MIN('Model inputs'!AD65,'Model inputs'!AI49)-1))*'Model inputs'!AI85) -> 11641.532 | AE21: =IF(IF(IF(ISERROR('Model inputs'!AE65<1),'Model inputs'!AE65<1,IF('Model inputs'!AE65="","",'Model inputs'!AE65<1))="",FALSE,IF(ISERROR('Model inputs'!AE65<1),'Model inputs'!AE65<1,IF('Model inputs'!AE65="","",'Model inputs'!AE65<1))),0,'Model inputs'!AI53*IF(AND((1+'Model inputs'!AI61)=0,(MIN('Model inputs'!AE65,'Model inputs'!AI49)-1)=0),SQRT(-1),(1+'Model inputs'!AI61)^(MIN('Model inputs'!AE65,'Model inputs'!AI49)-1))*'Model inputs'!AI85) -> 11641.532 | AF21: =IF(IF(IF(ISERROR('Model inputs'!AF65<1),'Model inputs'!AF65<1,IF('Model inputs'!AF65="","",'Model inputs'!AF65<1))="",FALSE,IF(ISERROR('Model inputs'!AF65<1),'Model inputs'!AF65<1,IF('Model inputs'!AF65="","",'Model inputs'!AF65<1))),0,'Model inputs'!AI53*IF(AND((1+'Model inputs'!AI61)=0,(MIN('Model inputs'!AF65,'Model inputs'!AI49)-1)=0),SQRT(-1),(1+'Model inputs'!AI61)^(MIN('Model inputs'!AF65,'Model inputs'!AI49)-1))*'Model inputs'!AI85) -> 11641.532 | AG21: =IF(IF(IF(ISERROR('Model inputs'!AG65<1),'Model inputs'!AG65<1,IF('Model inputs'!AG65="","",'Model inputs'!AG65<1))="",FALSE,IF(ISERROR('Model inputs'!AG65<1),'Model inputs'!AG65<1,IF('Model inputs'!AG65="","",'Model inputs'!AG65<1))),0,'Model inputs'!AI53*IF(AND((1+'Model inputs'!AI61)=0,(MIN('Model inputs'!AG65,'Model inputs'!AI49)-1)=0),SQRT(-1),(1+'Model inputs'!AI61)^(MIN('Model inputs'!AG65,'Model inputs'!AI49)-1))*'Model inputs'!AI85) -> 11641.532 | AH21: =IF(IF(IF(ISERROR('Model inputs'!AH65<1),'Model inputs'!AH65<1,IF('Model inputs'!AH65="","",'Model inputs'!AH65<1))="",FALSE,IF(ISERROR('Model inputs'!AH65<1),'Model inputs'!AH65<1,IF('Model inputs'!AH65="","",'Model inputs'!AH65<1))),0,'Model inputs'!AI53*IF(AND((1+'Model inputs'!AI61)=0,(MIN('Model inputs'!AH65,'Model inputs'!AI49)-1)=0),SQRT(-1),(1+'Model inputs'!AI61)^(MIN('Model inputs'!AH65,'Model inputs'!AI49)-1))*'Model inputs'!AI85) -> 11641.532
A22: Net cash flow · Main Scenario | B22: 0 | C22: 0 | D22: 0 | E22: 0 | F22: 0 | G22: 0 | H22: 0 | I22: 0 | J22: 0 | K22: ='Model inputs'!K34-'Model inputs'!K54-'Model inputs'!K42 -> -170 | L22: ='Model inputs'!L34-'Model inputs'!L54-'Model inputs'!L42 -> -267.5 | M22: ='Model inputs'!M34-'Model inputs'!M54-'Model inputs'!M42 -> -20.15 | N22: ='Model inputs'!N34-'Model inputs'!N54-'Model inputs'!N42 -> -20.15 | O22: ='Model inputs'!O34-'Model inputs'!O54-'Model inputs'!O42 -> -20.15 | P22: ='Model inputs'!P34-'Model inputs'!P54-'Model inputs'!P42 -> -20.15 | Q22: ='Model inputs'!Q34-'Model inputs'!Q54-'Model inputs'!Q42 -> -20.15 | R22: ='Model inputs'!R34-'Model inputs'!R54-'Model inputs'!R42 -> -20.15 | ... AH22: ='Model inputs'!AH34-'Model inputs'!AH54-'Model inputs'!AH42 -> -20.15
A23: Net cash flow · Growth · $0.60 | B23: 0 | C23: 0 | D23: 0 | E23: 0 | F23: 0 | G23: 0 | H23: 0 | I23: 0 | J23: 0 | K23: ='Model inputs'!K35-'Model inputs'!K55-'Model inputs'!K43 -> -170 | L23: ='Model inputs'!L35-'Model inputs'!L55-'Model inputs'!L43 -> -252.875 | M23: ='Model inputs'!M35-'Model inputs'!M55-'Model inputs'!M43 -> 97.43125 | N23: ='Model inputs'!N35-'Model inputs'!N55-'Model inputs'!N43 -> 164.28906 | O23: ='Model inputs'!O35-'Model inputs'!O55-'Model inputs'!O43 -> 247.86133 | P23: ='Model inputs'!P35-'Model inputs'!P55-'Model inputs'!P43 -> 352.32666 | Q23: ='Model inputs'!Q35-'Model inputs'!Q55-'Model inputs'!Q43 -> 482.90833 | R23: ='Model inputs'!R35-'Model inputs'!R55-'Model inputs'!R43 -> 646.13541 | ... AH23: ='Model inputs'!AH35-'Model inputs'!AH55-'Model inputs'!AH43 -> 3184.5075
A24: Net cash flow · Base · $0.60 | B24: 0 | C24: 0 | D24: 0 | E24: 0 | F24: 0 | G24: 0 | H24: 0 | I24: 0 | J24: 0 | K24: ='Model inputs'!K36-'Model inputs'!K56-'Model inputs'!K44 -> -170 | L24: ='Model inputs'!L36-'Model inputs'!L56-'Model inputs'!L44 -> -252.875 | M24: ='Model inputs'!M36-'Model inputs'!M56-'Model inputs'!M44 -> 118.15 | N24: ='Model inputs'!N36-'Model inputs'!N56-'Model inputs'!N44 -> 118.15 | O24: ='Model inputs'!O36-'Model inputs'!O56-'Model inputs'!O44 -> 118.15 | P24: ='Model inputs'!P36-'Model inputs'!P56-'Model inputs'!P44 -> 118.15 | Q24: ='Model inputs'!Q36-'Model inputs'!Q56-'Model inputs'!Q44 -> 118.15 | R24: ='Model inputs'!R36-'Model inputs'!R56-'Model inputs'!R44 -> 118.15 | ... AH24: ='Model inputs'!AH36-'Model inputs'!AH56-'Model inputs'!AH44 -> 118.15
A25: Net cash flow · Growth · $0.34 | B25: 0 | C25: 0 | D25: 0 | E25: 0 | F25: 0 | G25: 0 | H25: 0 | I25: 0 | J25: 0 | K25: ='Model inputs'!K37-'Model inputs'!K57-'Model inputs'!K45 -> -170 | L25: ='Model inputs'!L37-'Model inputs'!L57-'Model inputs'!L45 -> -267.5 | M25: ='Model inputs'!M37-'Model inputs'!M57-'Model inputs'!M45 -> -44.525 | N25: ='Model inputs'!N37-'Model inputs'!N57-'Model inputs'!N45 -> -13.15625 | O25: ='Model inputs'!O37-'Model inputs'!O57-'Model inputs'!O45 -> 26.054688 | P25: ='Model inputs'!P37-'Model inputs'!P57-'Model inputs'!P45 -> 75.068359 | Q25: ='Model inputs'!Q37-'Model inputs'!Q57-'Model inputs'!Q45 -> 136.33545 | R25: ='Model inputs'!R37-'Model inputs'!R57-'Model inputs'!R45 -> 212.91931 | ... AH25: ='Model inputs'!AH37-'Model inputs'!AH57-'Model inputs'!AH45 -> 1574.4836
A26: Operating profit · Main Scenario | B26: 0 | C26: 0 | D26: 0 | E26: 0 | F26: 0 | G26: 0 | H26: 0 | I26: 0 | J26: 0 | K26: ='Model inputs'!K14-'Model inputs'!K42 -> -170 | L26: ='Model inputs'!L14-'Model inputs'!L42 -> -20.15 | M26: ='Model inputs'!M14-'Model inputs'!M42 -> -20.15 | N26: ='Model inputs'!N14-'Model inputs'!N42 -> -20.15 | O26: ='Model inputs'!O14-'Model inputs'!O42 -> -20.15 | P26: ='Model inputs'!P14-'Model inputs'!P42 -> -20.15 | Q26: ='Model inputs'!Q14-'Model inputs'!Q42 -> -20.15 | R26: ='Model inputs'!R14-'Model inputs'!R42 -> -20.15 | ... AH26: ='Model inputs'!AH14-'Model inputs'!AH42 -> -20.15
A27: Operating profit · Growth · $0.60 | B27: 0 | C27: 0 | D27: 0 | E27: 0 | F27: 0 | G27: 0 | H27: 0 | I27: 0 | J27: 0 | K27: ='Model inputs'!K15-'Model inputs'!K43 -> -170 | L27: ='Model inputs'!L15-'Model inputs'!L43 -> 118.15 | M27: ='Model inputs'!M15-'Model inputs'!M43 -> 190.1875 | N27: ='Model inputs'!N15-'Model inputs'!N43 -> 280.23438 | O27: ='Model inputs'!O15-'Model inputs'!O43 -> 392.79297 | P27: ='Model inputs'!P15-'Model inputs'!P43 -> 533.49121 | Q27: ='Model inputs'!Q15-'Model inputs'!Q43 -> 709.36401 | R27: ='Model inputs'!R15-'Model inputs'!R43 -> 929.20502 | ... AH27: ='Model inputs'!AH15-'Model inputs'!AH43 -> 3184.5075
A28: Operating profit · Base · $0.60 | B28: 0 | C28: 0 | D28: 0 | E28: 0 | F28: 0 | G28: 0 | H28: 0 | I28: 0 | J28: 0 | K28: ='Model inputs'!K16-'Model inputs'!K44 -> -170 | L28: ='Model inputs'!L16-'Model inputs'!L44 -> 118.15 | M28: ='Model inputs'!M16-'Model inputs'!M44 -> 118.15 | N28: ='Model inputs'!N16-'Model inputs'!N44 -> 118.15 | O28: ='Model inputs'!O16-'Model inputs'!O44 -> 118.15 | P28: ='Model inputs'!P16-'Model inputs'!P44 -> 118.15 | Q28: ='Model inputs'!Q16-'Model inputs'!Q44 -> 118.15 | R28: ='Model inputs'!R16-'Model inputs'!R44 -> 118.15 | ... AH28: ='Model inputs'!AH16-'Model inputs'!AH44 -> 118.15
A29: Operating profit · Growth · $0.34 | B29: 0 | C29: 0 | D29: 0 | E29: 0 | F29: 0 | G29: 0 | H29: 0 | I29: 0 | J29: 0 | K29: ='Model inputs'!K17-'Model inputs'!K45 -> -170 | L29: ='Model inputs'!L17-'Model inputs'!L45 -> -20.15 | M29: ='Model inputs'!M17-'Model inputs'!M45 -> 17.3125 | N29: ='Model inputs'!N17-'Model inputs'!N45 -> 64.140625 | O29: ='Model inputs'!O17-'Model inputs'!O45 -> 122.67578 | P29: ='Model inputs'!P17-'Model inputs'!P45 -> 195.84473 | Q29: ='Model inputs'!Q17-'Model inputs'!Q45 -> 287.30591 | R29: ='Model inputs'!R17-'Model inputs'!R45 -> 401.63239 | ... AH29: ='Model inputs'!AH17-'Model inputs'!AH45 -> 1574.4836
A30: Revenue · Main Scenario | B30: 0 | C30: 0 | D30: 0 | E30: 0 | F30: 0 | G30: 0 | H30: 0 | I30: 0 | J30: 0 | K30: ='Model inputs'!K78*'Model inputs'!AI70 -> 0 | L30: ='Model inputs'!L78*'Model inputs'!AI70 -> 255 | M30: ='Model inputs'!M78*'Model inputs'!AI70 -> 255 | N30: ='Model inputs'!N78*'Model inputs'!AI70 -> 255 | O30: ='Model inputs'!O78*'Model inputs'!AI70 -> 255 | P30: ='Model inputs'!P78*'Model inputs'!AI70 -> 255 | Q30: ='Model inputs'!Q78*'Model inputs'!AI70 -> 255 | R30: ='Model inputs'!R78*'Model inputs'!AI70 -> 255 | S30: ='Model inputs'!S78*'Model inputs'!AI70 -> 255 | T30: ='Model inputs'!T78*'Model inputs'!AI70 -> 255 | U30: ='Model inputs'!U78*'Model inputs'!AI70 -> 255 | V30: ='Model inputs'!V78*'Model inputs'!AI70 -> 255 | W30: ='Model inputs'!W78*'Model inputs'!AI70 -> 255 | X30: ='Model inputs'!X78*'Model inputs'!AI70 -> 255 | Y30: ='Model inputs'!Y78*'Model inputs'!AI70 -> 255 | Z30: ='Model inputs'!Z78*'Model inputs'!AI70 -> 255 | AA30: ='Model inputs'!AA78*'Model inputs'!AI70 -> 255 | AB30: ='Model inputs'!AB78*'Model inputs'!AI70 -> 255 | AC30: ='Model inputs'!AC78*'Model inputs'!AI70 -> 255 | AD30: ='Model inputs'!AD78*'Model inputs'!AI70 -> 255 | AE30: ='Model inputs'!AE78*'Model inputs'!AI70 -> 255 | AF30: ='Model inputs'!AF78*'Model inputs'!AI70 -> 255 | AG30: ='Model inputs'!AG78*'Model inputs'!AI70 -> 255 | AH30: ='Model inputs'!AH78*'Model inputs'!AI70 -> 255
A31: Revenue · Growth · $0.60 | B31: 0 | C31: 0 | D31: 0 | E31: 0 | F31: 0 | G31: 0 | H31: 0 | I31: 0 | J31: 0 | K31: ='Model inputs'!K79*'Model inputs'!AI71 -> 0 | L31: ='Model inputs'!L79*'Model inputs'!AI71 -> 382.5 | M31: ='Model inputs'!M79*'Model inputs'!AI71 -> 478.125 | N31: ='Model inputs'!N79*'Model inputs'!AI71 -> 597.65625 | O31: ='Model inputs'!O79*'Model inputs'!AI71 -> 747.07031 | P31: ='Model inputs'!P79*'Model inputs'!AI71 -> 933.83789 | Q31: ='Model inputs'!Q79*'Model inputs'!AI71 -> 1167.2974 | R31: ='Model inputs'!R79*'Model inputs'!AI71 -> 1459.1217 | S31: ='Model inputs'!S79*'Model inputs'!AI71 -> 1823.9021 | T31: ='Model inputs'!T79*'Model inputs'!AI71 -> 2279.8777 | U31: ='Model inputs'!U79*'Model inputs'!AI71 -> 2849.8471 | V31: ='Model inputs'!V79*'Model inputs'!AI71 -> 3562.3088 | W31: ='Model inputs'!W79*'Model inputs'!AI71 -> 4452.8861 | X31: ='Model inputs'!X79*'Model inputs'!AI71 -> 4452.8861 | Y31: ='Model inputs'!Y79*'Model inputs'!AI71 -> 4452.8861 | Z31: ='Model inputs'!Z79*'Model inputs'!AI71 -> 4452.8861 | AA31: ='Model inputs'!AA79*'Model inputs'!AI71 -> 4452.8861 | AB31: ='Model inputs'!AB79*'Model inputs'!AI71 -> 4452.8861 | AC31: ='Model inputs'!AC79*'Model inputs'!AI71 -> 4452.8861 | AD31: ='Model inputs'!AD79*'Model inputs'!AI71 -> 4452.8861 | AE31: ='Model inputs'!AE79*'Model inputs'!AI71 -> 4452.8861 | AF31: ='Model inputs'!AF79*'Model inputs'!AI71 -> 4452.8861 | AG31: ='Model inputs'!AG79*'Model inputs'!AI71 -> 4452.8861 | AH31: ='Model inputs'!AH79*'Model inputs'!AI71 -> 4452.8861
A32: Revenue · Base · $0.60 | B32: 0 | C32: 0 | D32: 0 | E32: 0 | F32: 0 | G32: 0 | H32: 0 | I32: 0 | J32: 0 | K32: ='Model inputs'!K80*'Model inputs'!AI72 -> 0 | L32: ='Model inputs'!L80*'Model inputs'!AI72 -> 382.5 | M32: ='Model inputs'!M80*'Model inputs'!AI72 -> 382.5 | N32: ='Model inputs'!N80*'Model inputs'!AI72 -> 382.5 | O32: ='Model inputs'!O80*'Model inputs'!AI72 -> 382.5 | P32: ='Model inputs'!P80*'Model inputs'!AI72 -> 382.5 | Q32: ='Model inputs'!Q80*'Model inputs'!AI72 -> 382.5 | R32: ='Model inputs'!R80*'Model inputs'!AI72 -> 382.5 | S32: ='Model inputs'!S80*'Model inputs'!AI72 -> 382.5 | T32: ='Model inputs'!T80*'Model inputs'!AI72 -> 382.5 | U32: ='Model inputs'!U80*'Model inputs'!AI72 -> 382.5 | V32: ='Model inputs'!V80*'Model inputs'!AI72 -> 382.5 | W32: ='Model inputs'!W80*'Model inputs'!AI72 -> 382.5 | X32: ='Model inputs'!X80*'Model inputs'!AI72 -> 382.5 | Y32: ='Model inputs'!Y80*'Model inputs'!AI72 -> 382.5 | Z32: ='Model inputs'!Z80*'Model inputs'!AI72 -> 382.5 | AA32: ='Model inputs'!AA80*'Model inputs'!AI72 -> 382.5 | AB32: ='Model inputs'!AB80*'Model inputs'!AI72 -> 382.5 | AC32: ='Model inputs'!AC80*'Model inputs'!AI72 -> 382.5 | AD32: ='Model inputs'!AD80*'Model inputs'!AI72 -> 382.5 | AE32: ='Model inputs'!AE80*'Model inputs'!AI72 -> 382.5 | AF32: ='Model inputs'!AF80*'Model inputs'!AI72 -> 382.5 | AG32: ='Model inputs'!AG80*'Model inputs'!AI72 -> 382.5 | AH32: ='Model inputs'!AH80*'Model inputs'!AI72 -> 382.5
A33: Revenue · Growth · $0.34 | B33: 0 | C33: 0 | D33: 0 | E33: 0 | F33: 0 | G33: 0 | H33: 0 | I33: 0 | J33: 0 | K33: ='Model inputs'!K81*'Model inputs'!AI73 -> 0 | L33: ='Model inputs'!L81*'Model inputs'!AI73 -> 255 | M33: ='Model inputs'!M81*'Model inputs'!AI73 -> 318.75 | N33: ='Model inputs'!N81*'Model inputs'!AI73 -> 398.4375 | O33: ='Model inputs'!O81*'Model inputs'!AI73 -> 498.04688 | P33: ='Model inputs'!P81*'Model inputs'!AI73 -> 622.55859 | Q33: ='Model inputs'!Q81*'Model inputs'!AI73 -> 778.19824 | R33: ='Model inputs'!R81*'Model inputs'!AI73 -> 972.7478 | S33: ='Model inputs'!S81*'Model inputs'!AI73 -> 1215.9348 | T33: ='Model inputs'!T81*'Model inputs'!AI73 -> 1519.9184 | U33: ='Model inputs'!U81*'Model inputs'!AI73 -> 1899.8981 | V33: ='Model inputs'!V81*'Model inputs'!AI73 -> 2374.8726 | W33: ='Model inputs'!W81*'Model inputs'!AI73 -> 2968.5907 | X33: ='Model inputs'!X81*'Model inputs'!AI73 -> 2968.5907 | Y33: ='Model inputs'!Y81*'Model inputs'!AI73 -> 2968.5907 | Z33: ='Model inputs'!Z81*'Model inputs'!AI73 -> 2968.5907 | AA33: ='Model inputs'!AA81*'Model inputs'!AI73 -> 2968.5907 | AB33: ='Model inputs'!AB81*'Model inputs'!AI73 -> 2968.5907 | AC33: ='Model inputs'!AC81*'Model inputs'!AI73 -> 2968.5907 | AD33: ='Model inputs'!AD81*'Model inputs'!AI73 -> 2968.5907 | AE33: ='Model inputs'!AE81*'Model inputs'!AI73 -> 2968.5907 | AF33: ='Model inputs'!AF81*'Model inputs'!AI73 -> 2968.5907 | AG33: ='Model inputs'!AG81*'Model inputs'!AI73 -> 2968.5907 | AH33: ='Model inputs'!AH81*'Model inputs'!AI73 -> 2968.5907
A34: Cash collected from customers · Main Scenario | B34: 0 | C34: 0 | D34: 0 | E34: 0 | F34: 0 | G34: 0 | H34: 0 | I34: 0 | J34: 0 | K34: ='Model inputs'!J30*(1-'Model inputs'!AI122) -> 0 | L34: ='Model inputs'!K30*(1-'Model inputs'!AI122) -> 0 | M34: ='Model inputs'!L30*(1-'Model inputs'!AI122) -> 247.35 | N34: ='Model inputs'!M30*(1-'Model inputs'!AI122) -> 247.35 | O34: ='Model inputs'!N30*(1-'Model inputs'!AI122) -> 247.35 | P34: ='Model inputs'!O30*(1-'Model inputs'!AI122) -> 247.35 | Q34: ='Model inputs'!P30*(1-'Model inputs'!AI122) -> 247.35 | R34: ='Model inputs'!Q30*(1-'Model inputs'!AI122) -> 247.35 | S34: ='Model inputs'!R30*(1-'Model inputs'!AI122) -> 247.35 | T34: ='Model inputs'!S30*(1-'Model inputs'!AI122) -> 247.35 | U34: ='Model inputs'!T30*(1-'Model inputs'!AI122) -> 247.35 | V34: ='Model inputs'!U30*(1-'Model inputs'!AI122) -> 247.35 | W34: ='Model inputs'!V30*(1-'Model inputs'!AI122) -> 247.35 | X34: ='Model inputs'!W30*(1-'Model inputs'!AI122) -> 247.35 | Y34: ='Model inputs'!X30*(1-'Model inputs'!AI122) -> 247.35 | Z34: ='Model inputs'!Y30*(1-'Model inputs'!AI122) -> 247.35 | AA34: ='Model inputs'!Z30*(1-'Model inputs'!AI122) -> 247.35 | AB34: ='Model inputs'!AA30*(1-'Model inputs'!AI122) -> 247.35 | AC34: ='Model inputs'!AB30*(1-'Model inputs'!AI122) -> 247.35 | AD34: ='Model inputs'!AC30*(1-'Model inputs'!AI122) -> 247.35 | AE34: ='Model inputs'!AD30*(1-'Model inputs'!AI122) -> 247.35 | AF34: ='Model inputs'!AE30*(1-'Model inputs'!AI122) -> 247.35 | AG34: ='Model inputs'!AF30*(1-'Model inputs'!AI122) -> 247.35 | AH34: ='Model inputs'!AG30*(1-'Model inputs'!AI122) -> 247.35
A35: Cash collected from customers · Growth · $0.60 | B35: 0 | C35: 0 | D35: 0 | E35: 0 | F35: 0 | G35: 0 | H35: 0 | I35: 0 | J35: 0 | K35: ='Model inputs'!J31*(1-'Model inputs'!AI123) -> 0 | L35: ='Model inputs'!K31*(1-'Model inputs'!AI123) -> 0 | M35: ='Model inputs'!L31*(1-'Model inputs'!AI123) -> 371.025 | N35: ='Model inputs'!M31*(1-'Model inputs'!AI123) -> 463.78125 | O35: ='Model inputs'!N31*(1-'Model inputs'!AI123) -> 579.72656 | P35: ='Model inputs'!O31*(1-'Model inputs'!AI123) -> 724.6582 | Q35: ='Model inputs'!P31*(1-'Model inputs'!AI123) -> 905.82275 | R35: ='Model inputs'!Q31*(1-'Model inputs'!AI123) -> 1132.2784 | S35: ='Model inputs'!R31*(1-'Model inputs'!AI123) -> 1415.3481 | T35: ='Model inputs'!S31*(1-'Model inputs'!AI123) -> 1769.1851 | U35: ='Model inputs'!T31*(1-'Model inputs'!AI123) -> 2211.4813 | V35: ='Model inputs'!U31*(1-'Model inputs'!AI123) -> 2764.3517 | W35: ='Model inputs'!V31*(1-'Model inputs'!AI123) -> 3455.4396 | X35: ='Model inputs'!W31*(1-'Model inputs'!AI123) -> 4319.2995 | Y35: ='Model inputs'!X31*(1-'Model inputs'!AI123) -> 4319.2995 | Z35: ='Model inputs'!Y31*(1-'Model inputs'!AI123) -> 4319.2995 | AA35: ='Model inputs'!Z31*(1-'Model inputs'!AI123) -> 4319.2995 | AB35: ='Model inputs'!AA31*(1-'Model inputs'!AI123) -> 4319.2995 | AC35: ='Model inputs'!AB31*(1-'Model inputs'!AI123) -> 4319.2995 | AD35: ='Model inputs'!AC31*(1-'Model inputs'!AI123) -> 4319.2995 | AE35: ='Model inputs'!AD31*(1-'Model inputs'!AI123) -> 4319.2995 | AF35: ='Model inputs'!AE31*(1-'Model inputs'!AI123) -> 4319.2995 | AG35: ='Model inputs'!AF31*(1-'Model inputs'!AI123) -> 4319.2995 | AH35: ='Model inputs'!AG31*(1-'Model inputs'!AI123) -> 4319.2995
A36: Cash collected from customers · Base · $0.60 | B36: 0 | C36: 0 | D36: 0 | E36: 0 | F36: 0 | G36: 0 | H36: 0 | I36: 0 | J36: 0 | K36: ='Model inputs'!J32*(1-'Model inputs'!AI124) -> 0 | L36: ='Model inputs'!K32*(1-'Model inputs'!AI124) -> 0 | M36: ='Model inputs'!L32*(1-'Model inputs'!AI124) -> 371.025 | N36: ='Model inputs'!M32*(1-'Model inputs'!AI124) -> 371.025 | O36: ='Model inputs'!N32*(1-'Model inputs'!AI124) -> 371.025 | P36: ='Model inputs'!O32*(1-'Model inputs'!AI124) -> 371.025 | Q36: ='Model inputs'!P32*(1-'Model inputs'!AI124) -> 371.025 | R36: ='Model inputs'!Q32*(1-'Model inputs'!AI124) -> 371.025 | S36: ='Model inputs'!R32*(1-'Model inputs'!AI124) -> 371.025 | T36: ='Model inputs'!S32*(1-'Model inputs'!AI124) -> 371.025 | U36: ='Model inputs'!T32*(1-'Model inputs'!AI124) -> 371.025 | V36: ='Model inputs'!U32*(1-'Model inputs'!AI124) -> 371.025 | W36: ='Model inputs'!V32*(1-'Model inputs'!AI124) -> 371.025 | X36: ='Model inputs'!W32*(1-'Model inputs'!AI124) -> 371.025 | Y36: ='Model inputs'!X32*(1-'Model inputs'!AI124) -> 371.025 | Z36: ='Model inputs'!Y32*(1-'Model inputs'!AI124) -> 371.025 | AA36: ='Model inputs'!Z32*(1-'Model inputs'!AI124) -> 371.025 | AB36: ='Model inputs'!AA32*(1-'Model inputs'!AI124) -> 371.025 | AC36: ='Model inputs'!AB32*(1-'Model inputs'!AI124) -> 371.025 | AD36: ='Model inputs'!AC32*(1-'Model inputs'!AI124) -> 371.025 | AE36: ='Model inputs'!AD32*(1-'Model inputs'!AI124) -> 371.025 | AF36: ='Model inputs'!AE32*(1-'Model inputs'!AI124) -> 371.025 | AG36: ='Model inputs'!AF32*(1-'Model inputs'!AI124) -> 371.025 | AH36: ='Model inputs'!AG32*(1-'Model inputs'!AI124) -> 371.025
A37: Cash collected from customers · Growth · $0.34 | B37: 0 | C37: 0 | D37: 0 | E37: 0 | F37: 0 | G37: 0 | H37: 0 | I37: 0 | J37: 0 | K37: ='Model inputs'!J33*(1-'Model inputs'!AI125) -> 0 | L37: ='Model inputs'!K33*(1-'Model inputs'!AI125) -> 0 | M37: ='Model inputs'!L33*(1-'Model inputs'!AI125) -> 247.35 | N37: ='Model inputs'!M33*(1-'Model inputs'!AI125) -> 309.1875 | O37: ='Model inputs'!N33*(1-'Model inputs'!AI125) -> 386.48438 | P37: ='Model inputs'!O33*(1-'Model inputs'!AI125) -> 483.10547 | Q37: ='Model inputs'!P33*(1-'Model inputs'!AI125) -> 603.88184 | R37: ='Model inputs'!Q33*(1-'Model inputs'!AI125) -> 754.85229 | S37: ='Model inputs'!R33*(1-'Model inputs'!AI125) -> 943.56537 | T37: ='Model inputs'!S33*(1-'Model inputs'!AI125) -> 1179.4567 | U37: ='Model inputs'!T33*(1-'Model inputs'!AI125) -> 1474.3209 | V37: ='Model inputs'!U33*(1-'Model inputs'!AI125) -> 1842.9011 | W37: ='Model inputs'!V33*(1-'Model inputs'!AI125) -> 2303.6264 | X37: ='Model inputs'!W33*(1-'Model inputs'!AI125) -> 2879.533 | Y37: ='Model inputs'!X33*(1-'Model inputs'!AI125) -> 2879.533 | Z37: ='Model inputs'!Y33*(1-'Model inputs'!AI125) -> 2879.533 | AA37: ='Model inputs'!Z33*(1-'Model inputs'!AI125) -> 2879.533 | AB37: ='Model inputs'!AA33*(1-'Model inputs'!AI125) -> 2879.533 | AC37: ='Model inputs'!AB33*(1-'Model inputs'!AI125) -> 2879.533 | AD37: ='Model inputs'!AC33*(1-'Model inputs'!AI125) -> 2879.533 | AE37: ='Model inputs'!AD33*(1-'Model inputs'!AI125) -> 2879.533 | AF37: ='Model inputs'!AE33*(1-'Model inputs'!AI125) -> 2879.533 | AG37: ='Model inputs'!AF33*(1-'Model inputs'!AI125) -> 2879.533 | AH37: ='Model inputs'!AG33*(1-'Model inputs'!AI125) -> 2879.533
A38: Cost of revenue · Main Scenario | B38: 0 | C38: 0 | D38: 0 | E38: 0 | F38: 0 | G38: 0 | H38: 0 | I38: 0 | J38: 0 | K38: ='Model inputs'!K54+'Model inputs'!K118 -> 0 | L38: ='Model inputs'!L54+'Model inputs'!L118 -> 105.15 | M38: ='Model inputs'!M54+'Model inputs'!M118 -> 105.15 | N38: ='Model inputs'!N54+'Model inputs'!N118 -> 105.15 | O38: ='Model inputs'!O54+'Model inputs'!O118 -> 105.15 | P38: ='Model inputs'!P54+'Model inputs'!P118 -> 105.15 | Q38: ='Model inputs'!Q54+'Model inputs'!Q118 -> 105.15 | R38: ='Model inputs'!R54+'Model inputs'!R118 -> 105.15 | ... AH38: ='Model inputs'!AH54+'Model inputs'!AH118 -> 105.15
A39: Cost of revenue · Growth · $0.60 | B39: 0 | C39: 0 | D39: 0 | E39: 0 | F39: 0 | G39: 0 | H39: 0 | I39: 0 | J39: 0 | K39: ='Model inputs'!K55+'Model inputs'!K119 -> 0 | L39: ='Model inputs'!L55+'Model inputs'!L119 -> 94.35 | M39: ='Model inputs'!M55+'Model inputs'!M119 -> 117.9375 | N39: ='Model inputs'!N55+'Model inputs'!N119 -> 147.42188 | O39: ='Model inputs'!O55+'Model inputs'!O119 -> 184.27734 | P39: ='Model inputs'!P55+'Model inputs'!P119 -> 230.34668 | Q39: ='Model inputs'!Q55+'Model inputs'!Q119 -> 287.93335 | R39: ='Model inputs'!R55+'Model inputs'!R119 -> 359.91669 | ... AH39: ='Model inputs'!AH55+'Model inputs'!AH119 -> 1098.3786
A40: Cost of revenue · Base · $0.60 | B40: 0 | C40: 0 | D40: 0 | E40: 0 | F40: 0 | G40: 0 | H40: 0 | I40: 0 | J40: 0 | K40: ='Model inputs'!K56+'Model inputs'!K120 -> 0 | L40: ='Model inputs'!L56+'Model inputs'!L120 -> 94.35 | M40: ='Model inputs'!M56+'Model inputs'!M120 -> 94.35 | N40: ='Model inputs'!N56+'Model inputs'!N120 -> 94.35 | O40: ='Model inputs'!O56+'Model inputs'!O120 -> 94.35 | P40: ='Model inputs'!P56+'Model inputs'!P120 -> 94.35 | Q40: ='Model inputs'!Q56+'Model inputs'!Q120 -> 94.35 | R40: ='Model inputs'!R56+'Model inputs'!R120 -> 94.35 | ... AH40: ='Model inputs'!AH56+'Model inputs'!AH120 -> 94.35
A41: Cost of revenue · Growth · $0.34 | B41: 0 | C41: 0 | D41: 0 | E41: 0 | F41: 0 | G41: 0 | H41: 0 | I41: 0 | J41: 0 | K41: ='Model inputs'!K57+'Model inputs'!K121 -> 0 | L41: ='Model inputs'!L57+'Model inputs'!L121 -> 105.15 | M41: ='Model inputs'!M57+'Model inputs'!M121 -> 131.4375 | N41: ='Model inputs'!N57+'Model inputs'!N121 -> 164.29688 | O41: ='Model inputs'!O57+'Model inputs'!O121 -> 205.37109 | P41: ='Model inputs'!P57+'Model inputs'!P121 -> 256.71387 | Q41: ='Model inputs'!Q57+'Model inputs'!Q121 -> 320.89233 | R41: ='Model inputs'!R57+'Model inputs'!R121 -> 401.11542 | ... AH41: ='Model inputs'!AH57+'Model inputs'!AH121 -> 1224.1071
A42: Fixed costs · Main Scenario | B42: =SUM('Model inputs'!B91,'Model inputs'!B92,'Model inputs'!B93,'Model inputs'!B94) -> 0 | C42: =SUM('Model inputs'!C91,'Model inputs'!C92,'Model inputs'!C93,'Model inputs'!C94) -> 0 | D42: =SUM('Model inputs'!D91,'Model inputs'!D92,'Model inputs'!D93,'Model inputs'!D94) -> 0 | E42: =SUM('Model inputs'!E91,'Model inputs'!E92,'Model inputs'!E93,'Model inputs'!E94) -> 0 | F42: =SUM('Model inputs'!F91,'Model inputs'!F92,'Model inputs'!F93,'Model inputs'!F94) -> 0 | G42: =SUM('Model inputs'!G91,'Model inputs'!G92,'Model inputs'!G93,'Model inputs'!G94) -> 0 | H42: =SUM('Model inputs'!H91,'Model inputs'!H92,'Model inputs'!H93,'Model inputs'!H94) -> 0 | I42: =SUM('Model inputs'!I91,'Model inputs'!I92,'Model inputs'!I93,'Model inputs'!I94) -> 0 | ... AH42: =SUM('Model inputs'!AH91,'Model inputs'!AH92,'Model inputs'!AH93,'Model inputs'!AH94) -> 170
A43: Fixed costs · Growth · $0.60 | B43: =SUM('Model inputs'!B96,'Model inputs'!B97,'Model inputs'!B98,'Model inputs'!B99) -> 0 | C43: =SUM('Model inputs'!C96,'Model inputs'!C97,'Model inputs'!C98,'Model inputs'!C99) -> 0 | D43: =SUM('Model inputs'!D96,'Model inputs'!D97,'Model inputs'!D98,'Model inputs'!D99) -> 0 | E43: =SUM('Model inputs'!E96,'Model inputs'!E97,'Model inputs'!E98,'Model inputs'!E99) -> 0 | F43: =SUM('Model inputs'!F96,'Model inputs'!F97,'Model inputs'!F98,'Model inputs'!F99) -> 0 | G43: =SUM('Model inputs'!G96,'Model inputs'!G97,'Model inputs'!G98,'Model inputs'!G99) -> 0 | H43: =SUM('Model inputs'!H96,'Model inputs'!H97,'Model inputs'!H98,'Model inputs'!H99) -> 0 | I43: =SUM('Model inputs'!I96,'Model inputs'!I97,'Model inputs'!I98,'Model inputs'!I99) -> 0 | ... AH43: =SUM('Model inputs'!AH96,'Model inputs'!AH97,'Model inputs'!AH98,'Model inputs'!AH99) -> 170
A44: Fixed costs · Base · $0.60 | B44: =SUM('Model inputs'!B101,'Model inputs'!B102,'Model inputs'!B103,'Model inputs'!B104) -> 0 | C44: =SUM('Model inputs'!C101,'Model inputs'!C102,'Model inputs'!C103,'Model inputs'!C104) -> 0 | D44: =SUM('Model inputs'!D101,'Model inputs'!D102,'Model inputs'!D103,'Model inputs'!D104) -> 0 | E44: =SUM('Model inputs'!E101,'Model inputs'!E102,'Model inputs'!E103,'Model inputs'!E104) -> 0 | F44: =SUM('Model inputs'!F101,'Model inputs'!F102,'Model inputs'!F103,'Model inputs'!F104) -> 0 | G44: =SUM('Model inputs'!G101,'Model inputs'!G102,'Model inputs'!G103,'Model inputs'!G104) -> 0 | H44: =SUM('Model inputs'!H101,'Model inputs'!H102,'Model inputs'!H103,'Model inputs'!H104) -> 0 | I44: =SUM('Model inputs'!I101,'Model inputs'!I102,'Model inputs'!I103,'Model inputs'!I104) -> 0 | ... AH44: =SUM('Model inputs'!AH101,'Model inputs'!AH102,'Model inputs'!AH103,'Model inputs'!AH104) -> 170
A45: Fixed costs · Growth · $0.34 | B45: =SUM('Model inputs'!B106,'Model inputs'!B107,'Model inputs'!B108,'Model inputs'!B109) -> 0 | C45: =SUM('Model inputs'!C106,'Model inputs'!C107,'Model inputs'!C108,'Model inputs'!C109) -> 0 | D45: =SUM('Model inputs'!D106,'Model inputs'!D107,'Model inputs'!D108,'Model inputs'!D109) -> 0 | E45: =SUM('Model inputs'!E106,'Model inputs'!E107,'Model inputs'!E108,'Model inputs'!E109) -> 0 | F45: =SUM('Model inputs'!F106,'Model inputs'!F107,'Model inputs'!F108,'Model inputs'!F109) -> 0 | G45: =SUM('Model inputs'!G106,'Model inputs'!G107,'Model inputs'!G108,'Model inputs'!G109) -> 0 | H45: =SUM('Model inputs'!H106,'Model inputs'!H107,'Model inputs'!H108,'Model inputs'!H109) -> 0 | I45: =SUM('Model inputs'!I106,'Model inputs'!I107,'Model inputs'!I108,'Model inputs'!I109) -> 0 | ... AH45: =SUM('Model inputs'!AH106,'Model inputs'!AH107,'Model inputs'!AH108,'Model inputs'!AH109) -> 170
A46: Growth months · Main Scenario | AI46: =12 -> 12
A47: Growth months · Growth · $0.60 | AI47: ='Model inputs'!AI46 -> 12
A48: Growth months · Base · $0.60 | AI48: ='Model inputs'!AI46 -> 12
A49: Growth months · Growth · $0.34 | AI49: ='Model inputs'!AI46 -> 12
A50: Launch month jobs · Main Scenario | AI50: =1000 -> 1000
A51: Launch month jobs · Growth · $0.60 | AI51: ='Model inputs'!AI50 -> 1000
A52: Launch month jobs · Base · $0.60 | AI52: ='Model inputs'!AI50 -> 1000
A53: Launch month jobs · Growth · $0.34 | AI53: ='Model inputs'!AI50 -> 1000
A54: Model usage cost · Main Scenario | B54: 0 | C54: 0 | D54: 0 | E54: 0 | F54: 0 | G54: 0 | H54: 0 | I54: 0 | J54: 0 | K54: ='Model inputs'!K78*'Model inputs'!AI86 -> 0 | L54: ='Model inputs'!L78*'Model inputs'!AI86 -> 97.5 | M54: ='Model inputs'!M78*'Model inputs'!AI86 -> 97.5 | N54: ='Model inputs'!N78*'Model inputs'!AI86 -> 97.5 | O54: ='Model inputs'!O78*'Model inputs'!AI86 -> 97.5 | P54: ='Model inputs'!P78*'Model inputs'!AI86 -> 97.5 | Q54: ='Model inputs'!Q78*'Model inputs'!AI86 -> 97.5 | R54: ='Model inputs'!R78*'Model inputs'!AI86 -> 97.5 | S54: ='Model inputs'!S78*'Model inputs'!AI86 -> 97.5 | T54: ='Model inputs'!T78*'Model inputs'!AI86 -> 97.5 | U54: ='Model inputs'!U78*'Model inputs'!AI86 -> 97.5 | V54: ='Model inputs'!V78*'Model inputs'!AI86 -> 97.5 | W54: ='Model inputs'!W78*'Model inputs'!AI86 -> 97.5 | X54: ='Model inputs'!X78*'Model inputs'!AI86 -> 97.5 | Y54: ='Model inputs'!Y78*'Model inputs'!AI86 -> 97.5 | Z54: ='Model inputs'!Z78*'Model inputs'!AI86 -> 97.5 | AA54: ='Model inputs'!AA78*'Model inputs'!AI86 -> 97.5 | AB54: ='Model inputs'!AB78*'Model inputs'!AI86 -> 97.5 | AC54: ='Model inputs'!AC78*'Model inputs'!AI86 -> 97.5 | AD54: ='Model inputs'!AD78*'Model inputs'!AI86 -> 97.5 | AE54: ='Model inputs'!AE78*'Model inputs'!AI86 -> 97.5 | AF54: ='Model inputs'!AF78*'Model inputs'!AI86 -> 97.5 | AG54: ='Model inputs'!AG78*'Model inputs'!AI86 -> 97.5 | AH54: ='Model inputs'!AH78*'Model inputs'!AI86 -> 97.5
A55: Model usage cost · Growth · $0.60 | B55: 0 | C55: 0 | D55: 0 | E55: 0 | F55: 0 | G55: 0 | H55: 0 | I55: 0 | J55: 0 | K55: ='Model inputs'!K79*'Model inputs'!AI87 -> 0 | L55: ='Model inputs'!L79*'Model inputs'!AI87 -> 82.875 | M55: ='Model inputs'!M79*'Model inputs'!AI87 -> 103.59375 | N55: ='Model inputs'!N79*'Model inputs'!AI87 -> 129.49219 | O55: ='Model inputs'!O79*'Model inputs'!AI87 -> 161.86523 | P55: ='Model inputs'!P79*'Model inputs'!AI87 -> 202.33154 | Q55: ='Model inputs'!Q79*'Model inputs'!AI87 -> 252.91443 | R55: ='Model inputs'!R79*'Model inputs'!AI87 -> 316.14304 | S55: ='Model inputs'!S79*'Model inputs'!AI87 -> 395.17879 | T55: ='Model inputs'!T79*'Model inputs'!AI87 -> 493.97349 | U55: ='Model inputs'!U79*'Model inputs'!AI87 -> 617.46687 | V55: ='Model inputs'!V79*'Model inputs'!AI87 -> 771.83358 | W55: ='Model inputs'!W79*'Model inputs'!AI87 -> 964.79198 | X55: ='Model inputs'!X79*'Model inputs'!AI87 -> 964.79198 | Y55: ='Model inputs'!Y79*'Model inputs'!AI87 -> 964.79198 | Z55: ='Model inputs'!Z79*'Model inputs'!AI87 -> 964.79198 | AA55: ='Model inputs'!AA79*'Model inputs'!AI87 -> 964.79198 | AB55: ='Model inputs'!AB79*'Model inputs'!AI87 -> 964.79198 | AC55: ='Model inputs'!AC79*'Model inputs'!AI87 -> 964.79198 | AD55: ='Model inputs'!AD79*'Model inputs'!AI87 -> 964.79198 | AE55: ='Model inputs'!AE79*'Model inputs'!AI87 -> 964.79198 | AF55: ='Model inputs'!AF79*'Model inputs'!AI87 -> 964.79198 | AG55: ='Model inputs'!AG79*'Model inputs'!AI87 -> 964.79198 | AH55: ='Model inputs'!AH79*'Model inputs'!AI87 -> 964.79198
A56: Model usage cost · Base · $0.60 | B56: 0 | C56: 0 | D56: 0 | E56: 0 | F56: 0 | G56: 0 | H56: 0 | I56: 0 | J56: 0 | K56: ='Model inputs'!K80*'Model inputs'!AI88 -> 0 | L56: ='Model inputs'!L80*'Model inputs'!AI88 -> 82.875 | M56: ='Model inputs'!M80*'Model inputs'!AI88 -> 82.875 | N56: ='Model inputs'!N80*'Model inputs'!AI88 -> 82.875 | O56: ='Model inputs'!O80*'Model inputs'!AI88 -> 82.875 | P56: ='Model inputs'!P80*'Model inputs'!AI88 -> 82.875 | Q56: ='Model inputs'!Q80*'Model inputs'!AI88 -> 82.875 | R56: ='Model inputs'!R80*'Model inputs'!AI88 -> 82.875 | S56: ='Model inputs'!S80*'Model inputs'!AI88 -> 82.875 | T56: ='Model inputs'!T80*'Model inputs'!AI88 -> 82.875 | U56: ='Model inputs'!U80*'Model inputs'!AI88 -> 82.875 | V56: ='Model inputs'!V80*'Model inputs'!AI88 -> 82.875 | W56: ='Model inputs'!W80*'Model inputs'!AI88 -> 82.875 | X56: ='Model inputs'!X80*'Model inputs'!AI88 -> 82.875 | Y56: ='Model inputs'!Y80*'Model inputs'!AI88 -> 82.875 | Z56: ='Model inputs'!Z80*'Model inputs'!AI88 -> 82.875 | AA56: ='Model inputs'!AA80*'Model inputs'!AI88 -> 82.875 | AB56: ='Model inputs'!AB80*'Model inputs'!AI88 -> 82.875 | AC56: ='Model inputs'!AC80*'Model inputs'!AI88 -> 82.875 | AD56: ='Model inputs'!AD80*'Model inputs'!AI88 -> 82.875 | AE56: ='Model inputs'!AE80*'Model inputs'!AI88 -> 82.875 | AF56: ='Model inputs'!AF80*'Model inputs'!AI88 -> 82.875 | AG56: ='Model inputs'!AG80*'Model inputs'!AI88 -> 82.875 | AH56: ='Model inputs'!AH80*'Model inputs'!AI88 -> 82.875
A57: Model usage cost · Growth · $0.34 | B57: 0 | C57: 0 | D57: 0 | E57: 0 | F57: 0 | G57: 0 | H57: 0 | I57: 0 | J57: 0 | K57: ='Model inputs'!K81*'Model inputs'!AI89 -> 0 | L57: ='Model inputs'!L81*'Model inputs'!AI89 -> 97.5 | M57: ='Model inputs'!M81*'Model inputs'!AI89 -> 121.875 | N57: ='Model inputs'!N81*'Model inputs'!AI89 -> 152.34375 | O57: ='Model inputs'!O81*'Model inputs'!AI89 -> 190.42969 | P57: ='Model inputs'!P81*'Model inputs'!AI89 -> 238.03711 | Q57: ='Model inputs'!Q81*'Model inputs'!AI89 -> 297.54639 | R57: ='Model inputs'!R81*'Model inputs'!AI89 -> 371.93298 | S57: ='Model inputs'!S81*'Model inputs'!AI89 -> 464.91623 | T57: ='Model inputs'!T81*'Model inputs'!AI89 -> 581.14529 | U57: ='Model inputs'!U81*'Model inputs'!AI89 -> 726.43161 | V57: ='Model inputs'!V81*'Model inputs'!AI89 -> 908.03951 | W57: ='Model inputs'!W81*'Model inputs'!AI89 -> 1135.0494 | X57: ='Model inputs'!X81*'Model inputs'!AI89 -> 1135.0494 | Y57: ='Model inputs'!Y81*'Model inputs'!AI89 -> 1135.0494 | Z57: ='Model inputs'!Z81*'Model inputs'!AI89 -> 1135.0494 | AA57: ='Model inputs'!AA81*'Model inputs'!AI89 -> 1135.0494 | AB57: ='Model inputs'!AB81*'Model inputs'!AI89 -> 1135.0494 | AC57: ='Model inputs'!AC81*'Model inputs'!AI89 -> 1135.0494 | AD57: ='Model inputs'!AD81*'Model inputs'!AI89 -> 1135.0494 | AE57: ='Model inputs'!AE81*'Model inputs'!AI89 -> 1135.0494 | AF57: ='Model inputs'!AF81*'Model inputs'!AI89 -> 1135.0494 | AG57: ='Model inputs'!AG81*'Model inputs'!AI89 -> 1135.0494 | AH57: ='Model inputs'!AH81*'Model inputs'!AI89 -> 1135.0494
A58: Monthly job growth · Main Scenario | AI58: =0 -> 0
A59: Monthly job growth · Growth · $0.60 | AI59: =0.25 -> 0.25
A60: Monthly job growth · Base · $0.60 | AI60: ='Model inputs'!AI58 -> 0
A61: Monthly job growth · Growth · $0.34 | AI61: =0.25 -> 0.25
A62: Months since launch · Main Scenario | B62: 0 | C62: 0 | D62: 0 | E62: 0 | F62: 0 | G62: 0 | H62: 0 | I62: 0 | J62: 0 | K62: =IF(IF(IF(ISERROR(DATE(2026,10,1)<DATE(YEAR('Model inputs'!AI114),MONTH('Model inputs'!AI114),1)),DATE(2026,10,1)<DATE(YEAR('Model inputs'!AI114),MONTH('Model inputs'!AI114),1),IF(DATE(YEAR('Model inputs'!AI114),MONTH('Model inputs'!AI114),1)="","",DATE(2026,10,1)<DATE(YEAR('Model inputs'!AI114),MONTH('Model inputs'!AI114),1)))="",FALSE,IF(ISERROR(DATE(2026,10,1)<DATE(YEAR('Model inputs'!AI114),MONTH('Model inputs'!AI114),1)),DATE(2026,10,1)<DATE(YEAR('Model inputs'!AI114),MONTH('Model inputs'!AI114),1),IF(DATE(YEAR('Model inputs'!AI114),MONTH('Model inputs'!AI114),1)="","",DATE(2026,10,1)<DATE(YEAR('Model inputs'!AI114),MONTH('Model inputs'!AI114),1)))),0,IFERROR(DATEDIF(DATE(YEAR('Model inputs'!AI114),MONTH('Model inputs'!AI114),1),DATE(2026,10,1),"M"),0)+1) -> 0 | L62: =IF(IF(IF(ISERROR(DATE(2026,11,1)<DATE(YEAR('Model inputs'!AI114),MONTH('Model inputs'!AI114),1)),DATE(2026,11,1)<DATE(YEAR('Model inputs'!AI114),MONTH('Model inputs'!AI114),1),IF(DATE(YEAR('Model inputs'!AI114),MONTH('Model inputs'!AI114),1)="","",DATE(2026,11,1)<DATE(YEAR('Model inputs'!AI114),MONTH('Model inputs'!AI114),1)))="",FALSE,IF(ISERROR(DATE(2026,11,1)<DATE(YEAR('Model inputs'!AI114),MONTH('Model inputs'!AI114),1)),DATE(2026,11,1)<DATE(YEAR('Model inputs'!AI114),MONTH('Model inputs'!AI114),1),IF(DATE(YEAR('Model inputs'!AI114),MONTH('Model inputs'!AI114),1)="","",DATE(2026,11,1)<DATE(YEAR('Model inputs'!AI114),MONTH('Model inputs'!AI114),1)))),0,IFERROR(DATEDIF(DATE(YEAR('Model inputs'!AI114),MONTH('Model inputs'!AI114),1),DATE(2026,11,1),"M"),0)+1) -> 1 | M62: =IF(IF(IF(ISERROR(DATE(2026,12,1)<DATE(YEAR('Model inputs'!AI114),MONTH('Model inputs'!AI114),1)),DATE(2026,12,1)<DATE(YEAR('Model inputs'!AI114),MONTH('Model inputs'!AI114),1),IF(DATE(YEAR('Model inputs'!AI114),MONTH('Model inputs'!AI114),1)="","",DATE(2026,12,1)<DATE(YEAR('Model inputs'!AI114),MONTH('Model inputs'!AI114),1)))="",FALSE,IF(ISERROR(DATE(2026,12,1)<DATE(YEAR('Model inputs'!AI114),MONTH('Model inputs'!AI114),1)),DATE(2026,12,1)<DATE(YEAR('Model inputs'!AI114),MONTH('Model inputs'!AI114),1),IF(DATE(YEAR('Model inputs'!AI114),MONTH('Model inputs'!AI114),1)="","",DATE(2026,12,1)<DATE(YEAR('Model inputs'!AI114),MONTH('Model inputs'!AI114),1)))),0,IFERROR(DATEDIF(DATE(YEAR('Model inputs'!AI114),MONTH('Model inputs'!AI114),1),DATE(2026,12,1),"M"),0)+1) -> 2 | N62: =IF(IF(IF(ISERROR(DATE(2027,1,1)<DATE(YEAR('Model inputs'!AI114),MONTH('Model inputs'!AI114),1)),DATE(2027,1,1)<DATE(YEAR('Model inputs'!AI114),MONTH('Model inputs'!AI114),1),IF(DATE(YEAR('Model inputs'!AI114),MONTH('Model inputs'!AI114),1)="","",DATE(2027,1,1)<DATE(YEAR('Model inputs'!AI114),MONTH('Model inputs'!AI114),1)))="",FALSE,IF(ISERROR(DATE(2027,1,1)<DATE(YEAR('Model inputs'!AI114),MONTH('Model inputs'!AI114),1)),DATE(2027,1,1)<DATE(YEAR('Model inputs'!AI114),MONTH('Model inputs'!AI114),1),IF(DATE(YEAR('Model inputs'!AI114),MONTH('Model inputs'!AI114),1)="","",DATE(2027,1,1)<DATE(YEAR('Model inputs'!AI114),MONTH('Model inputs'!AI114),1)))),0,IFERROR(DATEDIF(DATE(YEAR('Model inputs'!AI114),MONTH('Model inputs'!AI114),1),DATE(2027,1,1),"M"),0)+1) -> 3 | O62: =IF(IF(IF(ISERROR(DATE(2027,2,1)<DATE(YEAR('Model inputs'!AI114),MONTH('Model inputs'!AI114),1)),DATE(2027,2,1)<DATE(YEAR('Model inputs'!AI114),MONTH('Model inputs'!AI114),1),IF(DATE(YEAR('Model inputs'!AI114),MONTH('Model inputs'!AI114),1)="","",DATE(2027,2,1)<DATE(YEAR('Model inputs'!AI114),MONTH('Model inputs'!AI114),1)))="",FALSE,IF(ISERROR(DATE(2027,2,1)<DATE(YEAR('Model inputs'!AI114),MONTH('Model inputs'!AI114),1)),DATE(2027,2,1)<DATE(YEAR('Model inputs'!AI114),MONTH('Model inputs'!AI114),1),IF(DATE(YEAR('Model inputs'!AI114),MONTH('Model inputs'!AI114),1)="","",DATE(2027,2,1)<DATE(YEAR('Model inputs'!AI114),MONTH('Model inputs'!AI114),1)))),0,IFERROR(DATEDIF(DATE(YEAR('Model inputs'!AI114),MONTH('Model inputs'!AI114),1),DATE(2027,2,1),"M"),0)+1) -> 4 | P62: =IF(IF(IF(ISERROR(DATE(2027,3,1)<DATE(YEAR('Model inputs'!AI114),MONTH('Model inputs'!AI114),1)),DATE(2027,3,1)<DATE(YEAR('Model inputs'!AI114),MONTH('Model inputs'!AI114),1),IF(DATE(YEAR('Model inputs'!AI114),MONTH('Model inputs'!AI114),1)="","",DATE(2027,3,1)<DATE(YEAR('Model inputs'!AI114),MONTH('Model inputs'!AI114),1)))="",FALSE,IF(ISERROR(DATE(2027,3,1)<DATE(YEAR('Model inputs'!AI114),MONTH('Model inputs'!AI114),1)),DATE(2027,3,1)<DATE(YEAR('Model inputs'!AI114),MONTH('Model inputs'!AI114),1),IF(DATE(YEAR('Model inputs'!AI114),MONTH('Model inputs'!AI114),1)="","",DATE(2027,3,1)<DATE(YEAR('Model inputs'!AI114),MONTH('Model inputs'!AI114),1)))),0,IFERROR(DATEDIF(DATE(YEAR('Model inputs'!AI114),MONTH('Model inputs'!AI114),1),DATE(2027,3,1),"M"),0)+1) -> 5 | Q62: =IF(IF(IF(ISERROR(DATE(2027,4,1)<DATE(YEAR('Model inputs'!AI114),MONTH('Model inputs'!AI114),1)),DATE(2027,4,1)<DATE(YEAR('Model inputs'!AI114),MONTH('Model inputs'!AI114),1),IF(DATE(YEAR('Model inputs'!AI114),MONTH('Model inputs'!AI114),1)="","",DATE(2027,4,1)<DATE(YEAR('Model inputs'!AI114),MONTH('Model inputs'!AI114),1)))="",FALSE,IF(ISERROR(DATE(2027,4,1)<DATE(YEAR('Model inputs'!AI114),MONTH('Model inputs'!AI114),1)),DATE(2027,4,1)<DATE(YEAR('Model inputs'!AI114),MONTH('Model inputs'!AI114),1),IF(DATE(YEAR('Model inputs'!AI114),MONTH('Model inputs'!AI114),1)="","",DATE(2027,4,1)<DATE(YEAR('Model inputs'!AI114),MONTH('Model inputs'!AI114),1)))),0,IFERROR(DATEDIF(DATE(YEAR('Model inputs'!AI114),MONTH('Model inputs'!AI114),1),DATE(2027,4,1),"M"),0)+1) -> 6 | R62: =IF(IF(IF(ISERROR(DATE(2027,5,1)<DATE(YEAR('Model inputs'!AI114),MONTH('Model inputs'!AI114),1)),DATE(2027,5,1)<DATE(YEAR('Model inputs'!AI114),MONTH('Model inputs'!AI114),1),IF(DATE(YEAR('Model inputs'!AI114),MONTH('Model inputs'!AI114),1)="","",DATE(2027,5,1)<DATE(YEAR('Model inputs'!AI114),MONTH('Model inputs'!AI114),1)))="",FALSE,IF(ISERROR(DATE(2027,5,1)<DATE(YEAR('Model inputs'!AI114),MONTH('Model inputs'!AI114),1)),DATE(2027,5,1)<DATE(YEAR('Model inputs'!AI114),MONTH('Model inputs'!AI114),1),IF(DATE(YEAR('Model inputs'!AI114),MONTH('Model inputs'!AI114),1)="","",DATE(2027,5,1)<DATE(YEAR('Model inputs'!AI114),MONTH('Model inputs'!AI114),1)))),0,IFERROR(DATEDIF(DATE(YEAR('Model inputs'!AI114),MONTH('Model inputs'!AI114),1),DATE(2027,5,1),"M"),0)+1) -> 7 | S62: =IF(IF(IF(ISERROR(DATE(2027,6,1)<DATE(YEAR('Model inputs'!AI114),MONTH('Model inputs'!AI114),1)),DATE(2027,6,1)<DATE(YEAR('Model inputs'!AI114),MONTH('Model inputs'!AI114),1),IF(DATE(YEAR('Model inputs'!AI114),MONTH('Model inputs'!AI114),1)="","",DATE(2027,6,1)<DATE(YEAR('Model inputs'!AI114),MONTH('Model inputs'!AI114),1)))="",FALSE,IF(ISERROR(DATE(2027,6,1)<DATE(YEAR('Model inputs'!AI114),MONTH('Model inputs'!AI114),1)),DATE(2027,6,1)<DATE(YEAR('Model inputs'!AI114),MONTH('Model inputs'!AI114),1),IF(DATE(YEAR('Model inputs'!AI114),MONTH('Model inputs'!AI114),1)="","",DATE(2027,6,1)<DATE(YEAR('Model inputs'!AI114),MONTH('Model inputs'!AI114),1)))),0,IFERROR(DATEDIF(DATE(YEAR('Model inputs'!AI114),MONTH('Model inputs'!AI114),1),DATE(2027,6,1),"M"),0)+1) -> 8 | T62: =IF(IF(IF(ISERROR(DATE(2027,7,1)<DATE(YEAR('Model inputs'!AI114),MONTH('Model inputs'!AI114),1)),DATE(2027,7,1)<DATE(YEAR('Model inputs'!AI114),MONTH('Model inputs'!AI114),1),IF(DATE(YEAR('Model inputs'!AI114),MONTH('Model inputs'!AI114),1)="","",DATE(2027,7,1)<DATE(YEAR('Model inputs'!AI114),MONTH('Model inputs'!AI114),1)))="",FALSE,IF(ISERROR(DATE(2027,7,1)<DATE(YEAR('Model inputs'!AI114),MONTH('Model inputs'!AI114),1)),DATE(2027,7,1)<DATE(YEAR('Model inputs'!AI114),MONTH('Model inputs'!AI114),1),IF(DATE(YEAR('Model inputs'!AI114),MONTH('Model inputs'!AI114),1)="","",DATE(2027,7,1)<DATE(YEAR('Model inputs'!AI114),MONTH('Model inputs'!AI114),1)))),0,IFERROR(DATEDIF(DATE(YEAR('Model inputs'!AI114),MONTH('Model inputs'!AI114),1),DATE(2027,7,1),"M"),0)+1) -> 9 | U62: =IF(IF(IF(ISERROR(DATE(2027,8,1)<DATE(YEAR('Model inputs'!AI114),MONTH('Model inputs'!AI114),1)),DATE(2027,8,1)<DATE(YEAR('Model inputs'!AI114),MONTH('Model inputs'!AI114),1),IF(DATE(YEAR('Model inputs'!AI114),MONTH('Model inputs'!AI114),1)="","",DATE(2027,8,1)<DATE(YEAR('Model inputs'!AI114),MONTH('Model inputs'!AI114),1)))="",FALSE,IF(ISERROR(DATE(2027,8,1)<DATE(YEAR('Model inputs'!AI114),MONTH('Model inputs'!AI114),1)),DATE(2027,8,1)<DATE(YEAR('Model inputs'!AI114),MONTH('Model inputs'!AI114),1),IF(DATE(YEAR('Model inputs'!AI114),MONTH('Model inputs'!AI114),1)="","",DATE(2027,8,1)<DATE(YEAR('Model inputs'!AI114),MONTH('Model inputs'!AI114),1)))),0,IFERROR(DATEDIF(DATE(YEAR('Model inputs'!AI114),MONTH('Model inputs'!AI114),1),DATE(2027,8,1),"M"),0)+1) -> 10 | V62: =IF(IF(IF(ISERROR(DATE(2027,9,1)<DATE(YEAR('Model inputs'!AI114),MONTH('Model inputs'!AI114),1)),DATE(2027,9,1)<DATE(YEAR('Model inputs'!AI114),MONTH('Model inputs'!AI114),1),IF(DATE(YEAR('Model inputs'!AI114),MONTH('Model inputs'!AI114),1)="","",DATE(2027,9,1)<DATE(YEAR('Model inputs'!AI114),MONTH('Model inputs'!AI114),1)))="",FALSE,IF(ISERROR(DATE(2027,9,1)<DATE(YEAR('Model inputs'!AI114),MONTH('Model inputs'!AI114),1)),DATE(2027,9,1)<DATE(YEAR('Model inputs'!AI114),MONTH('Model inputs'!AI114),1),IF(DATE(YEAR('Model inputs'!AI114),MONTH('Model inputs'!AI114),1)="","",DATE(2027,9,1)<DATE(YEAR('Model inputs'!AI114),MONTH('Model inputs'!AI114),1)))),0,IFERROR(DATEDIF(DATE(YEAR('Model inputs'!AI114),MONTH('Model inputs'!AI114),1),DATE(2027,9,1),"M"),0)+1) -> 11 | W62: =IF(IF(IF(ISERROR(DATE(2027,10,1)<DATE(YEAR('Model inputs'!AI114),MONTH('Model inputs'!AI114),1)),DATE(2027,10,1)<DATE(YEAR('Model inputs'!AI114),MONTH('Model inputs'!AI114),1),IF(DATE(YEAR('Model inputs'!AI114),MONTH('Model inputs'!AI114),1)="","",DATE(2027,10,1)<DATE(YEAR('Model inputs'!AI114),MONTH('Model inputs'!AI114),1)))="",FALSE,IF(ISERROR(DATE(2027,10,1)<DATE(YEAR('Model inputs'!AI114),MONTH('Model inputs'!AI114),1)),DATE(2027,10,1)<DATE(YEAR('Model inputs'!AI114),MONTH('Model inputs'!AI114),1),IF(DATE(YEAR('Model inputs'!AI114),MONTH('Model inputs'!AI114),1)="","",DATE(2027,10,1)<DATE(YEAR('Model inputs'!AI114),MONTH('Model inputs'!AI114),1)))),0,IFERROR(DATEDIF(DATE(YEAR('Model inputs'!AI114),MONTH('Model inputs'!AI114),1),DATE(2027,10,1),"M"),0)+1) -> 12 | X62: =IF(IF(IF(ISERROR(DATE(2027,11,1)<DATE(YEAR('Model inputs'!AI114),MONTH('Model inputs'!AI114),1)),DATE(2027,11,1)<DATE(YEAR('Model inputs'!AI114),MONTH('Model inputs'!AI114),1),IF(DATE(YEAR('Model inputs'!AI114),MONTH('Model inputs'!AI114),1)="","",DATE(2027,11,1)<DATE(YEAR('Model inputs'!AI114),MONTH('Model inputs'!AI114),1)))="",FALSE,IF(ISERROR(DATE(2027,11,1)<DATE(YEAR('Model inputs'!AI114),MONTH('Model inputs'!AI114),1)),DATE(2027,11,1)<DATE(YEAR('Model inputs'!AI114),MONTH('Model inputs'!AI114),1),IF(DATE(YEAR('Model inputs'!AI114),MONTH('Model inputs'!AI114),1)="","",DATE(2027,11,1)<DATE(YEAR('Model inputs'!AI114),MONTH('Model inputs'!AI114),1)))),0,IFERROR(DATEDIF(DATE(YEAR('Model inputs'!AI114),MONTH('Model inputs'!AI114),1),DATE(2027,11,1),"M"),0)+1) -> 13 | Y62: =IF(IF(IF(ISERROR(DATE(2027,12,1)<DATE(YEAR('Model inputs'!AI114),MONTH('Model inputs'!AI114),1)),DATE(2027,12,1)<DATE(YEAR('Model inputs'!AI114),MONTH('Model inputs'!AI114),1),IF(DATE(YEAR('Model inputs'!AI114),MONTH('Model inputs'!AI114),1)="","",DATE(2027,12,1)<DATE(YEAR('Model inputs'!AI114),MONTH('Model inputs'!AI114),1)))="",FALSE,IF(ISERROR(DATE(2027,12,1)<DATE(YEAR('Model inputs'!AI114),MONTH('Model inputs'!AI114),1)),DATE(2027,12,1)<DATE(YEAR('Model inputs'!AI114),MONTH('Model inputs'!AI114),1),IF(DATE(YEAR('Model inputs'!AI114),MONTH('Model inputs'!AI114),1)="","",DATE(2027,12,1)<DATE(YEAR('Model inputs'!AI114),MONTH('Model inputs'!AI114),1)))),0,IFERROR(DATEDIF(DATE(YEAR('Model inputs'!AI114),MONTH('Model inputs'!AI114),1),DATE(2027,12,1),"M"),0)+1) -> 14 | Z62: =IF(IF(IF(ISERROR(DATE(2028,1,1)<DATE(YEAR('Model inputs'!AI114),MONTH('Model inputs'!AI114),1)),DATE(2028,1,1)<DATE(YEAR('Model inputs'!AI114),MONTH('Model inputs'!AI114),1),IF(DATE(YEAR('Model inputs'!AI114),MONTH('Model inputs'!AI114),1)="","",DATE(2028,1,1)<DATE(YEAR('Model inputs'!AI114),MONTH('Model inputs'!AI114),1)))="",FALSE,IF(ISERROR(DATE(2028,1,1)<DATE(YEAR('Model inputs'!AI114),MONTH('Model inputs'!AI114),1)),DATE(2028,1,1)<DATE(YEAR('Model inputs'!AI114),MONTH('Model inputs'!AI114),1),IF(DATE(YEAR('Model inputs'!AI114),MONTH('Model inputs'!AI114),1)="","",DATE(2028,1,1)<DATE(YEAR('Model inputs'!AI114),MONTH('Model inputs'!AI114),1)))),0,IFERROR(DATEDIF(DATE(YEAR('Model inputs'!AI114),MONTH('Model inputs'!AI114),1),DATE(2028,1,1),"M"),0)+1) -> 15 | AA62: =IF(IF(IF(ISERROR(DATE(2028,2,1)<DATE(YEAR('Model inputs'!AI114),MONTH('Model inputs'!AI114),1)),DATE(2028,2,1)<DATE(YEAR('Model inputs'!AI114),MONTH('Model inputs'!AI114),1),IF(DATE(YEAR('Model inputs'!AI114),MONTH('Model inputs'!AI114),1)="","",DATE(2028,2,1)<DATE(YEAR('Model inputs'!AI114),MONTH('Model inputs'!AI114),1)))="",FALSE,IF(ISERROR(DATE(2028,2,1)<DATE(YEAR('Model inputs'!AI114),MONTH('Model inputs'!AI114),1)),DATE(2028,2,1)<DATE(YEAR('Model inputs'!AI114),MONTH('Model inputs'!AI114),1),IF(DATE(YEAR('Model inputs'!AI114),MONTH('Model inputs'!AI114),1)="","",DATE(2028,2,1)<DATE(YEAR('Model inputs'!AI114),MONTH('Model inputs'!AI114),1)))),0,IFERROR(DATEDIF(DATE(YEAR('Model inputs'!AI114),MONTH('Model inputs'!AI114),1),DATE(2028,2,1),"M"),0)+1) -> 16 | AB62: =IF(IF(IF(ISERROR(DATE(2028,3,1)<DATE(YEAR('Model inputs'!AI114),MONTH('Model inputs'!AI114),1)),DATE(2028,3,1)<DATE(YEAR('Model inputs'!AI114),MONTH('Model inputs'!AI114),1),IF(DATE(YEAR('Model inputs'!AI114),MONTH('Model inputs'!AI114),1)="","",DATE(2028,3,1)<DATE(YEAR('Model inputs'!AI114),MONTH('Model inputs'!AI114),1)))="",FALSE,IF(ISERROR(DATE(2028,3,1)<DATE(YEAR('Model inputs'!AI114),MONTH('Model inputs'!AI114),1)),DATE(2028,3,1)<DATE(YEAR('Model inputs'!AI114),MONTH('Model inputs'!AI114),1),IF(DATE(YEAR('Model inputs'!AI114),MONTH('Model inputs'!AI114),1)="","",DATE(2028,3,1)<DATE(YEAR('Model inputs'!AI114),MONTH('Model inputs'!AI114),1)))),0,IFERROR(DATEDIF(DATE(YEAR('Model inputs'!AI114),MONTH('Model inputs'!AI114),1),DATE(2028,3,1),"M"),0)+1) -> 17 | AC62: =IF(IF(IF(ISERROR(DATE(2028,4,1)<DATE(YEAR('Model inputs'!AI114),MONTH('Model inputs'!AI114),1)),DATE(2028,4,1)<DATE(YEAR('Model inputs'!AI114),MONTH('Model inputs'!AI114),1),IF(DATE(YEAR('Model inputs'!AI114),MONTH('Model inputs'!AI114),1)="","",DATE(2028,4,1)<DATE(YEAR('Model inputs'!AI114),MONTH('Model inputs'!AI114),1)))="",FALSE,IF(ISERROR(DATE(2028,4,1)<DATE(YEAR('Model inputs'!AI114),MONTH('Model inputs'!AI114),1)),DATE(2028,4,1)<DATE(YEAR('Model inputs'!AI114),MONTH('Model inputs'!AI114),1),IF(DATE(YEAR('Model inputs'!AI114),MONTH('Model inputs'!AI114),1)="","",DATE(2028,4,1)<DATE(YEAR('Model inputs'!AI114),MONTH('Model inputs'!AI114),1)))),0,IFERROR(DATEDIF(DATE(YEAR('Model inputs'!AI114),MONTH('Model inputs'!AI114),1),DATE(2028,4,1),"M"),0)+1) -> 18 | AD62: =IF(IF(IF(ISERROR(DATE(2028,5,1)<DATE(YEAR('Model inputs'!AI114),MONTH('Model inputs'!AI114),1)),DATE(2028,5,1)<DATE(YEAR('Model inputs'!AI114),MONTH('Model inputs'!AI114),1),IF(DATE(YEAR('Model inputs'!AI114),MONTH('Model inputs'!AI114),1)="","",DATE(2028,5,1)<DATE(YEAR('Model inputs'!AI114),MONTH('Model inputs'!AI114),1)))="",FALSE,IF(ISERROR(DATE(2028,5,1)<DATE(YEAR('Model inputs'!AI114),MONTH('Model inputs'!AI114),1)),DATE(2028,5,1)<DATE(YEAR('Model inputs'!AI114),MONTH('Model inputs'!AI114),1),IF(DATE(YEAR('Model inputs'!AI114),MONTH('Model inputs'!AI114),1)="","",DATE(2028,5,1)<DATE(YEAR('Model inputs'!AI114),MONTH('Model inputs'!AI114),1)))),0,IFERROR(DATEDIF(DATE(YEAR('Model inputs'!AI114),MONTH('Model inputs'!AI114),1),DATE(2028,5,1),"M"),0)+1) -> 19 | AE62: =IF(IF(IF(ISERROR(DATE(2028,6,1)<DATE(YEAR('Model inputs'!AI114),MONTH('Model inputs'!AI114),1)),DATE(2028,6,1)<DATE(YEAR('Model inputs'!AI114),MONTH('Model inputs'!AI114),1),IF(DATE(YEAR('Model inputs'!AI114),MONTH('Model inputs'!AI114),1)="","",DATE(2028,6,1)<DATE(YEAR('Model inputs'!AI114),MONTH('Model inputs'!AI114),1)))="",FALSE,IF(ISERROR(DATE(2028,6,1)<DATE(YEAR('Model inputs'!AI114),MONTH('Model inputs'!AI114),1)),DATE(2028,6,1)<DATE(YEAR('Model inputs'!AI114),MONTH('Model inputs'!AI114),1),IF(DATE(YEAR('Model inputs'!AI114),MONTH('Model inputs'!AI114),1)="","",DATE(2028,6,1)<DATE(YEAR('Model inputs'!AI114),MONTH('Model inputs'!AI114),1)))),0,IFERROR(DATEDIF(DATE(YEAR('Model inputs'!AI114),MONTH('Model inputs'!AI114),1),DATE(2028,6,1),"M"),0)+1) -> 20 | AF62: =IF(IF(IF(ISERROR(DATE(2028,7,1)<DATE(YEAR('Model inputs'!AI114),MONTH('Model inputs'!AI114),1)),DATE(2028,7,1)<DATE(YEAR('Model inputs'!AI114),MONTH('Model inputs'!AI114),1),IF(DATE(YEAR('Model inputs'!AI114),MONTH('Model inputs'!AI114),1)="","",DATE(2028,7,1)<DATE(YEAR('Model inputs'!AI114),MONTH('Model inputs'!AI114),1)))="",FALSE,IF(ISERROR(DATE(2028,7,1)<DATE(YEAR('Model inputs'!AI114),MONTH('Model inputs'!AI114),1)),DATE(2028,7,1)<DATE(YEAR('Model inputs'!AI114),MONTH('Model inputs'!AI114),1),IF(DATE(YEAR('Model inputs'!AI114),MONTH('Model inputs'!AI114),1)="","",DATE(2028,7,1)<DATE(YEAR('Model inputs'!AI114),MONTH('Model inputs'!AI114),1)))),0,IFERROR(DATEDIF(DATE(YEAR('Model inputs'!AI114),MONTH('Model inputs'!AI114),1),DATE(2028,7,1),"M"),0)+1) -> 21 | AG62: =IF(IF(IF(ISERROR(DATE(2028,8,1)<DATE(YEAR('Model inputs'!AI114),MONTH('Model inputs'!AI114),1)),DATE(2028,8,1)<DATE(YEAR('Model inputs'!AI114),MONTH('Model inputs'!AI114),1),IF(DATE(YEAR('Model inputs'!AI114),MONTH('Model inputs'!AI114),1)="","",DATE(2028,8,1)<DATE(YEAR('Model inputs'!AI114),MONTH('Model inputs'!AI114),1)))="",FALSE,IF(ISERROR(DATE(2028,8,1)<DATE(YEAR('Model inputs'!AI114),MONTH('Model inputs'!AI114),1)),DATE(2028,8,1)<DATE(YEAR('Model inputs'!AI114),MONTH('Model inputs'!AI114),1),IF(DATE(YEAR('Model inputs'!AI114),MONTH('Model inputs'!AI114),1)="","",DATE(2028,8,1)<DATE(YEAR('Model inputs'!AI114),MONTH('Model inputs'!AI114),1)))),0,IFERROR(DATEDIF(DATE(YEAR('Model inputs'!AI114),MONTH('Model inputs'!AI114),1),DATE(2028,8,1),"M"),0)+1) -> 22 | AH62: =IF(IF(IF(ISERROR(DATE(2028,9,1)<DATE(YEAR('Model inputs'!AI114),MONTH('Model inputs'!AI114),1)),DATE(2028,9,1)<DATE(YEAR('Model inputs'!AI114),MONTH('Model inputs'!AI114),1),IF(DATE(YEAR('Model inputs'!AI114),MONTH('Model inputs'!AI114),1)="","",DATE(2028,9,1)<DATE(YEAR('Model inputs'!AI114),MONTH('Model inputs'!AI114),1)))="",FALSE,IF(ISERROR(DATE(2028,9,1)<DATE(YEAR('Model inputs'!AI114),MONTH('Model inputs'!AI114),1)),DATE(2028,9,1)<DATE(YEAR('Model inputs'!AI114),MONTH('Model inputs'!AI114),1),IF(DATE(YEAR('Model inputs'!AI114),MONTH('Model inputs'!AI114),1)="","",DATE(2028,9,1)<DATE(YEAR('Model inputs'!AI114),MONTH('Model inputs'!AI114),1)))),0,IFERROR(DATEDIF(DATE(YEAR('Model inputs'!AI114),MONTH('Model inputs'!AI114),1),DATE(2028,9,1),"M"),0)+1) -> 23
A63: Months since launch · Growth · $0.60 | B63: 0 | C63: 0 | D63: 0 | E63: 0 | F63: 0 | G63: 0 | H63: 0 | I63: 0 | J63: 0 | K63: =IF(IF(IF(ISERROR(DATE(2026,10,1)<DATE(YEAR('Model inputs'!AI115),MONTH('Model inputs'!AI115),1)),DATE(2026,10,1)<DATE(YEAR('Model inputs'!AI115),MONTH('Model inputs'!AI115),1),IF(DATE(YEAR('Model inputs'!AI115),MONTH('Model inputs'!AI115),1)="","",DATE(2026,10,1)<DATE(YEAR('Model inputs'!AI115),MONTH('Model inputs'!AI115),1)))="",FALSE,IF(ISERROR(DATE(2026,10,1)<DATE(YEAR('Model inputs'!AI115),MONTH('Model inputs'!AI115),1)),DATE(2026,10,1)<DATE(YEAR('Model inputs'!AI115),MONTH('Model inputs'!AI115),1),IF(DATE(YEAR('Model inputs'!AI115),MONTH('Model inputs'!AI115),1)="","",DATE(2026,10,1)<DATE(YEAR('Model inputs'!AI115),MONTH('Model inputs'!AI115),1)))),0,IFERROR(DATEDIF(DATE(YEAR('Model inputs'!AI115),MONTH('Model inputs'!AI115),1),DATE(2026,10,1),"M"),0)+1) -> 0 | L63: =IF(IF(IF(ISERROR(DATE(2026,11,1)<DATE(YEAR('Model inputs'!AI115),MONTH('Model inputs'!AI115),1)),DATE(2026,11,1)<DATE(YEAR('Model inputs'!AI115),MONTH('Model inputs'!AI115),1),IF(DATE(YEAR('Model inputs'!AI115),MONTH('Model inputs'!AI115),1)="","",DATE(2026,11,1)<DATE(YEAR('Model inputs'!AI115),MONTH('Model inputs'!AI115),1)))="",FALSE,IF(ISERROR(DATE(2026,11,1)<DATE(YEAR('Model inputs'!AI115),MONTH('Model inputs'!AI115),1)),DATE(2026,11,1)<DATE(YEAR('Model inputs'!AI115),MONTH('Model inputs'!AI115),1),IF(DATE(YEAR('Model inputs'!AI115),MONTH('Model inputs'!AI115),1)="","",DATE(2026,11,1)<DATE(YEAR('Model inputs'!AI115),MONTH('Model inputs'!AI115),1)))),0,IFERROR(DATEDIF(DATE(YEAR('Model inputs'!AI115),MONTH('Model inputs'!AI115),1),DATE(2026,11,1),"M"),0)+1) -> 1 | M63: =IF(IF(IF(ISERROR(DATE(2026,12,1)<DATE(YEAR('Model inputs'!AI115),MONTH('Model inputs'!AI115),1)),DATE(2026,12,1)<DATE(YEAR('Model inputs'!AI115),MONTH('Model inputs'!AI115),1),IF(DATE(YEAR('Model inputs'!AI115),MONTH('Model inputs'!AI115),1)="","",DATE(2026,12,1)<DATE(YEAR('Model inputs'!AI115),MONTH('Model inputs'!AI115),1)))="",FALSE,IF(ISERROR(DATE(2026,12,1)<DATE(YEAR('Model inputs'!AI115),MONTH('Model inputs'!AI115),1)),DATE(2026,12,1)<DATE(YEAR('Model inputs'!AI115),MONTH('Model inputs'!AI115),1),IF(DATE(YEAR('Model inputs'!AI115),MONTH('Model inputs'!AI115),1)="","",DATE(2026,12,1)<DATE(YEAR('Model inputs'!AI115),MONTH('Model inputs'!AI115),1)))),0,IFERROR(DATEDIF(DATE(YEAR('Model inputs'!AI115),MONTH('Model inputs'!AI115),1),DATE(2026,12,1),"M"),0)+1) -> 2 | N63: =IF(IF(IF(ISERROR(DATE(2027,1,1)<DATE(YEAR('Model inputs'!AI115),MONTH('Model inputs'!AI115),1)),DATE(2027,1,1)<DATE(YEAR('Model inputs'!AI115),MONTH('Model inputs'!AI115),1),IF(DATE(YEAR('Model inputs'!AI115),MONTH('Model inputs'!AI115),1)="","",DATE(2027,1,1)<DATE(YEAR('Model inputs'!AI115),MONTH('Model inputs'!AI115),1)))="",FALSE,IF(ISERROR(DATE(2027,1,1)<DATE(YEAR('Model inputs'!AI115),MONTH('Model inputs'!AI115),1)),DATE(2027,1,1)<DATE(YEAR('Model inputs'!AI115),MONTH('Model inputs'!AI115),1),IF(DATE(YEAR('Model inputs'!AI115),MONTH('Model inputs'!AI115),1)="","",DATE(2027,1,1)<DATE(YEAR('Model inputs'!AI115),MONTH('Model inputs'!AI115),1)))),0,IFERROR(DATEDIF(DATE(YEAR('Model inputs'!AI115),MONTH('Model inputs'!AI115),1),DATE(2027,1,1),"M"),0)+1) -> 3 | O63: =IF(IF(IF(ISERROR(DATE(2027,2,1)<DATE(YEAR('Model inputs'!AI115),MONTH('Model inputs'!AI115),1)),DATE(2027,2,1)<DATE(YEAR('Model inputs'!AI115),MONTH('Model inputs'!AI115),1),IF(DATE(YEAR('Model inputs'!AI115),MONTH('Model inputs'!AI115),1)="","",DATE(2027,2,1)<DATE(YEAR('Model inputs'!AI115),MONTH('Model inputs'!AI115),1)))="",FALSE,IF(ISERROR(DATE(2027,2,1)<DATE(YEAR('Model inputs'!AI115),MONTH('Model inputs'!AI115),1)),DATE(2027,2,1)<DATE(YEAR('Model inputs'!AI115),MONTH('Model inputs'!AI115),1),IF(DATE(YEAR('Model inputs'!AI115),MONTH('Model inputs'!AI115),1)="","",DATE(2027,2,1)<DATE(YEAR('Model inputs'!AI115),MONTH('Model inputs'!AI115),1)))),0,IFERROR(DATEDIF(DATE(YEAR('Model inputs'!AI115),MONTH('Model inputs'!AI115),1),DATE(2027,2,1),"M"),0)+1) -> 4 | P63: =IF(IF(IF(ISERROR(DATE(2027,3,1)<DATE(YEAR('Model inputs'!AI115),MONTH('Model inputs'!AI115),1)),DATE(2027,3,1)<DATE(YEAR('Model inputs'!AI115),MONTH('Model inputs'!AI115),1),IF(DATE(YEAR('Model inputs'!AI115),MONTH('Model inputs'!AI115),1)="","",DATE(2027,3,1)<DATE(YEAR('Model inputs'!AI115),MONTH('Model inputs'!AI115),1)))="",FALSE,IF(ISERROR(DATE(2027,3,1)<DATE(YEAR('Model inputs'!AI115),MONTH('Model inputs'!AI115),1)),DATE(2027,3,1)<DATE(YEAR('Model inputs'!AI115),MONTH('Model inputs'!AI115),1),IF(DATE(YEAR('Model inputs'!AI115),MONTH('Model inputs'!AI115),1)="","",DATE(2027,3,1)<DATE(YEAR('Model inputs'!AI115),MONTH('Model inputs'!AI115),1)))),0,IFERROR(DATEDIF(DATE(YEAR('Model inputs'!AI115),MONTH('Model inputs'!AI115),1),DATE(2027,3,1),"M"),0)+1) -> 5 | Q63: =IF(IF(IF(ISERROR(DATE(2027,4,1)<DATE(YEAR('Model inputs'!AI115),MONTH('Model inputs'!AI115),1)),DATE(2027,4,1)<DATE(YEAR('Model inputs'!AI115),MONTH('Model inputs'!AI115),1),IF(DATE(YEAR('Model inputs'!AI115),MONTH('Model inputs'!AI115),1)="","",DATE(2027,4,1)<DATE(YEAR('Model inputs'!AI115),MONTH('Model inputs'!AI115),1)))="",FALSE,IF(ISERROR(DATE(2027,4,1)<DATE(YEAR('Model inputs'!AI115),MONTH('Model inputs'!AI115),1)),DATE(2027,4,1)<DATE(YEAR('Model inputs'!AI115),MONTH('Model inputs'!AI115),1),IF(DATE(YEAR('Model inputs'!AI115),MONTH('Model inputs'!AI115),1)="","",DATE(2027,4,1)<DATE(YEAR('Model inputs'!AI115),MONTH('Model inputs'!AI115),1)))),0,IFERROR(DATEDIF(DATE(YEAR('Model inputs'!AI115),MONTH('Model inputs'!AI115),1),DATE(2027,4,1),"M"),0)+1) -> 6 | R63: =IF(IF(IF(ISERROR(DATE(2027,5,1)<DATE(YEAR('Model inputs'!AI115),MONTH('Model inputs'!AI115),1)),DATE(2027,5,1)<DATE(YEAR('Model inputs'!AI115),MONTH('Model inputs'!AI115),1),IF(DATE(YEAR('Model inputs'!AI115),MONTH('Model inputs'!AI115),1)="","",DATE(2027,5,1)<DATE(YEAR('Model inputs'!AI115),MONTH('Model inputs'!AI115),1)))="",FALSE,IF(ISERROR(DATE(2027,5,1)<DATE(YEAR('Model inputs'!AI115),MONTH('Model inputs'!AI115),1)),DATE(2027,5,1)<DATE(YEAR('Model inputs'!AI115),MONTH('Model inputs'!AI115),1),IF(DATE(YEAR('Model inputs'!AI115),MONTH('Model inputs'!AI115),1)="","",DATE(2027,5,1)<DATE(YEAR('Model inputs'!AI115),MONTH('Model inputs'!AI115),1)))),0,IFERROR(DATEDIF(DATE(YEAR('Model inputs'!AI115),MONTH('Model inputs'!AI115),1),DATE(2027,5,1),"M"),0)+1) -> 7 | S63: =IF(IF(IF(ISERROR(DATE(2027,6,1)<DATE(YEAR('Model inputs'!AI115),MONTH('Model inputs'!AI115),1)),DATE(2027,6,1)<DATE(YEAR('Model inputs'!AI115),MONTH('Model inputs'!AI115),1),IF(DATE(YEAR('Model inputs'!AI115),MONTH('Model inputs'!AI115),1)="","",DATE(2027,6,1)<DATE(YEAR('Model inputs'!AI115),MONTH('Model inputs'!AI115),1)))="",FALSE,IF(ISERROR(DATE(2027,6,1)<DATE(YEAR('Model inputs'!AI115),MONTH('Model inputs'!AI115),1)),DATE(2027,6,1)<DATE(YEAR('Model inputs'!AI115),MONTH('Model inputs'!AI115),1),IF(DATE(YEAR('Model inputs'!AI115),MONTH('Model inputs'!AI115),1)="","",DATE(2027,6,1)<DATE(YEAR('Model inputs'!AI115),MONTH('Model inputs'!AI115),1)))),0,IFERROR(DATEDIF(DATE(YEAR('Model inputs'!AI115),MONTH('Model inputs'!AI115),1),DATE(2027,6,1),"M"),0)+1) -> 8 | T63: =IF(IF(IF(ISERROR(DATE(2027,7,1)<DATE(YEAR('Model inputs'!AI115),MONTH('Model inputs'!AI115),1)),DATE(2027,7,1)<DATE(YEAR('Model inputs'!AI115),MONTH('Model inputs'!AI115),1),IF(DATE(YEAR('Model inputs'!AI115),MONTH('Model inputs'!AI115),1)="","",DATE(2027,7,1)<DATE(YEAR('Model inputs'!AI115),MONTH('Model inputs'!AI115),1)))="",FALSE,IF(ISERROR(DATE(2027,7,1)<DATE(YEAR('Model inputs'!AI115),MONTH('Model inputs'!AI115),1)),DATE(2027,7,1)<DATE(YEAR('Model inputs'!AI115),MONTH('Model inputs'!AI115),1),IF(DATE(YEAR('Model inputs'!AI115),MONTH('Model inputs'!AI115),1)="","",DATE(2027,7,1)<DATE(YEAR('Model inputs'!AI115),MONTH('Model inputs'!AI115),1)))),0,IFERROR(DATEDIF(DATE(YEAR('Model inputs'!AI115),MONTH('Model inputs'!AI115),1),DATE(2027,7,1),"M"),0)+1) -> 9 | U63: =IF(IF(IF(ISERROR(DATE(2027,8,1)<DATE(YEAR('Model inputs'!AI115),MONTH('Model inputs'!AI115),1)),DATE(2027,8,1)<DATE(YEAR('Model inputs'!AI115),MONTH('Model inputs'!AI115),1),IF(DATE(YEAR('Model inputs'!AI115),MONTH('Model inputs'!AI115),1)="","",DATE(2027,8,1)<DATE(YEAR('Model inputs'!AI115),MONTH('Model inputs'!AI115),1)))="",FALSE,IF(ISERROR(DATE(2027,8,1)<DATE(YEAR('Model inputs'!AI115),MONTH('Model inputs'!AI115),1)),DATE(2027,8,1)<DATE(YEAR('Model inputs'!AI115),MONTH('Model inputs'!AI115),1),IF(DATE(YEAR('Model inputs'!AI115),MONTH('Model inputs'!AI115),1)="","",DATE(2027,8,1)<DATE(YEAR('Model inputs'!AI115),MONTH('Model inputs'!AI115),1)))),0,IFERROR(DATEDIF(DATE(YEAR('Model inputs'!AI115),MONTH('Model inputs'!AI115),1),DATE(2027,8,1),"M"),0)+1) -> 10 | V63: =IF(IF(IF(ISERROR(DATE(2027,9,1)<DATE(YEAR('Model inputs'!AI115),MONTH('Model inputs'!AI115),1)),DATE(2027,9,1)<DATE(YEAR('Model inputs'!AI115),MONTH('Model inputs'!AI115),1),IF(DATE(YEAR('Model inputs'!AI115),MONTH('Model inputs'!AI115),1)="","",DATE(2027,9,1)<DATE(YEAR('Model inputs'!AI115),MONTH('Model inputs'!AI115),1)))="",FALSE,IF(ISERROR(DATE(2027,9,1)<DATE(YEAR('Model inputs'!AI115),MONTH('Model inputs'!AI115),1)),DATE(2027,9,1)<DATE(YEAR('Model inputs'!AI115),MONTH('Model inputs'!AI115),1),IF(DATE(YEAR('Model inputs'!AI115),MONTH('Model inputs'!AI115),1)="","",DATE(2027,9,1)<DATE(YEAR('Model inputs'!AI115),MONTH('Model inputs'!AI115),1)))),0,IFERROR(DATEDIF(DATE(YEAR('Model inputs'!AI115),MONTH('Model inputs'!AI115),1),DATE(2027,9,1),"M"),0)+1) -> 11 | W63: =IF(IF(IF(ISERROR(DATE(2027,10,1)<DATE(YEAR('Model inputs'!AI115),MONTH('Model inputs'!AI115),1)),DATE(2027,10,1)<DATE(YEAR('Model inputs'!AI115),MONTH('Model inputs'!AI115),1),IF(DATE(YEAR('Model inputs'!AI115),MONTH('Model inputs'!AI115),1)="","",DATE(2027,10,1)<DATE(YEAR('Model inputs'!AI115),MONTH('Model inputs'!AI115),1)))="",FALSE,IF(ISERROR(DATE(2027,10,1)<DATE(YEAR('Model inputs'!AI115),MONTH('Model inputs'!AI115),1)),DATE(2027,10,1)<DATE(YEAR('Model inputs'!AI115),MONTH('Model inputs'!AI115),1),IF(DATE(YEAR('Model inputs'!AI115),MONTH('Model inputs'!AI115),1)="","",DATE(2027,10,1)<DATE(YEAR('Model inputs'!AI115),MONTH('Model inputs'!AI115),1)))),0,IFERROR(DATEDIF(DATE(YEAR('Model inputs'!AI115),MONTH('Model inputs'!AI115),1),DATE(2027,10,1),"M"),0)+1) -> 12 | X63: =IF(IF(IF(ISERROR(DATE(2027,11,1)<DATE(YEAR('Model inputs'!AI115),MONTH('Model inputs'!AI115),1)),DATE(2027,11,1)<DATE(YEAR('Model inputs'!AI115),MONTH('Model inputs'!AI115),1),IF(DATE(YEAR('Model inputs'!AI115),MONTH('Model inputs'!AI115),1)="","",DATE(2027,11,1)<DATE(YEAR('Model inputs'!AI115),MONTH('Model inputs'!AI115),1)))="",FALSE,IF(ISERROR(DATE(2027,11,1)<DATE(YEAR('Model inputs'!AI115),MONTH('Model inputs'!AI115),1)),DATE(2027,11,1)<DATE(YEAR('Model inputs'!AI115),MONTH('Model inputs'!AI115),1),IF(DATE(YEAR('Model inputs'!AI115),MONTH('Model inputs'!AI115),1)="","",DATE(2027,11,1)<DATE(YEAR('Model inputs'!AI115),MONTH('Model inputs'!AI115),1)))),0,IFERROR(DATEDIF(DATE(YEAR('Model inputs'!AI115),MONTH('Model inputs'!AI115),1),DATE(2027,11,1),"M"),0)+1) -> 13 | Y63: =IF(IF(IF(ISERROR(DATE(2027,12,1)<DATE(YEAR('Model inputs'!AI115),MONTH('Model inputs'!AI115),1)),DATE(2027,12,1)<DATE(YEAR('Model inputs'!AI115),MONTH('Model inputs'!AI115),1),IF(DATE(YEAR('Model inputs'!AI115),MONTH('Model inputs'!AI115),1)="","",DATE(2027,12,1)<DATE(YEAR('Model inputs'!AI115),MONTH('Model inputs'!AI115),1)))="",FALSE,IF(ISERROR(DATE(2027,12,1)<DATE(YEAR('Model inputs'!AI115),MONTH('Model inputs'!AI115),1)),DATE(2027,12,1)<DATE(YEAR('Model inputs'!AI115),MONTH('Model inputs'!AI115),1),IF(DATE(YEAR('Model inputs'!AI115),MONTH('Model inputs'!AI115),1)="","",DATE(2027,12,1)<DATE(YEAR('Model inputs'!AI115),MONTH('Model inputs'!AI115),1)))),0,IFERROR(DATEDIF(DATE(YEAR('Model inputs'!AI115),MONTH('Model inputs'!AI115),1),DATE(2027,12,1),"M"),0)+1) -> 14 | Z63: =IF(IF(IF(ISERROR(DATE(2028,1,1)<DATE(YEAR('Model inputs'!AI115),MONTH('Model inputs'!AI115),1)),DATE(2028,1,1)<DATE(YEAR('Model inputs'!AI115),MONTH('Model inputs'!AI115),1),IF(DATE(YEAR('Model inputs'!AI115),MONTH('Model inputs'!AI115),1)="","",DATE(2028,1,1)<DATE(YEAR('Model inputs'!AI115),MONTH('Model inputs'!AI115),1)))="",FALSE,IF(ISERROR(DATE(2028,1,1)<DATE(YEAR('Model inputs'!AI115),MONTH('Model inputs'!AI115),1)),DATE(2028,1,1)<DATE(YEAR('Model inputs'!AI115),MONTH('Model inputs'!AI115),1),IF(DATE(YEAR('Model inputs'!AI115),MONTH('Model inputs'!AI115),1)="","",DATE(2028,1,1)<DATE(YEAR('Model inputs'!AI115),MONTH('Model inputs'!AI115),1)))),0,IFERROR(DATEDIF(DATE(YEAR('Model inputs'!AI115),MONTH('Model inputs'!AI115),1),DATE(2028,1,1),"M"),0)+1) -> 15 | AA63: =IF(IF(IF(ISERROR(DATE(2028,2,1)<DATE(YEAR('Model inputs'!AI115),MONTH('Model inputs'!AI115),1)),DATE(2028,2,1)<DATE(YEAR('Model inputs'!AI115),MONTH('Model inputs'!AI115),1),IF(DATE(YEAR('Model inputs'!AI115),MONTH('Model inputs'!AI115),1)="","",DATE(2028,2,1)<DATE(YEAR('Model inputs'!AI115),MONTH('Model inputs'!AI115),1)))="",FALSE,IF(ISERROR(DATE(2028,2,1)<DATE(YEAR('Model inputs'!AI115),MONTH('Model inputs'!AI115),1)),DATE(2028,2,1)<DATE(YEAR('Model inputs'!AI115),MONTH('Model inputs'!AI115),1),IF(DATE(YEAR('Model inputs'!AI115),MONTH('Model inputs'!AI115),1)="","",DATE(2028,2,1)<DATE(YEAR('Model inputs'!AI115),MONTH('Model inputs'!AI115),1)))),0,IFERROR(DATEDIF(DATE(YEAR('Model inputs'!AI115),MONTH('Model inputs'!AI115),1),DATE(2028,2,1),"M"),0)+1) -> 16 | AB63: =IF(IF(IF(ISERROR(DATE(2028,3,1)<DATE(YEAR('Model inputs'!AI115),MONTH('Model inputs'!AI115),1)),DATE(2028,3,1)<DATE(YEAR('Model inputs'!AI115),MONTH('Model inputs'!AI115),1),IF(DATE(YEAR('Model inputs'!AI115),MONTH('Model inputs'!AI115),1)="","",DATE(2028,3,1)<DATE(YEAR('Model inputs'!AI115),MONTH('Model inputs'!AI115),1)))="",FALSE,IF(ISERROR(DATE(2028,3,1)<DATE(YEAR('Model inputs'!AI115),MONTH('Model inputs'!AI115),1)),DATE(2028,3,1)<DATE(YEAR('Model inputs'!AI115),MONTH('Model inputs'!AI115),1),IF(DATE(YEAR('Model inputs'!AI115),MONTH('Model inputs'!AI115),1)="","",DATE(2028,3,1)<DATE(YEAR('Model inputs'!AI115),MONTH('Model inputs'!AI115),1)))),0,IFERROR(DATEDIF(DATE(YEAR('Model inputs'!AI115),MONTH('Model inputs'!AI115),1),DATE(2028,3,1),"M"),0)+1) -> 17 | AC63: =IF(IF(IF(ISERROR(DATE(2028,4,1)<DATE(YEAR('Model inputs'!AI115),MONTH('Model inputs'!AI115),1)),DATE(2028,4,1)<DATE(YEAR('Model inputs'!AI115),MONTH('Model inputs'!AI115),1),IF(DATE(YEAR('Model inputs'!AI115),MONTH('Model inputs'!AI115),1)="","",DATE(2028,4,1)<DATE(YEAR('Model inputs'!AI115),MONTH('Model inputs'!AI115),1)))="",FALSE,IF(ISERROR(DATE(2028,4,1)<DATE(YEAR('Model inputs'!AI115),MONTH('Model inputs'!AI115),1)),DATE(2028,4,1)<DATE(YEAR('Model inputs'!AI115),MONTH('Model inputs'!AI115),1),IF(DATE(YEAR('Model inputs'!AI115),MONTH('Model inputs'!AI115),1)="","",DATE(2028,4,1)<DATE(YEAR('Model inputs'!AI115),MONTH('Model inputs'!AI115),1)))),0,IFERROR(DATEDIF(DATE(YEAR('Model inputs'!AI115),MONTH('Model inputs'!AI115),1),DATE(2028,4,1),"M"),0)+1) -> 18 | AD63: =IF(IF(IF(ISERROR(DATE(2028,5,1)<DATE(YEAR('Model inputs'!AI115),MONTH('Model inputs'!AI115),1)),DATE(2028,5,1)<DATE(YEAR('Model inputs'!AI115),MONTH('Model inputs'!AI115),1),IF(DATE(YEAR('Model inputs'!AI115),MONTH('Model inputs'!AI115),1)="","",DATE(2028,5,1)<DATE(YEAR('Model inputs'!AI115),MONTH('Model inputs'!AI115),1)))="",FALSE,IF(ISERROR(DATE(2028,5,1)<DATE(YEAR('Model inputs'!AI115),MONTH('Model inputs'!AI115),1)),DATE(2028,5,1)<DATE(YEAR('Model inputs'!AI115),MONTH('Model inputs'!AI115),1),IF(DATE(YEAR('Model inputs'!AI115),MONTH('Model inputs'!AI115),1)="","",DATE(2028,5,1)<DATE(YEAR('Model inputs'!AI115),MONTH('Model inputs'!AI115),1)))),0,IFERROR(DATEDIF(DATE(YEAR('Model inputs'!AI115),MONTH('Model inputs'!AI115),1),DATE(2028,5,1),"M"),0)+1) -> 19 | AE63: =IF(IF(IF(ISERROR(DATE(2028,6,1)<DATE(YEAR('Model inputs'!AI115),MONTH('Model inputs'!AI115),1)),DATE(2028,6,1)<DATE(YEAR('Model inputs'!AI115),MONTH('Model inputs'!AI115),1),IF(DATE(YEAR('Model inputs'!AI115),MONTH('Model inputs'!AI115),1)="","",DATE(2028,6,1)<DATE(YEAR('Model inputs'!AI115),MONTH('Model inputs'!AI115),1)))="",FALSE,IF(ISERROR(DATE(2028,6,1)<DATE(YEAR('Model inputs'!AI115),MONTH('Model inputs'!AI115),1)),DATE(2028,6,1)<DATE(YEAR('Model inputs'!AI115),MONTH('Model inputs'!AI115),1),IF(DATE(YEAR('Model inputs'!AI115),MONTH('Model inputs'!AI115),1)="","",DATE(2028,6,1)<DATE(YEAR('Model inputs'!AI115),MONTH('Model inputs'!AI115),1)))),0,IFERROR(DATEDIF(DATE(YEAR('Model inputs'!AI115),MONTH('Model inputs'!AI115),1),DATE(2028,6,1),"M"),0)+1) -> 20 | AF63: =IF(IF(IF(ISERROR(DATE(2028,7,1)<DATE(YEAR('Model inputs'!AI115),MONTH('Model inputs'!AI115),1)),DATE(2028,7,1)<DATE(YEAR('Model inputs'!AI115),MONTH('Model inputs'!AI115),1),IF(DATE(YEAR('Model inputs'!AI115),MONTH('Model inputs'!AI115),1)="","",DATE(2028,7,1)<DATE(YEAR('Model inputs'!AI115),MONTH('Model inputs'!AI115),1)))="",FALSE,IF(ISERROR(DATE(2028,7,1)<DATE(YEAR('Model inputs'!AI115),MONTH('Model inputs'!AI115),1)),DATE(2028,7,1)<DATE(YEAR('Model inputs'!AI115),MONTH('Model inputs'!AI115),1),IF(DATE(YEAR('Model inputs'!AI115),MONTH('Model inputs'!AI115),1)="","",DATE(2028,7,1)<DATE(YEAR('Model inputs'!AI115),MONTH('Model inputs'!AI115),1)))),0,IFERROR(DATEDIF(DATE(YEAR('Model inputs'!AI115),MONTH('Model inputs'!AI115),1),DATE(2028,7,1),"M"),0)+1) -> 21 | AG63: =IF(IF(IF(ISERROR(DATE(2028,8,1)<DATE(YEAR('Model inputs'!AI115),MONTH('Model inputs'!AI115),1)),DATE(2028,8,1)<DATE(YEAR('Model inputs'!AI115),MONTH('Model inputs'!AI115),1),IF(DATE(YEAR('Model inputs'!AI115),MONTH('Model inputs'!AI115),1)="","",DATE(2028,8,1)<DATE(YEAR('Model inputs'!AI115),MONTH('Model inputs'!AI115),1)))="",FALSE,IF(ISERROR(DATE(2028,8,1)<DATE(YEAR('Model inputs'!AI115),MONTH('Model inputs'!AI115),1)),DATE(2028,8,1)<DATE(YEAR('Model inputs'!AI115),MONTH('Model inputs'!AI115),1),IF(DATE(YEAR('Model inputs'!AI115),MONTH('Model inputs'!AI115),1)="","",DATE(2028,8,1)<DATE(YEAR('Model inputs'!AI115),MONTH('Model inputs'!AI115),1)))),0,IFERROR(DATEDIF(DATE(YEAR('Model inputs'!AI115),MONTH('Model inputs'!AI115),1),DATE(2028,8,1),"M"),0)+1) -> 22 | AH63: =IF(IF(IF(ISERROR(DATE(2028,9,1)<DATE(YEAR('Model inputs'!AI115),MONTH('Model inputs'!AI115),1)),DATE(2028,9,1)<DATE(YEAR('Model inputs'!AI115),MONTH('Model inputs'!AI115),1),IF(DATE(YEAR('Model inputs'!AI115),MONTH('Model inputs'!AI115),1)="","",DATE(2028,9,1)<DATE(YEAR('Model inputs'!AI115),MONTH('Model inputs'!AI115),1)))="",FALSE,IF(ISERROR(DATE(2028,9,1)<DATE(YEAR('Model inputs'!AI115),MONTH('Model inputs'!AI115),1)),DATE(2028,9,1)<DATE(YEAR('Model inputs'!AI115),MONTH('Model inputs'!AI115),1),IF(DATE(YEAR('Model inputs'!AI115),MONTH('Model inputs'!AI115),1)="","",DATE(2028,9,1)<DATE(YEAR('Model inputs'!AI115),MONTH('Model inputs'!AI115),1)))),0,IFERROR(DATEDIF(DATE(YEAR('Model inputs'!AI115),MONTH('Model inputs'!AI115),1),DATE(2028,9,1),"M"),0)+1) -> 23
A64: Months since launch · Base · $0.60 | B64: 0 | C64: 0 | D64: 0 | E64: 0 | F64: 0 | G64: 0 | H64: 0 | I64: 0 | J64: 0 | K64: =IF(IF(IF(ISERROR(DATE(2026,10,1)<DATE(YEAR('Model inputs'!AI116),MONTH('Model inputs'!AI116),1)),DATE(2026,10,1)<DATE(YEAR('Model inputs'!AI116),MONTH('Model inputs'!AI116),1),IF(DATE(YEAR('Model inputs'!AI116),MONTH('Model inputs'!AI116),1)="","",DATE(2026,10,1)<DATE(YEAR('Model inputs'!AI116),MONTH('Model inputs'!AI116),1)))="",FALSE,IF(ISERROR(DATE(2026,10,1)<DATE(YEAR('Model inputs'!AI116),MONTH('Model inputs'!AI116),1)),DATE(2026,10,1)<DATE(YEAR('Model inputs'!AI116),MONTH('Model inputs'!AI116),1),IF(DATE(YEAR('Model inputs'!AI116),MONTH('Model inputs'!AI116),1)="","",DATE(2026,10,1)<DATE(YEAR('Model inputs'!AI116),MONTH('Model inputs'!AI116),1)))),0,IFERROR(DATEDIF(DATE(YEAR('Model inputs'!AI116),MONTH('Model inputs'!AI116),1),DATE(2026,10,1),"M"),0)+1) -> 0 | L64: =IF(IF(IF(ISERROR(DATE(2026,11,1)<DATE(YEAR('Model inputs'!AI116),MONTH('Model inputs'!AI116),1)),DATE(2026,11,1)<DATE(YEAR('Model inputs'!AI116),MONTH('Model inputs'!AI116),1),IF(DATE(YEAR('Model inputs'!AI116),MONTH('Model inputs'!AI116),1)="","",DATE(2026,11,1)<DATE(YEAR('Model inputs'!AI116),MONTH('Model inputs'!AI116),1)))="",FALSE,IF(ISERROR(DATE(2026,11,1)<DATE(YEAR('Model inputs'!AI116),MONTH('Model inputs'!AI116),1)),DATE(2026,11,1)<DATE(YEAR('Model inputs'!AI116),MONTH('Model inputs'!AI116),1),IF(DATE(YEAR('Model inputs'!AI116),MONTH('Model inputs'!AI116),1)="","",DATE(2026,11,1)<DATE(YEAR('Model inputs'!AI116),MONTH('Model inputs'!AI116),1)))),0,IFERROR(DATEDIF(DATE(YEAR('Model inputs'!AI116),MONTH('Model inputs'!AI116),1),DATE(2026,11,1),"M"),0)+1) -> 1 | M64: =IF(IF(IF(ISERROR(DATE(2026,12,1)<DATE(YEAR('Model inputs'!AI116),MONTH('Model inputs'!AI116),1)),DATE(2026,12,1)<DATE(YEAR('Model inputs'!AI116),MONTH('Model inputs'!AI116),1),IF(DATE(YEAR('Model inputs'!AI116),MONTH('Model inputs'!AI116),1)="","",DATE(2026,12,1)<DATE(YEAR('Model inputs'!AI116),MONTH('Model inputs'!AI116),1)))="",FALSE,IF(ISERROR(DATE(2026,12,1)<DATE(YEAR('Model inputs'!AI116),MONTH('Model inputs'!AI116),1)),DATE(2026,12,1)<DATE(YEAR('Model inputs'!AI116),MONTH('Model inputs'!AI116),1),IF(DATE(YEAR('Model inputs'!AI116),MONTH('Model inputs'!AI116),1)="","",DATE(2026,12,1)<DATE(YEAR('Model inputs'!AI116),MONTH('Model inputs'!AI116),1)))),0,IFERROR(DATEDIF(DATE(YEAR('Model inputs'!AI116),MONTH('Model inputs'!AI116),1),DATE(2026,12,1),"M"),0)+1) -> 2 | N64: =IF(IF(IF(ISERROR(DATE(2027,1,1)<DATE(YEAR('Model inputs'!AI116),MONTH('Model inputs'!AI116),1)),DATE(2027,1,1)<DATE(YEAR('Model inputs'!AI116),MONTH('Model inputs'!AI116),1),IF(DATE(YEAR('Model inputs'!AI116),MONTH('Model inputs'!AI116),1)="","",DATE(2027,1,1)<DATE(YEAR('Model inputs'!AI116),MONTH('Model inputs'!AI116),1)))="",FALSE,IF(ISERROR(DATE(2027,1,1)<DATE(YEAR('Model inputs'!AI116),MONTH('Model inputs'!AI116),1)),DATE(2027,1,1)<DATE(YEAR('Model inputs'!AI116),MONTH('Model inputs'!AI116),1),IF(DATE(YEAR('Model inputs'!AI116),MONTH('Model inputs'!AI116),1)="","",DATE(2027,1,1)<DATE(YEAR('Model inputs'!AI116),MONTH('Model inputs'!AI116),1)))),0,IFERROR(DATEDIF(DATE(YEAR('Model inputs'!AI116),MONTH('Model inputs'!AI116),1),DATE(2027,1,1),"M"),0)+1) -> 3 | O64: =IF(IF(IF(ISERROR(DATE(2027,2,1)<DATE(YEAR('Model inputs'!AI116),MONTH('Model inputs'!AI116),1)),DATE(2027,2,1)<DATE(YEAR('Model inputs'!AI116),MONTH('Model inputs'!AI116),1),IF(DATE(YEAR('Model inputs'!AI116),MONTH('Model inputs'!AI116),1)="","",DATE(2027,2,1)<DATE(YEAR('Model inputs'!AI116),MONTH('Model inputs'!AI116),1)))="",FALSE,IF(ISERROR(DATE(2027,2,1)<DATE(YEAR('Model inputs'!AI116),MONTH('Model inputs'!AI116),1)),DATE(2027,2,1)<DATE(YEAR('Model inputs'!AI116),MONTH('Model inputs'!AI116),1),IF(DATE(YEAR('Model inputs'!AI116),MONTH('Model inputs'!AI116),1)="","",DATE(2027,2,1)<DATE(YEAR('Model inputs'!AI116),MONTH('Model inputs'!AI116),1)))),0,IFERROR(DATEDIF(DATE(YEAR('Model inputs'!AI116),MONTH('Model inputs'!AI116),1),DATE(2027,2,1),"M"),0)+1) -> 4 | P64: =IF(IF(IF(ISERROR(DATE(2027,3,1)<DATE(YEAR('Model inputs'!AI116),MONTH('Model inputs'!AI116),1)),DATE(2027,3,1)<DATE(YEAR('Model inputs'!AI116),MONTH('Model inputs'!AI116),1),IF(DATE(YEAR('Model inputs'!AI116),MONTH('Model inputs'!AI116),1)="","",DATE(2027,3,1)<DATE(YEAR('Model inputs'!AI116),MONTH('Model inputs'!AI116),1)))="",FALSE,IF(ISERROR(DATE(2027,3,1)<DATE(YEAR('Model inputs'!AI116),MONTH('Model inputs'!AI116),1)),DATE(2027,3,1)<DATE(YEAR('Model inputs'!AI116),MONTH('Model inputs'!AI116),1),IF(DATE(YEAR('Model inputs'!AI116),MONTH('Model inputs'!AI116),1)="","",DATE(2027,3,1)<DATE(YEAR('Model inputs'!AI116),MONTH('Model inputs'!AI116),1)))),0,IFERROR(DATEDIF(DATE(YEAR('Model inputs'!AI116),MONTH('Model inputs'!AI116),1),DATE(2027,3,1),"M"),0)+1) -> 5 | Q64: =IF(IF(IF(ISERROR(DATE(2027,4,1)<DATE(YEAR('Model inputs'!AI116),MONTH('Model inputs'!AI116),1)),DATE(2027,4,1)<DATE(YEAR('Model inputs'!AI116),MONTH('Model inputs'!AI116),1),IF(DATE(YEAR('Model inputs'!AI116),MONTH('Model inputs'!AI116),1)="","",DATE(2027,4,1)<DATE(YEAR('Model inputs'!AI116),MONTH('Model inputs'!AI116),1)))="",FALSE,IF(ISERROR(DATE(2027,4,1)<DATE(YEAR('Model inputs'!AI116),MONTH('Model inputs'!AI116),1)),DATE(2027,4,1)<DATE(YEAR('Model inputs'!AI116),MONTH('Model inputs'!AI116),1),IF(DATE(YEAR('Model inputs'!AI116),MONTH('Model inputs'!AI116),1)="","",DATE(2027,4,1)<DATE(YEAR('Model inputs'!AI116),MONTH('Model inputs'!AI116),1)))),0,IFERROR(DATEDIF(DATE(YEAR('Model inputs'!AI116),MONTH('Model inputs'!AI116),1),DATE(2027,4,1),"M"),0)+1) -> 6 | R64: =IF(IF(IF(ISERROR(DATE(2027,5,1)<DATE(YEAR('Model inputs'!AI116),MONTH('Model inputs'!AI116),1)),DATE(2027,5,1)<DATE(YEAR('Model inputs'!AI116),MONTH('Model inputs'!AI116),1),IF(DATE(YEAR('Model inputs'!AI116),MONTH('Model inputs'!AI116),1)="","",DATE(2027,5,1)<DATE(YEAR('Model inputs'!AI116),MONTH('Model inputs'!AI116),1)))="",FALSE,IF(ISERROR(DATE(2027,5,1)<DATE(YEAR('Model inputs'!AI116),MONTH('Model inputs'!AI116),1)),DATE(2027,5,1)<DATE(YEAR('Model inputs'!AI116),MONTH('Model inputs'!AI116),1),IF(DATE(YEAR('Model inputs'!AI116),MONTH('Model inputs'!AI116),1)="","",DATE(2027,5,1)<DATE(YEAR('Model inputs'!AI116),MONTH('Model inputs'!AI116),1)))),0,IFERROR(DATEDIF(DATE(YEAR('Model inputs'!AI116),MONTH('Model inputs'!AI116),1),DATE(2027,5,1),"M"),0)+1) -> 7 | S64: =IF(IF(IF(ISERROR(DATE(2027,6,1)<DATE(YEAR('Model inputs'!AI116),MONTH('Model inputs'!AI116),1)),DATE(2027,6,1)<DATE(YEAR('Model inputs'!AI116),MONTH('Model inputs'!AI116),1),IF(DATE(YEAR('Model inputs'!AI116),MONTH('Model inputs'!AI116),1)="","",DATE(2027,6,1)<DATE(YEAR('Model inputs'!AI116),MONTH('Model inputs'!AI116),1)))="",FALSE,IF(ISERROR(DATE(2027,6,1)<DATE(YEAR('Model inputs'!AI116),MONTH('Model inputs'!AI116),1)),DATE(2027,6,1)<DATE(YEAR('Model inputs'!AI116),MONTH('Model inputs'!AI116),1),IF(DATE(YEAR('Model inputs'!AI116),MONTH('Model inputs'!AI116),1)="","",DATE(2027,6,1)<DATE(YEAR('Model inputs'!AI116),MONTH('Model inputs'!AI116),1)))),0,IFERROR(DATEDIF(DATE(YEAR('Model inputs'!AI116),MONTH('Model inputs'!AI116),1),DATE(2027,6,1),"M"),0)+1) -> 8 | T64: =IF(IF(IF(ISERROR(DATE(2027,7,1)<DATE(YEAR('Model inputs'!AI116),MONTH('Model inputs'!AI116),1)),DATE(2027,7,1)<DATE(YEAR('Model inputs'!AI116),MONTH('Model inputs'!AI116),1),IF(DATE(YEAR('Model inputs'!AI116),MONTH('Model inputs'!AI116),1)="","",DATE(2027,7,1)<DATE(YEAR('Model inputs'!AI116),MONTH('Model inputs'!AI116),1)))="",FALSE,IF(ISERROR(DATE(2027,7,1)<DATE(YEAR('Model inputs'!AI116),MONTH('Model inputs'!AI116),1)),DATE(2027,7,1)<DATE(YEAR('Model inputs'!AI116),MONTH('Model inputs'!AI116),1),IF(DATE(YEAR('Model inputs'!AI116),MONTH('Model inputs'!AI116),1)="","",DATE(2027,7,1)<DATE(YEAR('Model inputs'!AI116),MONTH('Model inputs'!AI116),1)))),0,IFERROR(DATEDIF(DATE(YEAR('Model inputs'!AI116),MONTH('Model inputs'!AI116),1),DATE(2027,7,1),"M"),0)+1) -> 9 | U64: =IF(IF(IF(ISERROR(DATE(2027,8,1)<DATE(YEAR('Model inputs'!AI116),MONTH('Model inputs'!AI116),1)),DATE(2027,8,1)<DATE(YEAR('Model inputs'!AI116),MONTH('Model inputs'!AI116),1),IF(DATE(YEAR('Model inputs'!AI116),MONTH('Model inputs'!AI116),1)="","",DATE(2027,8,1)<DATE(YEAR('Model inputs'!AI116),MONTH('Model inputs'!AI116),1)))="",FALSE,IF(ISERROR(DATE(2027,8,1)<DATE(YEAR('Model inputs'!AI116),MONTH('Model inputs'!AI116),1)),DATE(2027,8,1)<DATE(YEAR('Model inputs'!AI116),MONTH('Model inputs'!AI116),1),IF(DATE(YEAR('Model inputs'!AI116),MONTH('Model inputs'!AI116),1)="","",DATE(2027,8,1)<DATE(YEAR('Model inputs'!AI116),MONTH('Model inputs'!AI116),1)))),0,IFERROR(DATEDIF(DATE(YEAR('Model inputs'!AI116),MONTH('Model inputs'!AI116),1),DATE(2027,8,1),"M"),0)+1) -> 10 | V64: =IF(IF(IF(ISERROR(DATE(2027,9,1)<DATE(YEAR('Model inputs'!AI116),MONTH('Model inputs'!AI116),1)),DATE(2027,9,1)<DATE(YEAR('Model inputs'!AI116),MONTH('Model inputs'!AI116),1),IF(DATE(YEAR('Model inputs'!AI116),MONTH('Model inputs'!AI116),1)="","",DATE(2027,9,1)<DATE(YEAR('Model inputs'!AI116),MONTH('Model inputs'!AI116),1)))="",FALSE,IF(ISERROR(DATE(2027,9,1)<DATE(YEAR('Model inputs'!AI116),MONTH('Model inputs'!AI116),1)),DATE(2027,9,1)<DATE(YEAR('Model inputs'!AI116),MONTH('Model inputs'!AI116),1),IF(DATE(YEAR('Model inputs'!AI116),MONTH('Model inputs'!AI116),1)="","",DATE(2027,9,1)<DATE(YEAR('Model inputs'!AI116),MONTH('Model inputs'!AI116),1)))),0,IFERROR(DATEDIF(DATE(YEAR('Model inputs'!AI116),MONTH('Model inputs'!AI116),1),DATE(2027,9,1),"M"),0)+1) -> 11 | W64: =IF(IF(IF(ISERROR(DATE(2027,10,1)<DATE(YEAR('Model inputs'!AI116),MONTH('Model inputs'!AI116),1)),DATE(2027,10,1)<DATE(YEAR('Model inputs'!AI116),MONTH('Model inputs'!AI116),1),IF(DATE(YEAR('Model inputs'!AI116),MONTH('Model inputs'!AI116),1)="","",DATE(2027,10,1)<DATE(YEAR('Model inputs'!AI116),MONTH('Model inputs'!AI116),1)))="",FALSE,IF(ISERROR(DATE(2027,10,1)<DATE(YEAR('Model inputs'!AI116),MONTH('Model inputs'!AI116),1)),DATE(2027,10,1)<DATE(YEAR('Model inputs'!AI116),MONTH('Model inputs'!AI116),1),IF(DATE(YEAR('Model inputs'!AI116),MONTH('Model inputs'!AI116),1)="","",DATE(2027,10,1)<DATE(YEAR('Model inputs'!AI116),MONTH('Model inputs'!AI116),1)))),0,IFERROR(DATEDIF(DATE(YEAR('Model inputs'!AI116),MONTH('Model inputs'!AI116),1),DATE(2027,10,1),"M"),0)+1) -> 12 | X64: =IF(IF(IF(ISERROR(DATE(2027,11,1)<DATE(YEAR('Model inputs'!AI116),MONTH('Model inputs'!AI116),1)),DATE(2027,11,1)<DATE(YEAR('Model inputs'!AI116),MONTH('Model inputs'!AI116),1),IF(DATE(YEAR('Model inputs'!AI116),MONTH('Model inputs'!AI116),1)="","",DATE(2027,11,1)<DATE(YEAR('Model inputs'!AI116),MONTH('Model inputs'!AI116),1)))="",FALSE,IF(ISERROR(DATE(2027,11,1)<DATE(YEAR('Model inputs'!AI116),MONTH('Model inputs'!AI116),1)),DATE(2027,11,1)<DATE(YEAR('Model inputs'!AI116),MONTH('Model inputs'!AI116),1),IF(DATE(YEAR('Model inputs'!AI116),MONTH('Model inputs'!AI116),1)="","",DATE(2027,11,1)<DATE(YEAR('Model inputs'!AI116),MONTH('Model inputs'!AI116),1)))),0,IFERROR(DATEDIF(DATE(YEAR('Model inputs'!AI116),MONTH('Model inputs'!AI116),1),DATE(2027,11,1),"M"),0)+1) -> 13 | Y64: =IF(IF(IF(ISERROR(DATE(2027,12,1)<DATE(YEAR('Model inputs'!AI116),MONTH('Model inputs'!AI116),1)),DATE(2027,12,1)<DATE(YEAR('Model inputs'!AI116),MONTH('Model inputs'!AI116),1),IF(DATE(YEAR('Model inputs'!AI116),MONTH('Model inputs'!AI116),1)="","",DATE(2027,12,1)<DATE(YEAR('Model inputs'!AI116),MONTH('Model inputs'!AI116),1)))="",FALSE,IF(ISERROR(DATE(2027,12,1)<DATE(YEAR('Model inputs'!AI116),MONTH('Model inputs'!AI116),1)),DATE(2027,12,1)<DATE(YEAR('Model inputs'!AI116),MONTH('Model inputs'!AI116),1),IF(DATE(YEAR('Model inputs'!AI116),MONTH('Model inputs'!AI116),1)="","",DATE(2027,12,1)<DATE(YEAR('Model inputs'!AI116),MONTH('Model inputs'!AI116),1)))),0,IFERROR(DATEDIF(DATE(YEAR('Model inputs'!AI116),MONTH('Model inputs'!AI116),1),DATE(2027,12,1),"M"),0)+1) -> 14 | Z64: =IF(IF(IF(ISERROR(DATE(2028,1,1)<DATE(YEAR('Model inputs'!AI116),MONTH('Model inputs'!AI116),1)),DATE(2028,1,1)<DATE(YEAR('Model inputs'!AI116),MONTH('Model inputs'!AI116),1),IF(DATE(YEAR('Model inputs'!AI116),MONTH('Model inputs'!AI116),1)="","",DATE(2028,1,1)<DATE(YEAR('Model inputs'!AI116),MONTH('Model inputs'!AI116),1)))="",FALSE,IF(ISERROR(DATE(2028,1,1)<DATE(YEAR('Model inputs'!AI116),MONTH('Model inputs'!AI116),1)),DATE(2028,1,1)<DATE(YEAR('Model inputs'!AI116),MONTH('Model inputs'!AI116),1),IF(DATE(YEAR('Model inputs'!AI116),MONTH('Model inputs'!AI116),1)="","",DATE(2028,1,1)<DATE(YEAR('Model inputs'!AI116),MONTH('Model inputs'!AI116),1)))),0,IFERROR(DATEDIF(DATE(YEAR('Model inputs'!AI116),MONTH('Model inputs'!AI116),1),DATE(2028,1,1),"M"),0)+1) -> 15 | AA64: =IF(IF(IF(ISERROR(DATE(2028,2,1)<DATE(YEAR('Model inputs'!AI116),MONTH('Model inputs'!AI116),1)),DATE(2028,2,1)<DATE(YEAR('Model inputs'!AI116),MONTH('Model inputs'!AI116),1),IF(DATE(YEAR('Model inputs'!AI116),MONTH('Model inputs'!AI116),1)="","",DATE(2028,2,1)<DATE(YEAR('Model inputs'!AI116),MONTH('Model inputs'!AI116),1)))="",FALSE,IF(ISERROR(DATE(2028,2,1)<DATE(YEAR('Model inputs'!AI116),MONTH('Model inputs'!AI116),1)),DATE(2028,2,1)<DATE(YEAR('Model inputs'!AI116),MONTH('Model inputs'!AI116),1),IF(DATE(YEAR('Model inputs'!AI116),MONTH('Model inputs'!AI116),1)="","",DATE(2028,2,1)<DATE(YEAR('Model inputs'!AI116),MONTH('Model inputs'!AI116),1)))),0,IFERROR(DATEDIF(DATE(YEAR('Model inputs'!AI116),MONTH('Model inputs'!AI116),1),DATE(2028,2,1),"M"),0)+1) -> 16 | AB64: =IF(IF(IF(ISERROR(DATE(2028,3,1)<DATE(YEAR('Model inputs'!AI116),MONTH('Model inputs'!AI116),1)),DATE(2028,3,1)<DATE(YEAR('Model inputs'!AI116),MONTH('Model inputs'!AI116),1),IF(DATE(YEAR('Model inputs'!AI116),MONTH('Model inputs'!AI116),1)="","",DATE(2028,3,1)<DATE(YEAR('Model inputs'!AI116),MONTH('Model inputs'!AI116),1)))="",FALSE,IF(ISERROR(DATE(2028,3,1)<DATE(YEAR('Model inputs'!AI116),MONTH('Model inputs'!AI116),1)),DATE(2028,3,1)<DATE(YEAR('Model inputs'!AI116),MONTH('Model inputs'!AI116),1),IF(DATE(YEAR('Model inputs'!AI116),MONTH('Model inputs'!AI116),1)="","",DATE(2028,3,1)<DATE(YEAR('Model inputs'!AI116),MONTH('Model inputs'!AI116),1)))),0,IFERROR(DATEDIF(DATE(YEAR('Model inputs'!AI116),MONTH('Model inputs'!AI116),1),DATE(2028,3,1),"M"),0)+1) -> 17 | AC64: =IF(IF(IF(ISERROR(DATE(2028,4,1)<DATE(YEAR('Model inputs'!AI116),MONTH('Model inputs'!AI116),1)),DATE(2028,4,1)<DATE(YEAR('Model inputs'!AI116),MONTH('Model inputs'!AI116),1),IF(DATE(YEAR('Model inputs'!AI116),MONTH('Model inputs'!AI116),1)="","",DATE(2028,4,1)<DATE(YEAR('Model inputs'!AI116),MONTH('Model inputs'!AI116),1)))="",FALSE,IF(ISERROR(DATE(2028,4,1)<DATE(YEAR('Model inputs'!AI116),MONTH('Model inputs'!AI116),1)),DATE(2028,4,1)<DATE(YEAR('Model inputs'!AI116),MONTH('Model inputs'!AI116),1),IF(DATE(YEAR('Model inputs'!AI116),MONTH('Model inputs'!AI116),1)="","",DATE(2028,4,1)<DATE(YEAR('Model inputs'!AI116),MONTH('Model inputs'!AI116),1)))),0,IFERROR(DATEDIF(DATE(YEAR('Model inputs'!AI116),MONTH('Model inputs'!AI116),1),DATE(2028,4,1),"M"),0)+1) -> 18 | AD64: =IF(IF(IF(ISERROR(DATE(2028,5,1)<DATE(YEAR('Model inputs'!AI116),MONTH('Model inputs'!AI116),1)),DATE(2028,5,1)<DATE(YEAR('Model inputs'!AI116),MONTH('Model inputs'!AI116),1),IF(DATE(YEAR('Model inputs'!AI116),MONTH('Model inputs'!AI116),1)="","",DATE(2028,5,1)<DATE(YEAR('Model inputs'!AI116),MONTH('Model inputs'!AI116),1)))="",FALSE,IF(ISERROR(DATE(2028,5,1)<DATE(YEAR('Model inputs'!AI116),MONTH('Model inputs'!AI116),1)),DATE(2028,5,1)<DATE(YEAR('Model inputs'!AI116),MONTH('Model inputs'!AI116),1),IF(DATE(YEAR('Model inputs'!AI116),MONTH('Model inputs'!AI116),1)="","",DATE(2028,5,1)<DATE(YEAR('Model inputs'!AI116),MONTH('Model inputs'!AI116),1)))),0,IFERROR(DATEDIF(DATE(YEAR('Model inputs'!AI116),MONTH('Model inputs'!AI116),1),DATE(2028,5,1),"M"),0)+1) -> 19 | AE64: =IF(IF(IF(ISERROR(DATE(2028,6,1)<DATE(YEAR('Model inputs'!AI116),MONTH('Model inputs'!AI116),1)),DATE(2028,6,1)<DATE(YEAR('Model inputs'!AI116),MONTH('Model inputs'!AI116),1),IF(DATE(YEAR('Model inputs'!AI116),MONTH('Model inputs'!AI116),1)="","",DATE(2028,6,1)<DATE(YEAR('Model inputs'!AI116),MONTH('Model inputs'!AI116),1)))="",FALSE,IF(ISERROR(DATE(2028,6,1)<DATE(YEAR('Model inputs'!AI116),MONTH('Model inputs'!AI116),1)),DATE(2028,6,1)<DATE(YEAR('Model inputs'!AI116),MONTH('Model inputs'!AI116),1),IF(DATE(YEAR('Model inputs'!AI116),MONTH('Model inputs'!AI116),1)="","",DATE(2028,6,1)<DATE(YEAR('Model inputs'!AI116),MONTH('Model inputs'!AI116),1)))),0,IFERROR(DATEDIF(DATE(YEAR('Model inputs'!AI116),MONTH('Model inputs'!AI116),1),DATE(2028,6,1),"M"),0)+1) -> 20 | AF64: =IF(IF(IF(ISERROR(DATE(2028,7,1)<DATE(YEAR('Model inputs'!AI116),MONTH('Model inputs'!AI116),1)),DATE(2028,7,1)<DATE(YEAR('Model inputs'!AI116),MONTH('Model inputs'!AI116),1),IF(DATE(YEAR('Model inputs'!AI116),MONTH('Model inputs'!AI116),1)="","",DATE(2028,7,1)<DATE(YEAR('Model inputs'!AI116),MONTH('Model inputs'!AI116),1)))="",FALSE,IF(ISERROR(DATE(2028,7,1)<DATE(YEAR('Model inputs'!AI116),MONTH('Model inputs'!AI116),1)),DATE(2028,7,1)<DATE(YEAR('Model inputs'!AI116),MONTH('Model inputs'!AI116),1),IF(DATE(YEAR('Model inputs'!AI116),MONTH('Model inputs'!AI116),1)="","",DATE(2028,7,1)<DATE(YEAR('Model inputs'!AI116),MONTH('Model inputs'!AI116),1)))),0,IFERROR(DATEDIF(DATE(YEAR('Model inputs'!AI116),MONTH('Model inputs'!AI116),1),DATE(2028,7,1),"M"),0)+1) -> 21 | AG64: =IF(IF(IF(ISERROR(DATE(2028,8,1)<DATE(YEAR('Model inputs'!AI116),MONTH('Model inputs'!AI116),1)),DATE(2028,8,1)<DATE(YEAR('Model inputs'!AI116),MONTH('Model inputs'!AI116),1),IF(DATE(YEAR('Model inputs'!AI116),MONTH('Model inputs'!AI116),1)="","",DATE(2028,8,1)<DATE(YEAR('Model inputs'!AI116),MONTH('Model inputs'!AI116),1)))="",FALSE,IF(ISERROR(DATE(2028,8,1)<DATE(YEAR('Model inputs'!AI116),MONTH('Model inputs'!AI116),1)),DATE(2028,8,1)<DATE(YEAR('Model inputs'!AI116),MONTH('Model inputs'!AI116),1),IF(DATE(YEAR('Model inputs'!AI116),MONTH('Model inputs'!AI116),1)="","",DATE(2028,8,1)<DATE(YEAR('Model inputs'!AI116),MONTH('Model inputs'!AI116),1)))),0,IFERROR(DATEDIF(DATE(YEAR('Model inputs'!AI116),MONTH('Model inputs'!AI116),1),DATE(2028,8,1),"M"),0)+1) -> 22 | AH64: =IF(IF(IF(ISERROR(DATE(2028,9,1)<DATE(YEAR('Model inputs'!AI116),MONTH('Model inputs'!AI116),1)),DATE(2028,9,1)<DATE(YEAR('Model inputs'!AI116),MONTH('Model inputs'!AI116),1),IF(DATE(YEAR('Model inputs'!AI116),MONTH('Model inputs'!AI116),1)="","",DATE(2028,9,1)<DATE(YEAR('Model inputs'!AI116),MONTH('Model inputs'!AI116),1)))="",FALSE,IF(ISERROR(DATE(2028,9,1)<DATE(YEAR('Model inputs'!AI116),MONTH('Model inputs'!AI116),1)),DATE(2028,9,1)<DATE(YEAR('Model inputs'!AI116),MONTH('Model inputs'!AI116),1),IF(DATE(YEAR('Model inputs'!AI116),MONTH('Model inputs'!AI116),1)="","",DATE(2028,9,1)<DATE(YEAR('Model inputs'!AI116),MONTH('Model inputs'!AI116),1)))),0,IFERROR(DATEDIF(DATE(YEAR('Model inputs'!AI116),MONTH('Model inputs'!AI116),1),DATE(2028,9,1),"M"),0)+1) -> 23
A65: Months since launch · Growth · $0.34 | B65: 0 | C65: 0 | D65: 0 | E65: 0 | F65: 0 | G65: 0 | H65: 0 | I65: 0 | J65: 0 | K65: =IF(IF(IF(ISERROR(DATE(2026,10,1)<DATE(YEAR('Model inputs'!AI117),MONTH('Model inputs'!AI117),1)),DATE(2026,10,1)<DATE(YEAR('Model inputs'!AI117),MONTH('Model inputs'!AI117),1),IF(DATE(YEAR('Model inputs'!AI117),MONTH('Model inputs'!AI117),1)="","",DATE(2026,10,1)<DATE(YEAR('Model inputs'!AI117),MONTH('Model inputs'!AI117),1)))="",FALSE,IF(ISERROR(DATE(2026,10,1)<DATE(YEAR('Model inputs'!AI117),MONTH('Model inputs'!AI117),1)),DATE(2026,10,1)<DATE(YEAR('Model inputs'!AI117),MONTH('Model inputs'!AI117),1),IF(DATE(YEAR('Model inputs'!AI117),MONTH('Model inputs'!AI117),1)="","",DATE(2026,10,1)<DATE(YEAR('Model inputs'!AI117),MONTH('Model inputs'!AI117),1)))),0,IFERROR(DATEDIF(DATE(YEAR('Model inputs'!AI117),MONTH('Model inputs'!AI117),1),DATE(2026,10,1),"M"),0)+1) -> 0 | L65: =IF(IF(IF(ISERROR(DATE(2026,11,1)<DATE(YEAR('Model inputs'!AI117),MONTH('Model inputs'!AI117),1)),DATE(2026,11,1)<DATE(YEAR('Model inputs'!AI117),MONTH('Model inputs'!AI117),1),IF(DATE(YEAR('Model inputs'!AI117),MONTH('Model inputs'!AI117),1)="","",DATE(2026,11,1)<DATE(YEAR('Model inputs'!AI117),MONTH('Model inputs'!AI117),1)))="",FALSE,IF(ISERROR(DATE(2026,11,1)<DATE(YEAR('Model inputs'!AI117),MONTH('Model inputs'!AI117),1)),DATE(2026,11,1)<DATE(YEAR('Model inputs'!AI117),MONTH('Model inputs'!AI117),1),IF(DATE(YEAR('Model inputs'!AI117),MONTH('Model inputs'!AI117),1)="","",DATE(2026,11,1)<DATE(YEAR('Model inputs'!AI117),MONTH('Model inputs'!AI117),1)))),0,IFERROR(DATEDIF(DATE(YEAR('Model inputs'!AI117),MONTH('Model inputs'!AI117),1),DATE(2026,11,1),"M"),0)+1) -> 1 | M65: =IF(IF(IF(ISERROR(DATE(2026,12,1)<DATE(YEAR('Model inputs'!AI117),MONTH('Model inputs'!AI117),1)),DATE(2026,12,1)<DATE(YEAR('Model inputs'!AI117),MONTH('Model inputs'!AI117),1),IF(DATE(YEAR('Model inputs'!AI117),MONTH('Model inputs'!AI117),1)="","",DATE(2026,12,1)<DATE(YEAR('Model inputs'!AI117),MONTH('Model inputs'!AI117),1)))="",FALSE,IF(ISERROR(DATE(2026,12,1)<DATE(YEAR('Model inputs'!AI117),MONTH('Model inputs'!AI117),1)),DATE(2026,12,1)<DATE(YEAR('Model inputs'!AI117),MONTH('Model inputs'!AI117),1),IF(DATE(YEAR('Model inputs'!AI117),MONTH('Model inputs'!AI117),1)="","",DATE(2026,12,1)<DATE(YEAR('Model inputs'!AI117),MONTH('Model inputs'!AI117),1)))),0,IFERROR(DATEDIF(DATE(YEAR('Model inputs'!AI117),MONTH('Model inputs'!AI117),1),DATE(2026,12,1),"M"),0)+1) -> 2 | N65: =IF(IF(IF(ISERROR(DATE(2027,1,1)<DATE(YEAR('Model inputs'!AI117),MONTH('Model inputs'!AI117),1)),DATE(2027,1,1)<DATE(YEAR('Model inputs'!AI117),MONTH('Model inputs'!AI117),1),IF(DATE(YEAR('Model inputs'!AI117),MONTH('Model inputs'!AI117),1)="","",DATE(2027,1,1)<DATE(YEAR('Model inputs'!AI117),MONTH('Model inputs'!AI117),1)))="",FALSE,IF(ISERROR(DATE(2027,1,1)<DATE(YEAR('Model inputs'!AI117),MONTH('Model inputs'!AI117),1)),DATE(2027,1,1)<DATE(YEAR('Model inputs'!AI117),MONTH('Model inputs'!AI117),1),IF(DATE(YEAR('Model inputs'!AI117),MONTH('Model inputs'!AI117),1)="","",DATE(2027,1,1)<DATE(YEAR('Model inputs'!AI117),MONTH('Model inputs'!AI117),1)))),0,IFERROR(DATEDIF(DATE(YEAR('Model inputs'!AI117),MONTH('Model inputs'!AI117),1),DATE(2027,1,1),"M"),0)+1) -> 3 | O65: =IF(IF(IF(ISERROR(DATE(2027,2,1)<DATE(YEAR('Model inputs'!AI117),MONTH('Model inputs'!AI117),1)),DATE(2027,2,1)<DATE(YEAR('Model inputs'!AI117),MONTH('Model inputs'!AI117),1),IF(DATE(YEAR('Model inputs'!AI117),MONTH('Model inputs'!AI117),1)="","",DATE(2027,2,1)<DATE(YEAR('Model inputs'!AI117),MONTH('Model inputs'!AI117),1)))="",FALSE,IF(ISERROR(DATE(2027,2,1)<DATE(YEAR('Model inputs'!AI117),MONTH('Model inputs'!AI117),1)),DATE(2027,2,1)<DATE(YEAR('Model inputs'!AI117),MONTH('Model inputs'!AI117),1),IF(DATE(YEAR('Model inputs'!AI117),MONTH('Model inputs'!AI117),1)="","",DATE(2027,2,1)<DATE(YEAR('Model inputs'!AI117),MONTH('Model inputs'!AI117),1)))),0,IFERROR(DATEDIF(DATE(YEAR('Model inputs'!AI117),MONTH('Model inputs'!AI117),1),DATE(2027,2,1),"M"),0)+1) -> 4 | P65: =IF(IF(IF(ISERROR(DATE(2027,3,1)<DATE(YEAR('Model inputs'!AI117),MONTH('Model inputs'!AI117),1)),DATE(2027,3,1)<DATE(YEAR('Model inputs'!AI117),MONTH('Model inputs'!AI117),1),IF(DATE(YEAR('Model inputs'!AI117),MONTH('Model inputs'!AI117),1)="","",DATE(2027,3,1)<DATE(YEAR('Model inputs'!AI117),MONTH('Model inputs'!AI117),1)))="",FALSE,IF(ISERROR(DATE(2027,3,1)<DATE(YEAR('Model inputs'!AI117),MONTH('Model inputs'!AI117),1)),DATE(2027,3,1)<DATE(YEAR('Model inputs'!AI117),MONTH('Model inputs'!AI117),1),IF(DATE(YEAR('Model inputs'!AI117),MONTH('Model inputs'!AI117),1)="","",DATE(2027,3,1)<DATE(YEAR('Model inputs'!AI117),MONTH('Model inputs'!AI117),1)))),0,IFERROR(DATEDIF(DATE(YEAR('Model inputs'!AI117),MONTH('Model inputs'!AI117),1),DATE(2027,3,1),"M"),0)+1) -> 5 | Q65: =IF(IF(IF(ISERROR(DATE(2027,4,1)<DATE(YEAR('Model inputs'!AI117),MONTH('Model inputs'!AI117),1)),DATE(2027,4,1)<DATE(YEAR('Model inputs'!AI117),MONTH('Model inputs'!AI117),1),IF(DATE(YEAR('Model inputs'!AI117),MONTH('Model inputs'!AI117),1)="","",DATE(2027,4,1)<DATE(YEAR('Model inputs'!AI117),MONTH('Model inputs'!AI117),1)))="",FALSE,IF(ISERROR(DATE(2027,4,1)<DATE(YEAR('Model inputs'!AI117),MONTH('Model inputs'!AI117),1)),DATE(2027,4,1)<DATE(YEAR('Model inputs'!AI117),MONTH('Model inputs'!AI117),1),IF(DATE(YEAR('Model inputs'!AI117),MONTH('Model inputs'!AI117),1)="","",DATE(2027,4,1)<DATE(YEAR('Model inputs'!AI117),MONTH('Model inputs'!AI117),1)))),0,IFERROR(DATEDIF(DATE(YEAR('Model inputs'!AI117),MONTH('Model inputs'!AI117),1),DATE(2027,4,1),"M"),0)+1) -> 6 | R65: =IF(IF(IF(ISERROR(DATE(2027,5,1)<DATE(YEAR('Model inputs'!AI117),MONTH('Model inputs'!AI117),1)),DATE(2027,5,1)<DATE(YEAR('Model inputs'!AI117),MONTH('Model inputs'!AI117),1),IF(DATE(YEAR('Model inputs'!AI117),MONTH('Model inputs'!AI117),1)="","",DATE(2027,5,1)<DATE(YEAR('Model inputs'!AI117),MONTH('Model inputs'!AI117),1)))="",FALSE,IF(ISERROR(DATE(2027,5,1)<DATE(YEAR('Model inputs'!AI117),MONTH('Model inputs'!AI117),1)),DATE(2027,5,1)<DATE(YEAR('Model inputs'!AI117),MONTH('Model inputs'!AI117),1),IF(DATE(YEAR('Model inputs'!AI117),MONTH('Model inputs'!AI117),1)="","",DATE(2027,5,1)<DATE(YEAR('Model inputs'!AI117),MONTH('Model inputs'!AI117),1)))),0,IFERROR(DATEDIF(DATE(YEAR('Model inputs'!AI117),MONTH('Model inputs'!AI117),1),DATE(2027,5,1),"M"),0)+1) -> 7 | S65: =IF(IF(IF(ISERROR(DATE(2027,6,1)<DATE(YEAR('Model inputs'!AI117),MONTH('Model inputs'!AI117),1)),DATE(2027,6,1)<DATE(YEAR('Model inputs'!AI117),MONTH('Model inputs'!AI117),1),IF(DATE(YEAR('Model inputs'!AI117),MONTH('Model inputs'!AI117),1)="","",DATE(2027,6,1)<DATE(YEAR('Model inputs'!AI117),MONTH('Model inputs'!AI117),1)))="",FALSE,IF(ISERROR(DATE(2027,6,1)<DATE(YEAR('Model inputs'!AI117),MONTH('Model inputs'!AI117),1)),DATE(2027,6,1)<DATE(YEAR('Model inputs'!AI117),MONTH('Model inputs'!AI117),1),IF(DATE(YEAR('Model inputs'!AI117),MONTH('Model inputs'!AI117),1)="","",DATE(2027,6,1)<DATE(YEAR('Model inputs'!AI117),MONTH('Model inputs'!AI117),1)))),0,IFERROR(DATEDIF(DATE(YEAR('Model inputs'!AI117),MONTH('Model inputs'!AI117),1),DATE(2027,6,1),"M"),0)+1) -> 8 | T65: =IF(IF(IF(ISERROR(DATE(2027,7,1)<DATE(YEAR('Model inputs'!AI117),MONTH('Model inputs'!AI117),1)),DATE(2027,7,1)<DATE(YEAR('Model inputs'!AI117),MONTH('Model inputs'!AI117),1),IF(DATE(YEAR('Model inputs'!AI117),MONTH('Model inputs'!AI117),1)="","",DATE(2027,7,1)<DATE(YEAR('Model inputs'!AI117),MONTH('Model inputs'!AI117),1)))="",FALSE,IF(ISERROR(DATE(2027,7,1)<DATE(YEAR('Model inputs'!AI117),MONTH('Model inputs'!AI117),1)),DATE(2027,7,1)<DATE(YEAR('Model inputs'!AI117),MONTH('Model inputs'!AI117),1),IF(DATE(YEAR('Model inputs'!AI117),MONTH('Model inputs'!AI117),1)="","",DATE(2027,7,1)<DATE(YEAR('Model inputs'!AI117),MONTH('Model inputs'!AI117),1)))),0,IFERROR(DATEDIF(DATE(YEAR('Model inputs'!AI117),MONTH('Model inputs'!AI117),1),DATE(2027,7,1),"M"),0)+1) -> 9 | U65: =IF(IF(IF(ISERROR(DATE(2027,8,1)<DATE(YEAR('Model inputs'!AI117),MONTH('Model inputs'!AI117),1)),DATE(2027,8,1)<DATE(YEAR('Model inputs'!AI117),MONTH('Model inputs'!AI117),1),IF(DATE(YEAR('Model inputs'!AI117),MONTH('Model inputs'!AI117),1)="","",DATE(2027,8,1)<DATE(YEAR('Model inputs'!AI117),MONTH('Model inputs'!AI117),1)))="",FALSE,IF(ISERROR(DATE(2027,8,1)<DATE(YEAR('Model inputs'!AI117),MONTH('Model inputs'!AI117),1)),DATE(2027,8,1)<DATE(YEAR('Model inputs'!AI117),MONTH('Model inputs'!AI117),1),IF(DATE(YEAR('Model inputs'!AI117),MONTH('Model inputs'!AI117),1)="","",DATE(2027,8,1)<DATE(YEAR('Model inputs'!AI117),MONTH('Model inputs'!AI117),1)))),0,IFERROR(DATEDIF(DATE(YEAR('Model inputs'!AI117),MONTH('Model inputs'!AI117),1),DATE(2027,8,1),"M"),0)+1) -> 10 | V65: =IF(IF(IF(ISERROR(DATE(2027,9,1)<DATE(YEAR('Model inputs'!AI117),MONTH('Model inputs'!AI117),1)),DATE(2027,9,1)<DATE(YEAR('Model inputs'!AI117),MONTH('Model inputs'!AI117),1),IF(DATE(YEAR('Model inputs'!AI117),MONTH('Model inputs'!AI117),1)="","",DATE(2027,9,1)<DATE(YEAR('Model inputs'!AI117),MONTH('Model inputs'!AI117),1)))="",FALSE,IF(ISERROR(DATE(2027,9,1)<DATE(YEAR('Model inputs'!AI117),MONTH('Model inputs'!AI117),1)),DATE(2027,9,1)<DATE(YEAR('Model inputs'!AI117),MONTH('Model inputs'!AI117),1),IF(DATE(YEAR('Model inputs'!AI117),MONTH('Model inputs'!AI117),1)="","",DATE(2027,9,1)<DATE(YEAR('Model inputs'!AI117),MONTH('Model inputs'!AI117),1)))),0,IFERROR(DATEDIF(DATE(YEAR('Model inputs'!AI117),MONTH('Model inputs'!AI117),1),DATE(2027,9,1),"M"),0)+1) -> 11 | W65: =IF(IF(IF(ISERROR(DATE(2027,10,1)<DATE(YEAR('Model inputs'!AI117),MONTH('Model inputs'!AI117),1)),DATE(2027,10,1)<DATE(YEAR('Model inputs'!AI117),MONTH('Model inputs'!AI117),1),IF(DATE(YEAR('Model inputs'!AI117),MONTH('Model inputs'!AI117),1)="","",DATE(2027,10,1)<DATE(YEAR('Model inputs'!AI117),MONTH('Model inputs'!AI117),1)))="",FALSE,IF(ISERROR(DATE(2027,10,1)<DATE(YEAR('Model inputs'!AI117),MONTH('Model inputs'!AI117),1)),DATE(2027,10,1)<DATE(YEAR('Model inputs'!AI117),MONTH('Model inputs'!AI117),1),IF(DATE(YEAR('Model inputs'!AI117),MONTH('Model inputs'!AI117),1)="","",DATE(2027,10,1)<DATE(YEAR('Model inputs'!AI117),MONTH('Model inputs'!AI117),1)))),0,IFERROR(DATEDIF(DATE(YEAR('Model inputs'!AI117),MONTH('Model inputs'!AI117),1),DATE(2027,10,1),"M"),0)+1) -> 12 | X65: =IF(IF(IF(ISERROR(DATE(2027,11,1)<DATE(YEAR('Model inputs'!AI117),MONTH('Model inputs'!AI117),1)),DATE(2027,11,1)<DATE(YEAR('Model inputs'!AI117),MONTH('Model inputs'!AI117),1),IF(DATE(YEAR('Model inputs'!AI117),MONTH('Model inputs'!AI117),1)="","",DATE(2027,11,1)<DATE(YEAR('Model inputs'!AI117),MONTH('Model inputs'!AI117),1)))="",FALSE,IF(ISERROR(DATE(2027,11,1)<DATE(YEAR('Model inputs'!AI117),MONTH('Model inputs'!AI117),1)),DATE(2027,11,1)<DATE(YEAR('Model inputs'!AI117),MONTH('Model inputs'!AI117),1),IF(DATE(YEAR('Model inputs'!AI117),MONTH('Model inputs'!AI117),1)="","",DATE(2027,11,1)<DATE(YEAR('Model inputs'!AI117),MONTH('Model inputs'!AI117),1)))),0,IFERROR(DATEDIF(DATE(YEAR('Model inputs'!AI117),MONTH('Model inputs'!AI117),1),DATE(2027,11,1),"M"),0)+1) -> 13 | Y65: =IF(IF(IF(ISERROR(DATE(2027,12,1)<DATE(YEAR('Model inputs'!AI117),MONTH('Model inputs'!AI117),1)),DATE(2027,12,1)<DATE(YEAR('Model inputs'!AI117),MONTH('Model inputs'!AI117),1),IF(DATE(YEAR('Model inputs'!AI117),MONTH('Model inputs'!AI117),1)="","",DATE(2027,12,1)<DATE(YEAR('Model inputs'!AI117),MONTH('Model inputs'!AI117),1)))="",FALSE,IF(ISERROR(DATE(2027,12,1)<DATE(YEAR('Model inputs'!AI117),MONTH('Model inputs'!AI117),1)),DATE(2027,12,1)<DATE(YEAR('Model inputs'!AI117),MONTH('Model inputs'!AI117),1),IF(DATE(YEAR('Model inputs'!AI117),MONTH('Model inputs'!AI117),1)="","",DATE(2027,12,1)<DATE(YEAR('Model inputs'!AI117),MONTH('Model inputs'!AI117),1)))),0,IFERROR(DATEDIF(DATE(YEAR('Model inputs'!AI117),MONTH('Model inputs'!AI117),1),DATE(2027,12,1),"M"),0)+1) -> 14 | Z65: =IF(IF(IF(ISERROR(DATE(2028,1,1)<DATE(YEAR('Model inputs'!AI117),MONTH('Model inputs'!AI117),1)),DATE(2028,1,1)<DATE(YEAR('Model inputs'!AI117),MONTH('Model inputs'!AI117),1),IF(DATE(YEAR('Model inputs'!AI117),MONTH('Model inputs'!AI117),1)="","",DATE(2028,1,1)<DATE(YEAR('Model inputs'!AI117),MONTH('Model inputs'!AI117),1)))="",FALSE,IF(ISERROR(DATE(2028,1,1)<DATE(YEAR('Model inputs'!AI117),MONTH('Model inputs'!AI117),1)),DATE(2028,1,1)<DATE(YEAR('Model inputs'!AI117),MONTH('Model inputs'!AI117),1),IF(DATE(YEAR('Model inputs'!AI117),MONTH('Model inputs'!AI117),1)="","",DATE(2028,1,1)<DATE(YEAR('Model inputs'!AI117),MONTH('Model inputs'!AI117),1)))),0,IFERROR(DATEDIF(DATE(YEAR('Model inputs'!AI117),MONTH('Model inputs'!AI117),1),DATE(2028,1,1),"M"),0)+1) -> 15 | AA65: =IF(IF(IF(ISERROR(DATE(2028,2,1)<DATE(YEAR('Model inputs'!AI117),MONTH('Model inputs'!AI117),1)),DATE(2028,2,1)<DATE(YEAR('Model inputs'!AI117),MONTH('Model inputs'!AI117),1),IF(DATE(YEAR('Model inputs'!AI117),MONTH('Model inputs'!AI117),1)="","",DATE(2028,2,1)<DATE(YEAR('Model inputs'!AI117),MONTH('Model inputs'!AI117),1)))="",FALSE,IF(ISERROR(DATE(2028,2,1)<DATE(YEAR('Model inputs'!AI117),MONTH('Model inputs'!AI117),1)),DATE(2028,2,1)<DATE(YEAR('Model inputs'!AI117),MONTH('Model inputs'!AI117),1),IF(DATE(YEAR('Model inputs'!AI117),MONTH('Model inputs'!AI117),1)="","",DATE(2028,2,1)<DATE(YEAR('Model inputs'!AI117),MONTH('Model inputs'!AI117),1)))),0,IFERROR(DATEDIF(DATE(YEAR('Model inputs'!AI117),MONTH('Model inputs'!AI117),1),DATE(2028,2,1),"M"),0)+1) -> 16 | AB65: =IF(IF(IF(ISERROR(DATE(2028,3,1)<DATE(YEAR('Model inputs'!AI117),MONTH('Model inputs'!AI117),1)),DATE(2028,3,1)<DATE(YEAR('Model inputs'!AI117),MONTH('Model inputs'!AI117),1),IF(DATE(YEAR('Model inputs'!AI117),MONTH('Model inputs'!AI117),1)="","",DATE(2028,3,1)<DATE(YEAR('Model inputs'!AI117),MONTH('Model inputs'!AI117),1)))="",FALSE,IF(ISERROR(DATE(2028,3,1)<DATE(YEAR('Model inputs'!AI117),MONTH('Model inputs'!AI117),1)),DATE(2028,3,1)<DATE(YEAR('Model inputs'!AI117),MONTH('Model inputs'!AI117),1),IF(DATE(YEAR('Model inputs'!AI117),MONTH('Model inputs'!AI117),1)="","",DATE(2028,3,1)<DATE(YEAR('Model inputs'!AI117),MONTH('Model inputs'!AI117),1)))),0,IFERROR(DATEDIF(DATE(YEAR('Model inputs'!AI117),MONTH('Model inputs'!AI117),1),DATE(2028,3,1),"M"),0)+1) -> 17 | AC65: =IF(IF(IF(ISERROR(DATE(2028,4,1)<DATE(YEAR('Model inputs'!AI117),MONTH('Model inputs'!AI117),1)),DATE(2028,4,1)<DATE(YEAR('Model inputs'!AI117),MONTH('Model inputs'!AI117),1),IF(DATE(YEAR('Model inputs'!AI117),MONTH('Model inputs'!AI117),1)="","",DATE(2028,4,1)<DATE(YEAR('Model inputs'!AI117),MONTH('Model inputs'!AI117),1)))="",FALSE,IF(ISERROR(DATE(2028,4,1)<DATE(YEAR('Model inputs'!AI117),MONTH('Model inputs'!AI117),1)),DATE(2028,4,1)<DATE(YEAR('Model inputs'!AI117),MONTH('Model inputs'!AI117),1),IF(DATE(YEAR('Model inputs'!AI117),MONTH('Model inputs'!AI117),1)="","",DATE(2028,4,1)<DATE(YEAR('Model inputs'!AI117),MONTH('Model inputs'!AI117),1)))),0,IFERROR(DATEDIF(DATE(YEAR('Model inputs'!AI117),MONTH('Model inputs'!AI117),1),DATE(2028,4,1),"M"),0)+1) -> 18 | AD65: =IF(IF(IF(ISERROR(DATE(2028,5,1)<DATE(YEAR('Model inputs'!AI117),MONTH('Model inputs'!AI117),1)),DATE(2028,5,1)<DATE(YEAR('Model inputs'!AI117),MONTH('Model inputs'!AI117),1),IF(DATE(YEAR('Model inputs'!AI117),MONTH('Model inputs'!AI117),1)="","",DATE(2028,5,1)<DATE(YEAR('Model inputs'!AI117),MONTH('Model inputs'!AI117),1)))="",FALSE,IF(ISERROR(DATE(2028,5,1)<DATE(YEAR('Model inputs'!AI117),MONTH('Model inputs'!AI117),1)),DATE(2028,5,1)<DATE(YEAR('Model inputs'!AI117),MONTH('Model inputs'!AI117),1),IF(DATE(YEAR('Model inputs'!AI117),MONTH('Model inputs'!AI117),1)="","",DATE(2028,5,1)<DATE(YEAR('Model inputs'!AI117),MONTH('Model inputs'!AI117),1)))),0,IFERROR(DATEDIF(DATE(YEAR('Model inputs'!AI117),MONTH('Model inputs'!AI117),1),DATE(2028,5,1),"M"),0)+1) -> 19 | AE65: =IF(IF(IF(ISERROR(DATE(2028,6,1)<DATE(YEAR('Model inputs'!AI117),MONTH('Model inputs'!AI117),1)),DATE(2028,6,1)<DATE(YEAR('Model inputs'!AI117),MONTH('Model inputs'!AI117),1),IF(DATE(YEAR('Model inputs'!AI117),MONTH('Model inputs'!AI117),1)="","",DATE(2028,6,1)<DATE(YEAR('Model inputs'!AI117),MONTH('Model inputs'!AI117),1)))="",FALSE,IF(ISERROR(DATE(2028,6,1)<DATE(YEAR('Model inputs'!AI117),MONTH('Model inputs'!AI117),1)),DATE(2028,6,1)<DATE(YEAR('Model inputs'!AI117),MONTH('Model inputs'!AI117),1),IF(DATE(YEAR('Model inputs'!AI117),MONTH('Model inputs'!AI117),1)="","",DATE(2028,6,1)<DATE(YEAR('Model inputs'!AI117),MONTH('Model inputs'!AI117),1)))),0,IFERROR(DATEDIF(DATE(YEAR('Model inputs'!AI117),MONTH('Model inputs'!AI117),1),DATE(2028,6,1),"M"),0)+1) -> 20 | AF65: =IF(IF(IF(ISERROR(DATE(2028,7,1)<DATE(YEAR('Model inputs'!AI117),MONTH('Model inputs'!AI117),1)),DATE(2028,7,1)<DATE(YEAR('Model inputs'!AI117),MONTH('Model inputs'!AI117),1),IF(DATE(YEAR('Model inputs'!AI117),MONTH('Model inputs'!AI117),1)="","",DATE(2028,7,1)<DATE(YEAR('Model inputs'!AI117),MONTH('Model inputs'!AI117),1)))="",FALSE,IF(ISERROR(DATE(2028,7,1)<DATE(YEAR('Model inputs'!AI117),MONTH('Model inputs'!AI117),1)),DATE(2028,7,1)<DATE(YEAR('Model inputs'!AI117),MONTH('Model inputs'!AI117),1),IF(DATE(YEAR('Model inputs'!AI117),MONTH('Model inputs'!AI117),1)="","",DATE(2028,7,1)<DATE(YEAR('Model inputs'!AI117),MONTH('Model inputs'!AI117),1)))),0,IFERROR(DATEDIF(DATE(YEAR('Model inputs'!AI117),MONTH('Model inputs'!AI117),1),DATE(2028,7,1),"M"),0)+1) -> 21 | AG65: =IF(IF(IF(ISERROR(DATE(2028,8,1)<DATE(YEAR('Model inputs'!AI117),MONTH('Model inputs'!AI117),1)),DATE(2028,8,1)<DATE(YEAR('Model inputs'!AI117),MONTH('Model inputs'!AI117),1),IF(DATE(YEAR('Model inputs'!AI117),MONTH('Model inputs'!AI117),1)="","",DATE(2028,8,1)<DATE(YEAR('Model inputs'!AI117),MONTH('Model inputs'!AI117),1)))="",FALSE,IF(ISERROR(DATE(2028,8,1)<DATE(YEAR('Model inputs'!AI117),MONTH('Model inputs'!AI117),1)),DATE(2028,8,1)<DATE(YEAR('Model inputs'!AI117),MONTH('Model inputs'!AI117),1),IF(DATE(YEAR('Model inputs'!AI117),MONTH('Model inputs'!AI117),1)="","",DATE(2028,8,1)<DATE(YEAR('Model inputs'!AI117),MONTH('Model inputs'!AI117),1)))),0,IFERROR(DATEDIF(DATE(YEAR('Model inputs'!AI117),MONTH('Model inputs'!AI117),1),DATE(2028,8,1),"M"),0)+1) -> 22 | AH65: =IF(IF(IF(ISERROR(DATE(2028,9,1)<DATE(YEAR('Model inputs'!AI117),MONTH('Model inputs'!AI117),1)),DATE(2028,9,1)<DATE(YEAR('Model inputs'!AI117),MONTH('Model inputs'!AI117),1),IF(DATE(YEAR('Model inputs'!AI117),MONTH('Model inputs'!AI117),1)="","",DATE(2028,9,1)<DATE(YEAR('Model inputs'!AI117),MONTH('Model inputs'!AI117),1)))="",FALSE,IF(ISERROR(DATE(2028,9,1)<DATE(YEAR('Model inputs'!AI117),MONTH('Model inputs'!AI117),1)),DATE(2028,9,1)<DATE(YEAR('Model inputs'!AI117),MONTH('Model inputs'!AI117),1),IF(DATE(YEAR('Model inputs'!AI117),MONTH('Model inputs'!AI117),1)="","",DATE(2028,9,1)<DATE(YEAR('Model inputs'!AI117),MONTH('Model inputs'!AI117),1)))),0,IFERROR(DATEDIF(DATE(YEAR('Model inputs'!AI117),MONTH('Model inputs'!AI117),1),DATE(2028,9,1),"M"),0)+1) -> 23
A66: Net cash flow with salary · Main Scenario | B66: 0 | C66: 0 | D66: 0 | E66: 0 | F66: 0 | G66: 0 | H66: 0 | I66: 0 | J66: 0 | K66: ='Model inputs'!K22-'Model inputs'!K110 -> -2170 | L66: ='Model inputs'!L22-'Model inputs'!L110 -> -2267.5 | M66: ='Model inputs'!M22-'Model inputs'!M110 -> -2020.15 | N66: ='Model inputs'!N22-'Model inputs'!N110 -> -2020.15 | O66: ='Model inputs'!O22-'Model inputs'!O110 -> -2020.15 | P66: ='Model inputs'!P22-'Model inputs'!P110 -> -2020.15 | Q66: ='Model inputs'!Q22-'Model inputs'!Q110 -> -2020.15 | R66: ='Model inputs'!R22-'Model inputs'!R110 -> -2020.15 | ... AH66: ='Model inputs'!AH22-'Model inputs'!AH110 -> -2020.15
A67: Net cash flow with salary · Growth · $0.60 | B67: 0 | C67: 0 | D67: 0 | E67: 0 | F67: 0 | G67: 0 | H67: 0 | I67: 0 | J67: 0 | K67: ='Model inputs'!K23-'Model inputs'!K111 -> -2170 | L67: ='Model inputs'!L23-'Model inputs'!L111 -> -2252.875 | M67: ='Model inputs'!M23-'Model inputs'!M111 -> -1902.5687 | N67: ='Model inputs'!N23-'Model inputs'!N111 -> -1835.7109 | O67: ='Model inputs'!O23-'Model inputs'!O111 -> -1752.1387 | P67: ='Model inputs'!P23-'Model inputs'!P111 -> -1647.6733 | Q67: ='Model inputs'!Q23-'Model inputs'!Q111 -> -1517.0917 | R67: ='Model inputs'!R23-'Model inputs'!R111 -> -1353.8646 | ... AH67: ='Model inputs'!AH23-'Model inputs'!AH111 -> 1184.5075
A68: Net cash flow with salary · Base · $0.60 | B68: 0 | C68: 0 | D68: 0 | E68: 0 | F68: 0 | G68: 0 | H68: 0 | I68: 0 | J68: 0 | K68: ='Model inputs'!K24-'Model inputs'!K112 -> -2170 | L68: ='Model inputs'!L24-'Model inputs'!L112 -> -2252.875 | M68: ='Model inputs'!M24-'Model inputs'!M112 -> -1881.85 | N68: ='Model inputs'!N24-'Model inputs'!N112 -> -1881.85 | O68: ='Model inputs'!O24-'Model inputs'!O112 -> -1881.85 | P68: ='Model inputs'!P24-'Model inputs'!P112 -> -1881.85 | Q68: ='Model inputs'!Q24-'Model inputs'!Q112 -> -1881.85 | R68: ='Model inputs'!R24-'Model inputs'!R112 -> -1881.85 | ... AH68: ='Model inputs'!AH24-'Model inputs'!AH112 -> -1881.85
A69: Net cash flow with salary · Growth · $0.34 | B69: 0 | C69: 0 | D69: 0 | E69: 0 | F69: 0 | G69: 0 | H69: 0 | I69: 0 | J69: 0 | K69: ='Model inputs'!K25-'Model inputs'!K113 -> -2170 | L69: ='Model inputs'!L25-'Model inputs'!L113 -> -2267.5 | M69: ='Model inputs'!M25-'Model inputs'!M113 -> -2044.525 | N69: ='Model inputs'!N25-'Model inputs'!N113 -> -2013.1562 | O69: ='Model inputs'!O25-'Model inputs'!O113 -> -1973.9453 | P69: ='Model inputs'!P25-'Model inputs'!P113 -> -1924.9316 | Q69: ='Model inputs'!Q25-'Model inputs'!Q113 -> -1863.6646 | R69: ='Model inputs'!R25-'Model inputs'!R113 -> -1787.0807 | ... AH69: ='Model inputs'!AH25-'Model inputs'!AH113 -> -425.5164
A70: Price per verified fix · Revenue · Main Scenario · Main Scenario | AI70: =0.34 -> 0.34
A71: Price per verified fix · Revenue · Growth · $0.60 · Growth · $0.60 | AI71: =0.6 -> 0.6
A72: Price per verified fix · Revenue · Base · $0.60 · Base · $0.60 | AI72: =0.6 -> 0.6
A73: Price per verified fix · Revenue · Growth · $0.34 · Growth · $0.34 | AI73: ='Model inputs'!AI70 -> 0.34
A74: Starting cash · Main Scenario | AI74: =3000 -> 3000
A75: Starting cash · Growth · $0.60 | AI75: ='Model inputs'!AI74 -> 3000
A76: Starting cash · Base · $0.60 | AI76: ='Model inputs'!AI74 -> 3000
A77: Starting cash · Growth · $0.34 | AI77: ='Model inputs'!AI74 -> 3000
A78: Verified fixes · Main Scenario | B78: 0 | C78: 0 | D78: 0 | E78: 0 | F78: 0 | G78: 0 | H78: 0 | I78: 0 | J78: 0 | K78: ='Model inputs'!K18*'Model inputs'!AI126 -> 0 | L78: ='Model inputs'!L18*'Model inputs'!AI126 -> 750 | M78: ='Model inputs'!M18*'Model inputs'!AI126 -> 750 | N78: ='Model inputs'!N18*'Model inputs'!AI126 -> 750 | O78: ='Model inputs'!O18*'Model inputs'!AI126 -> 750 | P78: ='Model inputs'!P18*'Model inputs'!AI126 -> 750 | Q78: ='Model inputs'!Q18*'Model inputs'!AI126 -> 750 | R78: ='Model inputs'!R18*'Model inputs'!AI126 -> 750 | S78: ='Model inputs'!S18*'Model inputs'!AI126 -> 750 | T78: ='Model inputs'!T18*'Model inputs'!AI126 -> 750 | U78: ='Model inputs'!U18*'Model inputs'!AI126 -> 750 | V78: ='Model inputs'!V18*'Model inputs'!AI126 -> 750 | W78: ='Model inputs'!W18*'Model inputs'!AI126 -> 750 | X78: ='Model inputs'!X18*'Model inputs'!AI126 -> 750 | Y78: ='Model inputs'!Y18*'Model inputs'!AI126 -> 750 | Z78: ='Model inputs'!Z18*'Model inputs'!AI126 -> 750 | AA78: ='Model inputs'!AA18*'Model inputs'!AI126 -> 750 | AB78: ='Model inputs'!AB18*'Model inputs'!AI126 -> 750 | AC78: ='Model inputs'!AC18*'Model inputs'!AI126 -> 750 | AD78: ='Model inputs'!AD18*'Model inputs'!AI126 -> 750 | AE78: ='Model inputs'!AE18*'Model inputs'!AI126 -> 750 | AF78: ='Model inputs'!AF18*'Model inputs'!AI126 -> 750 | AG78: ='Model inputs'!AG18*'Model inputs'!AI126 -> 750 | AH78: ='Model inputs'!AH18*'Model inputs'!AI126 -> 750
A79: Verified fixes · Growth · $0.60 | B79: 0 | C79: 0 | D79: 0 | E79: 0 | F79: 0 | G79: 0 | H79: 0 | I79: 0 | J79: 0 | K79: ='Model inputs'!K19*'Model inputs'!AI127 -> 0 | L79: ='Model inputs'!L19*'Model inputs'!AI127 -> 637.5 | M79: ='Model inputs'!M19*'Model inputs'!AI127 -> 796.875 | N79: ='Model inputs'!N19*'Model inputs'!AI127 -> 996.09375 | O79: ='Model inputs'!O19*'Model inputs'!AI127 -> 1245.1172 | P79: ='Model inputs'!P19*'Model inputs'!AI127 -> 1556.3965 | Q79: ='Model inputs'!Q19*'Model inputs'!AI127 -> 1945.4956 | R79: ='Model inputs'!R19*'Model inputs'!AI127 -> 2431.8695 | S79: ='Model inputs'!S19*'Model inputs'!AI127 -> 3039.8369 | T79: ='Model inputs'!T19*'Model inputs'!AI127 -> 3799.7961 | U79: ='Model inputs'!U19*'Model inputs'!AI127 -> 4749.7451 | V79: ='Model inputs'!V19*'Model inputs'!AI127 -> 5937.1814 | W79: ='Model inputs'!W19*'Model inputs'!AI127 -> 7421.4768 | X79: ='Model inputs'!X19*'Model inputs'!AI127 -> 7421.4768 | Y79: ='Model inputs'!Y19*'Model inputs'!AI127 -> 7421.4768 | Z79: ='Model inputs'!Z19*'Model inputs'!AI127 -> 7421.4768 | AA79: ='Model inputs'!AA19*'Model inputs'!AI127 -> 7421.4768 | AB79: ='Model inputs'!AB19*'Model inputs'!AI127 -> 7421.4768 | AC79: ='Model inputs'!AC19*'Model inputs'!AI127 -> 7421.4768 | AD79: ='Model inputs'!AD19*'Model inputs'!AI127 -> 7421.4768 | AE79: ='Model inputs'!AE19*'Model inputs'!AI127 -> 7421.4768 | AF79: ='Model inputs'!AF19*'Model inputs'!AI127 -> 7421.4768 | AG79: ='Model inputs'!AG19*'Model inputs'!AI127 -> 7421.4768 | AH79: ='Model inputs'!AH19*'Model inputs'!AI127 -> 7421.4768
A80: Verified fixes · Base · $0.60 | B80: 0 | C80: 0 | D80: 0 | E80: 0 | F80: 0 | G80: 0 | H80: 0 | I80: 0 | J80: 0 | K80: ='Model inputs'!K20*'Model inputs'!AI128 -> 0 | L80: ='Model inputs'!L20*'Model inputs'!AI128 -> 637.5 | M80: ='Model inputs'!M20*'Model inputs'!AI128 -> 637.5 | N80: ='Model inputs'!N20*'Model inputs'!AI128 -> 637.5 | O80: ='Model inputs'!O20*'Model inputs'!AI128 -> 637.5 | P80: ='Model inputs'!P20*'Model inputs'!AI128 -> 637.5 | Q80: ='Model inputs'!Q20*'Model inputs'!AI128 -> 637.5 | R80: ='Model inputs'!R20*'Model inputs'!AI128 -> 637.5 | S80: ='Model inputs'!S20*'Model inputs'!AI128 -> 637.5 | T80: ='Model inputs'!T20*'Model inputs'!AI128 -> 637.5 | U80: ='Model inputs'!U20*'Model inputs'!AI128 -> 637.5 | V80: ='Model inputs'!V20*'Model inputs'!AI128 -> 637.5 | W80: ='Model inputs'!W20*'Model inputs'!AI128 -> 637.5 | X80: ='Model inputs'!X20*'Model inputs'!AI128 -> 637.5 | Y80: ='Model inputs'!Y20*'Model inputs'!AI128 -> 637.5 | Z80: ='Model inputs'!Z20*'Model inputs'!AI128 -> 637.5 | AA80: ='Model inputs'!AA20*'Model inputs'!AI128 -> 637.5 | AB80: ='Model inputs'!AB20*'Model inputs'!AI128 -> 637.5 | AC80: ='Model inputs'!AC20*'Model inputs'!AI128 -> 637.5 | AD80: ='Model inputs'!AD20*'Model inputs'!AI128 -> 637.5 | AE80: ='Model inputs'!AE20*'Model inputs'!AI128 -> 637.5 | AF80: ='Model inputs'!AF20*'Model inputs'!AI128 -> 637.5 | AG80: ='Model inputs'!AG20*'Model inputs'!AI128 -> 637.5 | AH80: ='Model inputs'!AH20*'Model inputs'!AI128 -> 637.5
A81: Verified fixes · Growth · $0.34 | B81: 0 | C81: 0 | D81: 0 | E81: 0 | F81: 0 | G81: 0 | H81: 0 | I81: 0 | J81: 0 | K81: ='Model inputs'!K21*'Model inputs'!AI129 -> 0 | L81: ='Model inputs'!L21*'Model inputs'!AI129 -> 750 | M81: ='Model inputs'!M21*'Model inputs'!AI129 -> 937.5 | N81: ='Model inputs'!N21*'Model inputs'!AI129 -> 1171.875 | O81: ='Model inputs'!O21*'Model inputs'!AI129 -> 1464.8438 | P81: ='Model inputs'!P21*'Model inputs'!AI129 -> 1831.0547 | Q81: ='Model inputs'!Q21*'Model inputs'!AI129 -> 2288.8184 | R81: ='Model inputs'!R21*'Model inputs'!AI129 -> 2861.0229 | S81: ='Model inputs'!S21*'Model inputs'!AI129 -> 3576.2787 | T81: ='Model inputs'!T21*'Model inputs'!AI129 -> 4470.3484 | U81: ='Model inputs'!U21*'Model inputs'!AI129 -> 5587.9354 | V81: ='Model inputs'!V21*'Model inputs'!AI129 -> 6984.9193 | W81: ='Model inputs'!W21*'Model inputs'!AI129 -> 8731.1491 | X81: ='Model inputs'!X21*'Model inputs'!AI129 -> 8731.1491 | Y81: ='Model inputs'!Y21*'Model inputs'!AI129 -> 8731.1491 | Z81: ='Model inputs'!Z21*'Model inputs'!AI129 -> 8731.1491 | AA81: ='Model inputs'!AA21*'Model inputs'!AI129 -> 8731.1491 | AB81: ='Model inputs'!AB21*'Model inputs'!AI129 -> 8731.1491 | AC81: ='Model inputs'!AC21*'Model inputs'!AI129 -> 8731.1491 | AD81: ='Model inputs'!AD21*'Model inputs'!AI129 -> 8731.1491 | AE81: ='Model inputs'!AE21*'Model inputs'!AI129 -> 8731.1491 | AF81: ='Model inputs'!AF21*'Model inputs'!AI129 -> 8731.1491 | AG81: ='Model inputs'!AG21*'Model inputs'!AI129 -> 8731.1491 | AH81: ='Model inputs'!AH21*'Model inputs'!AI129 -> 8731.1491
A82: Volume vs $0.34 price · Main Scenario | AI82: =1 -> 1
A83: Volume vs $0.34 price · Growth · $0.60 | AI83: =0.85 -> 0.85
A84: Volume vs $0.34 price · Base · $0.60 | AI84: =0.85 -> 0.85
A85: Volume vs $0.34 price · Growth · $0.34 | AI85: ='Model inputs'!AI82 -> 1
A86: All-in cost per verified fix · Model usage cost · Main Scenario · Main Scenario | AI86: =0.13 -> 0.13
A87: All-in cost per verified fix · Model usage cost · Growth · $0.60 · Growth · $0.60 | AI87: ='Model inputs'!AI86 -> 0.13
A88: All-in cost per verified fix · Model usage cost · Base · $0.60 · Base · $0.60 | AI88: ='Model inputs'!AI86 -> 0.13
A89: All-in cost per verified fix · Model usage cost · Growth · $0.34 · Growth · $0.34 | AI89: ='Model inputs'!AI86 -> 0.13
A90: Fixed costs | B90: =IF('Model inputs'!B42="","",'Model inputs'!B42) -> 0 | C90: =IF('Model inputs'!C42="","",'Model inputs'!C42) -> 0 | D90: =IF('Model inputs'!D42="","",'Model inputs'!D42) -> 0 | E90: =IF('Model inputs'!E42="","",'Model inputs'!E42) -> 0 | F90: =IF('Model inputs'!F42="","",'Model inputs'!F42) -> 0 | G90: =IF('Model inputs'!G42="","",'Model inputs'!G42) -> 0 | H90: =IF('Model inputs'!H42="","",'Model inputs'!H42) -> 0 | I90: =IF('Model inputs'!I42="","",'Model inputs'!I42) -> 0 | ... AH90: =IF('Model inputs'!AH42="","",'Model inputs'!AH42) -> 170
A91: Fixed costs > Accounting, legal & misc | B91: =0 -> 0 | C91: =0 -> 0 | D91: =0 -> 0 | E91: =0 -> 0 | F91: =0 -> 0 | G91: =0 -> 0 | H91: =0 -> 0 | I91: =0 -> 0 | J91: =0 -> 0 | K91: =IF('Model inputs'!AI135="","",'Model inputs'!AI135) -> 50 | L91: =IF('Model inputs'!AI135="","",'Model inputs'!AI135) -> 50 | M91: =IF('Model inputs'!AI135="","",'Model inputs'!AI135) -> 50 | N91: =IF('Model inputs'!AI135="","",'Model inputs'!AI135) -> 50 | O91: =IF('Model inputs'!AI135="","",'Model inputs'!AI135) -> 50 | P91: =IF('Model inputs'!AI135="","",'Model inputs'!AI135) -> 50 | Q91: =IF('Model inputs'!AI135="","",'Model inputs'!AI135) -> 50 | R91: =IF('Model inputs'!AI135="","",'Model inputs'!AI135) -> 50 | S91: =IF('Model inputs'!AI135="","",'Model inputs'!AI135) -> 50 | T91: =IF('Model inputs'!AI135="","",'Model inputs'!AI135) -> 50 | U91: =IF('Model inputs'!AI135="","",'Model inputs'!AI135) -> 50 | V91: =IF('Model inputs'!AI135="","",'Model inputs'!AI135) -> 50 | W91: =IF('Model inputs'!AI135="","",'Model inputs'!AI135) -> 50 | X91: =IF('Model inputs'!AI135="","",'Model inputs'!AI135) -> 50 | Y91: =IF('Model inputs'!AI135="","",'Model inputs'!AI135) -> 50 | Z91: =IF('Model inputs'!AI135="","",'Model inputs'!AI135) -> 50 | AA91: =IF('Model inputs'!AI135="","",'Model inputs'!AI135) -> 50 | AB91: =IF('Model inputs'!AI135="","",'Model inputs'!AI135) -> 50 | AC91: =IF('Model inputs'!AI135="","",'Model inputs'!AI135) -> 50 | AD91: =IF('Model inputs'!AI135="","",'Model inputs'!AI135) -> 50 | AE91: =IF('Model inputs'!AI135="","",'Model inputs'!AI135) -> 50 | AF91: =IF('Model inputs'!AI135="","",'Model inputs'!AI135) -> 50 | AG91: =IF('Model inputs'!AI135="","",'Model inputs'!AI135) -> 50 | AH91: =IF('Model inputs'!AI135="","",'Model inputs'!AI135) -> 50
A92: Fixed costs > Hosting | B92: =0 -> 0 | C92: =0 -> 0 | D92: =0 -> 0 | E92: =0 -> 0 | F92: =0 -> 0 | G92: =0 -> 0 | H92: =0 -> 0 | I92: =0 -> 0 | J92: =0 -> 0 | K92: =IF('Model inputs'!AI136="","",'Model inputs'!AI136) -> 40 | L92: =IF('Model inputs'!AI136="","",'Model inputs'!AI136) -> 40 | M92: =IF('Model inputs'!AI136="","",'Model inputs'!AI136) -> 40 | N92: =IF('Model inputs'!AI136="","",'Model inputs'!AI136) -> 40 | O92: =IF('Model inputs'!AI136="","",'Model inputs'!AI136) -> 40 | P92: =IF('Model inputs'!AI136="","",'Model inputs'!AI136) -> 40 | Q92: =IF('Model inputs'!AI136="","",'Model inputs'!AI136) -> 40 | R92: =IF('Model inputs'!AI136="","",'Model inputs'!AI136) -> 40 | S92: =IF('Model inputs'!AI136="","",'Model inputs'!AI136) -> 40 | T92: =IF('Model inputs'!AI136="","",'Model inputs'!AI136) -> 40 | U92: =IF('Model inputs'!AI136="","",'Model inputs'!AI136) -> 40 | V92: =IF('Model inputs'!AI136="","",'Model inputs'!AI136) -> 40 | W92: =IF('Model inputs'!AI136="","",'Model inputs'!AI136) -> 40 | X92: =IF('Model inputs'!AI136="","",'Model inputs'!AI136) -> 40 | Y92: =IF('Model inputs'!AI136="","",'Model inputs'!AI136) -> 40 | Z92: =IF('Model inputs'!AI136="","",'Model inputs'!AI136) -> 40 | AA92: =IF('Model inputs'!AI136="","",'Model inputs'!AI136) -> 40 | AB92: =IF('Model inputs'!AI136="","",'Model inputs'!AI136) -> 40 | AC92: =IF('Model inputs'!AI136="","",'Model inputs'!AI136) -> 40 | AD92: =IF('Model inputs'!AI136="","",'Model inputs'!AI136) -> 40 | AE92: =IF('Model inputs'!AI136="","",'Model inputs'!AI136) -> 40 | AF92: =IF('Model inputs'!AI136="","",'Model inputs'!AI136) -> 40 | AG92: =IF('Model inputs'!AI136="","",'Model inputs'!AI136) -> 40 | AH92: =IF('Model inputs'!AI136="","",'Model inputs'!AI136) -> 40
A93: Fixed costs > Observability | B93: =0 -> 0 | C93: =0 -> 0 | D93: =0 -> 0 | E93: =0 -> 0 | F93: =0 -> 0 | G93: =0 -> 0 | H93: =0 -> 0 | I93: =0 -> 0 | J93: =0 -> 0 | K93: =IF('Model inputs'!AI137="","",'Model inputs'!AI137) -> 50 | L93: =IF('Model inputs'!AI137="","",'Model inputs'!AI137) -> 50 | M93: =IF('Model inputs'!AI137="","",'Model inputs'!AI137) -> 50 | N93: =IF('Model inputs'!AI137="","",'Model inputs'!AI137) -> 50 | O93: =IF('Model inputs'!AI137="","",'Model inputs'!AI137) -> 50 | P93: =IF('Model inputs'!AI137="","",'Model inputs'!AI137) -> 50 | Q93: =IF('Model inputs'!AI137="","",'Model inputs'!AI137) -> 50 | R93: =IF('Model inputs'!AI137="","",'Model inputs'!AI137) -> 50 | S93: =IF('Model inputs'!AI137="","",'Model inputs'!AI137) -> 50 | T93: =IF('Model inputs'!AI137="","",'Model inputs'!AI137) -> 50 | U93: =IF('Model inputs'!AI137="","",'Model inputs'!AI137) -> 50 | V93: =IF('Model inputs'!AI137="","",'Model inputs'!AI137) -> 50 | W93: =IF('Model inputs'!AI137="","",'Model inputs'!AI137) -> 50 | X93: =IF('Model inputs'!AI137="","",'Model inputs'!AI137) -> 50 | Y93: =IF('Model inputs'!AI137="","",'Model inputs'!AI137) -> 50 | Z93: =IF('Model inputs'!AI137="","",'Model inputs'!AI137) -> 50 | AA93: =IF('Model inputs'!AI137="","",'Model inputs'!AI137) -> 50 | AB93: =IF('Model inputs'!AI137="","",'Model inputs'!AI137) -> 50 | AC93: =IF('Model inputs'!AI137="","",'Model inputs'!AI137) -> 50 | AD93: =IF('Model inputs'!AI137="","",'Model inputs'!AI137) -> 50 | AE93: =IF('Model inputs'!AI137="","",'Model inputs'!AI137) -> 50 | AF93: =IF('Model inputs'!AI137="","",'Model inputs'!AI137) -> 50 | AG93: =IF('Model inputs'!AI137="","",'Model inputs'!AI137) -> 50 | AH93: =IF('Model inputs'!AI137="","",'Model inputs'!AI137) -> 50
A94: Fixed costs > Tooling & misc | B94: =0 -> 0 | C94: =0 -> 0 | D94: =0 -> 0 | E94: =0 -> 0 | F94: =0 -> 0 | G94: =0 -> 0 | H94: =0 -> 0 | I94: =0 -> 0 | J94: =0 -> 0 | K94: =IF('Model inputs'!AI138="","",'Model inputs'!AI138) -> 30 | L94: =IF('Model inputs'!AI138="","",'Model inputs'!AI138) -> 30 | M94: =IF('Model inputs'!AI138="","",'Model inputs'!AI138) -> 30 | N94: =IF('Model inputs'!AI138="","",'Model inputs'!AI138) -> 30 | O94: =IF('Model inputs'!AI138="","",'Model inputs'!AI138) -> 30 | P94: =IF('Model inputs'!AI138="","",'Model inputs'!AI138) -> 30 | Q94: =IF('Model inputs'!AI138="","",'Model inputs'!AI138) -> 30 | R94: =IF('Model inputs'!AI138="","",'Model inputs'!AI138) -> 30 | S94: =IF('Model inputs'!AI138="","",'Model inputs'!AI138) -> 30 | T94: =IF('Model inputs'!AI138="","",'Model inputs'!AI138) -> 30 | U94: =IF('Model inputs'!AI138="","",'Model inputs'!AI138) -> 30 | V94: =IF('Model inputs'!AI138="","",'Model inputs'!AI138) -> 30 | W94: =IF('Model inputs'!AI138="","",'Model inputs'!AI138) -> 30 | X94: =IF('Model inputs'!AI138="","",'Model inputs'!AI138) -> 30 | Y94: =IF('Model inputs'!AI138="","",'Model inputs'!AI138) -> 30 | Z94: =IF('Model inputs'!AI138="","",'Model inputs'!AI138) -> 30 | AA94: =IF('Model inputs'!AI138="","",'Model inputs'!AI138) -> 30 | AB94: =IF('Model inputs'!AI138="","",'Model inputs'!AI138) -> 30 | AC94: =IF('Model inputs'!AI138="","",'Model inputs'!AI138) -> 30 | AD94: =IF('Model inputs'!AI138="","",'Model inputs'!AI138) -> 30 | AE94: =IF('Model inputs'!AI138="","",'Model inputs'!AI138) -> 30 | AF94: =IF('Model inputs'!AI138="","",'Model inputs'!AI138) -> 30 | AG94: =IF('Model inputs'!AI138="","",'Model inputs'!AI138) -> 30 | AH94: =IF('Model inputs'!AI138="","",'Model inputs'!AI138) -> 30
